Day 060/ieee754_multiplier_fsm.v
module ieee754_multiplier_fsm(
    input clk, nreset, start,
    input [31:0] A, B,
    output reg [31:0] result,
    output reg valid, underflow, overflow, zero
);

    //FSM States
    localparam IDLE = 2'd0;
    localparam MULT = 2'd1;
    localparam NORM = 2'd2;
    localparam PACK = 2'd3;

    wire input_zero = (A == 0 | B == 0);
    reg [1:0] state;

    //Unpacking
    reg sign_a, sign_b;
    reg [7:0] exp_a, exp_b;
    reg [23:0] mant_a, mant_b;

    //Multiplication registers
    reg sign_res;
    reg signed [9:0] exp_int;
    reg [47:0] prod_mant;

    //Normalization outputs 
    reg [23:0] prod_norm;
    reg signed [9:0] exp_res;
    reg is_zero;
    always@(posedge clk or negedge nreset) begin
        if(!nreset) begin
            state <= IDLE;
            sign_a <= 0;
            sign_b <= 0;
            exp_a <= 0;
            exp_b <= 0;
            mant_a <= 0;
            mant_b <= 0;
            result <= 0;
            valid <= 0;
            underflow <= 0;
            overflow <= 0;
            zero <= 0;
            sign_res <= 0;
            exp_int <= 0;
            prod_mant <= 0;
            exp_res <= 0;
            prod_norm <= 0;
            is_zero <= 0;
        end
        else begin
            case(state)
                //Wait for start 
                IDLE: begin
                    result <= 0;
                    valid <= 0;
                    underflow <= 0;
                    zero <= 0;

                    if(start) begin
                        sign_a <= A[31];
                        sign_b <= B[31];
                        exp_a <= A[30:23];
                        exp_b <= B[30:23];
                        mant_a <= (A[30:23] == 8'd0) ? {1'd0, A[22:0]} : {1'd1, A[22:0]};
                        mant_b <= (B[30:23] == 8'd0) ? {1'd0, B[22:0]} : {1'd1, B[22:0]};
                        if(A[30:0] == 31'd0 || B[30:0] == 31'd0) begin
                            is_zero <= 1'b1;
                            state <= PACK;
                        end
                        else begin
                            is_zero <= 1'b0;
                            state <= MULT;
                        end
                    end
                end
                MULT: begin
                    prod_mant <= mant_a * mant_b;
                    exp_int <= $signed({2'b0, exp_a}) + $signed({2'b0, exp_b}) - 10'sd127;
                    state <= NORM;
                    sign_res <= sign_a ^ sign_b;
                end
                NORM: begin
                    if(prod_mant == 48'd0) begin 
                        is_zero <= 1;
                        prod_norm <= 0;
                        exp_res <= 0;
                    end
                    else if(prod_mant[47]) begin
                        is_zero <= 0;
                        exp_res <= exp_int + 1'b1;
                        prod_norm <= prod_mant[46:24];
                    end
                    else begin
                        is_zero <= 0;
                        exp_res <= exp_int;
                        prod_norm <= prod_mant[45:23];
                    end
                    state <= PACK;
                end
                PACK: begin
                    valid <= 1'b1;
                    if(is_zero) begin
                        result <= 32'd0;
                        zero <= 1'b1;
                    end
                    else if(exp_res >= 10'sd255) begin
                        result <= {sign_res, 8'hFF, 23'd0};
                        overflow <= 1'b1;
                    end
                    else if(exp_res <= 10'sd0) begin
                        result <= {sign_res, 8'h00, prod_norm[22:0]};
                        underflow <= 1'b1;
                    end
                    else begin
                        result <= {sign_res, exp_res[7:0], prod_norm[22:0]};
                    end
                    state <= IDLE;
                end
                default: state <= IDLE;
            endcase
        end
    end
endmodule

Day 060/tb.v
`timescale 1ns / 1ps

module tb_ieee754_multiplier_fsm();

    parameter CLK_PERIOD = 10;

    reg        clk;
    reg        nreset;
    reg        start;
    reg [31:0] A, B;
    wire [31:0] result;
    wire       valid, underflow, overflow, zero;

    integer errors = 0;

    // Instantiate Multi-Cycle FSM Core
    ieee754_multiplier_fsm uut (
        .clk(clk),
        .nreset(nreset),
        .start(start),
        .A(A),
        .B(B),
        .result(result),
        .valid(valid),
        .underflow(underflow),
        .overflow(overflow),
        .zero(zero)
    );

    // 100 MHz Clock Generator
    always #(CLK_PERIOD / 2) clk = ~clk;

    initial begin
        $dumpfile("dump.vcd");
        $dumpvars(0);

        clk    = 0;
        nreset = 0;
        start  = 0;
        A      = 0;
        B      = 0;

        #(CLK_PERIOD * 2);
        nreset = 1;
        #(CLK_PERIOD);

        $display("\n====================================================");
        $display("   DAY 60: FSM FP32 MULTIPLIER CORE VERIFICATION");
        $display("====================================================\n");

        // -------------------------------------------------------------
        // TEST 1: Standard Multiplication (3.0 * 4.0 = 12.0)
        // -------------------------------------------------------------
        $display("--- TEST 1: Standard Multiplication (3.0 * 4.0 = 12.0) ---");
        @(negedge clk);
        start = 1;
        A = 32'h4040_0000; // +3.0
        B = 32'h4080_0000; // +4.0
        @(negedge clk); start = 0;

        wait(valid); #1;
        if (result === 32'h4140_0000)
            $display("[PASS] 3.0 * 4.0 = 12.0 (Hex: 0x%08h)", result);
        else begin
            $display("[FAIL] Expected 0x41400000, Got 0x%08h", result);
            errors = errors + 1;
        end

        // -------------------------------------------------------------
        // TEST 2: Mantissa Overflow (1.5 * 1.5 = 2.25) -> Bit 47 Shift
        // -------------------------------------------------------------
        $display("\n--- TEST 2: Mantissa Shift Check (1.5 * 1.5 = 2.25) ---");
        @(negedge clk);
        start = 1;
        A = 32'h3FC0_0000; // +1.5
        B = 32'h3FC0_0000; // +1.5
        @(negedge clk); start = 0;

        wait(valid); #1;
        if (result === 32'h4010_0000)
            $display("[PASS] 1.5 * 1.5 = 2.25 (Hex: 0x%08h)", result);
        else begin
            $display("[FAIL] Expected 0x40100000, Got 0x%08h", result);
            errors = errors + 1;
        end

        // -------------------------------------------------------------
        // TEST 3: Zero Input (-0.0 * 25.5 = 0.0) -> Zero Flag
        // -------------------------------------------------------------
        $display("\n--- TEST 3: Zero Operand Multiplication (-0.0 * 25.5 = 0.0) ---");
        @(negedge clk);
        start = 1;
        A = 32'h8000_0000; // -0.0
        B = 32'h41CC_0000; // +25.5
        @(negedge clk); start = 0;

        wait(valid); #1;
        if (result === 32'h0000_0000 && zero)
            $display("[PASS] -0.0 * 25.5 = 0.0 (Hex: 0x%08h, Zero Flag Z=%0d)", result, zero);
        else begin
            $display("[FAIL] Expected 0x00000000 (Z=1), Got 0x%08h (zero=%b)", result, zero);
            errors = errors + 1;
        end

        // -------------------------------------------------------------
        // TEST 4: Exponent Overflow (Max FP32 * 2.0 -> Infinity)
        // -------------------------------------------------------------
        $display("\n--- TEST 4: Exponent Overflow Check ---");
        @(negedge clk);
        start = 1;
        A = 32'h7F7F_FFFF; // ~3.4028235e38
        B = 32'h4000_0000; // +2.0
        @(negedge clk); start = 0;

        wait(valid); #1;
        if (overflow && result[30:23] == 8'hFF)
            $display("[PASS] Overflow detected correctly! (Hex: 0x%08h, Overflow Flag V=%0d)", result, overflow);
        else begin
            $display("[FAIL] Expected Overflow V=1, Got V=%b (Result: 0x%08h)", overflow, result);
            errors = errors + 1;
        end

        // -------------------------------------------------------------
        // TEST 5: Exponent Underflow (Small * Small -> Flush to 0)
        // -------------------------------------------------------------
        $display("\n--- TEST 5: Exponent Underflow Check ---");
        @(negedge clk);
        start = 1;
        A = 32'h00C0_0000; // ~1.5 * 2^-126 (Smallest exponent E=1)
        B = 32'h3F00_0000; // +0.5 (Exponent E=126)
        @(negedge clk); start = 0;

        wait(valid); #1;
        if (underflow)
            $display("[PASS] Underflow detected correctly! (Hex: 0x%08h, Underflow Flag U=%0d)", result, underflow);
        else begin
            $display("[FAIL] Expected Underflow U=1, Got U=%b (Result: 0x%08h)", underflow, result);
            errors = errors + 1;
        end

        // SUMMARY
        $display("\n====================================================");
        if (errors == 0) $display(" ALL MULTI-CYCLE FSM FP32 MULTIPLIER TESTS PASSED!");
        else             $display(" VERIFICATION FAILED WITH %0d ERROR(S)", errors);
        $display("====================================================\n");

        #20;
        $finish;
    end

endmodule

Day 060/dump.vcd
$date
	Sat Aug 08 15:06:37 2026
$end
$version
	Icarus Verilog
$end
$timescale
	1ps
$end
$scope module tb_ieee754_multiplier_fsm $end
$var wire 1 ! zero $end
$var wire 1 " valid $end
$var wire 1 # underflow $end
$var wire 32 $ result [31:0] $end
$var wire 1 % overflow $end
$var parameter 32 & CLK_PERIOD $end
$var reg 32 ' A [31:0] $end
$var reg 32 ( B [31:0] $end
$var reg 1 ) clk $end
$var reg 1 * nreset $end
$var reg 1 + start $end
$var integer 32 , errors [31:0] $end
$scope module uut $end
$var wire 32 - A [31:0] $end
$var wire 32 . B [31:0] $end
$var wire 1 ) clk $end
$var wire 1 / input_zero $end
$var wire 1 * nreset $end
$var wire 1 + start $end
$var parameter 2 0 IDLE $end
$var parameter 2 1 MULT $end
$var parameter 2 2 NORM $end
$var parameter 2 3 PACK $end
$var reg 8 4 exp_a [7:0] $end
$var reg 8 5 exp_b [7:0] $end
$var reg 10 6 exp_int [9:0] $end
$var reg 10 7 exp_res [9:0] $end
$var reg 1 8 is_zero $end
$var reg 24 9 mant_a [23:0] $end
$var reg 24 : mant_b [23:0] $end
$var reg 1 % overflow $end
$var reg 48 ; prod_mant [47:0] $end
$var reg 24 < prod_norm [23:0] $end
$var reg 32 = result [31:0] $end
$var reg 1 > sign_a $end
$var reg 1 ? sign_b $end
$var reg 1 @ sign_res $end
$var reg 2 A state [1:0] $end
$var reg 1 # underflow $end
$var reg 1 " valid $end
$var reg 1 ! zero $end
$upscope $end
$upscope $end
$enddefinitions $end
$comment Show the parameter values. $end
$dumpall
b11 3
b10 2
b1 1
b0 0
b1010 &
$end
#0
$dumpvars
b0 A
0@
0?
0>
b0 =
b0 <
b0 ;
b0 :
b0 9
08
b0 7
b0 6
b0 5
b0 4
1/
b0 .
b0 -
b0 ,
0+
0*
0)
b0 (
b0 '
0%
b0 $
0#
0"
0!
$end
#5000
1)
#10000
0)
#15000
1)
#20000
0)
1*
#25000
1)
#30000
0/
b1000000100000000000000000000000 (
b1000000100000000000000000000000 .
b1000000010000000000000000000000 '
b1000000010000000000000000000000 -
1+
0)
#35000
b1 A
b100000000000000000000000 :
b110000000000000000000000 9
b10000001 5
b10000000 4
1)
#40000
0+
0)
#45000
b10 A
b10000010 6
b11000000000000000000000000000000000000000000000 ;
1)
#50000
0)
#55000
b11 A
b10000000000000000000000 <
b10000010 7
1)
#60000
0)
#65000
b0 A
b1000001010000000000000000000000 $
b1000001010000000000000000000000 =
1"
1)
#70000
b111111110000000000000000000000 (
b111111110000000000000000000000 .
b111111110000000000000000000000 '
b111111110000000000000000000000 -
1+
0)
#75000
b1 A
b110000000000000000000000 :
b1111111 5
b1111111 4
0"
b0 $
b0 =
1)
#80000
0+
0)
#85000
b10 A
b1111111 6
b100100000000000000000000000000000000000000000000 ;
1)
#90000
0)
#95000
b11 A
b100000000000000000000 <
b10000000 7
1)
#100000
0)
#105000
b0 A
b1000000000100000000000000000000 $
b1000000000100000000000000000000 =
1"
1)
#110000
b1000001110011000000000000000000 (
b1000001110011000000000000000000 .
b10000000000000000000000000000000 '
b10000000000000000000000000000000 -
1+
0)
#115000
b11 A
18
b110011000000000000000000 :
b0 9
b10000011 5
b0 4
1>
0"
b0 $
b0 =
1)
#120000
0+
0)
#125000
b0 A
1!
1"
1)
#130000
b1000000000000000000000000000000 (
b1000000000000000000000000000000 .
b1111111011111111111111111111111 '
b1111111011111111111111111111111 -
1+
0)
#135000
b1 A
08
b100000000000000000000000 :
b111111111111111111111111 9
b10000000 5
b11111110 4
0>
0!
0"
1)
#140000
0+
0)
#145000
b10 A
b11111111 6
b11111111111111111111111100000000000000000000000 ;
1)
#150000
0)
#155000
b11 A
b11111111111111111111111 <
b11111111 7
1)
#160000
0)
#165000
b0 A
1%
b1111111100000000000000000000000 $
b1111111100000000000000000000000 =
1"
1)
#170000
b111111000000000000000000000000 (
b111111000000000000000000000000 .
b110000000000000000000000 '
b110000000000000000000000 -
1+
0)
#175000
b1 A
b110000000000000000000000 9
b1111110 5
b1 4
0"
b0 $
b0 =
1)
#180000
0+
0)
#185000
b10 A
b0 6
b11000000000000000000000000000000000000000000000 ;
1)
#190000
0)
#195000
b11 A
b10000000000000000000000 <
b0 7
1)
#200000
0)
#205000
b0 A
1#
b10000000000000000000000 $
b10000000000000000000000 =
1"
1)
#210000
0)
#215000
0#
0"
b0 $
b0 =
1)
