Day 059/ieee754_adder.v
`timescale 1ns / 1ps

module ieee754_adder_fsm(
    input clk, nreset, start,
    input sub, 
    input [31:0] A, B,
    output reg [31:0] result,
    output reg valid, overflow, underflow, zero
);

    // FSM States
    localparam IDLE    = 3'd0;
    localparam ALIGN   = 3'd1;
    localparam ADD_SUB = 3'd2;
    localparam NORM    = 3'd3;
    localparam PACK    = 3'd4;

    reg [2:0] state;

    // Unpacked regs
    reg sign_a, sign_b_eff;
    reg [7:0] exp_a, exp_b;
    reg [23:0] mant_a, mant_b; // Including explicit leading bit

    // Alignment and Data path regs
    reg [7:0] exp_common;
    reg [24:0] aligned_a, aligned_b;
    reg [24:0] sum_mant;
    reg sign_res;

    // Normalized regs
    // CHANGE 1: Declared as 10-bit SIGNED register to handle negative exponent underflow
    reg signed [9:0] exp_res; 
    reg [23:0] norm_mant;

    integer i;
    reg [4:0] lzc;
    reg is_zero;

    always @(posedge clk or negedge nreset) begin
        if(!nreset) begin
            state       <= IDLE;
            valid       <= 0;
            result      <= 0;
            overflow    <= 0;
            underflow   <= 0;
            zero        <= 0;
            sign_a      <= 0;
            sign_b_eff  <= 0;
            exp_a       <= 0;
            exp_b       <= 0;
            mant_a      <= 0;
            mant_b      <= 0;
            exp_common  <= 0;
            aligned_a   <= 0;
            aligned_b   <= 0;
            sum_mant    <= 0;
            sign_res    <= 0;
            exp_res     <= 0;
            norm_mant   <= 0;
            is_zero     <= 0;
        end
        else begin
            case(state)
                // Wait for Start Signal
                IDLE: begin
                    valid     <= 0;
                    overflow  <= 0;
                    underflow <= 0;
                    zero      <= 0;

                    if(start) begin
                        sign_a     <= A[31];
                        sign_b_eff <= (sub) ? ~B[31] : B[31];
                        exp_a      <= A[30:23];
                        exp_b      <= B[30:23];
                        mant_a     <= (A[30:23] == 8'd0) ? {1'd0, A[22:0]} : {1'b1, A[22:0]};
                        mant_b     <= (B[30:23] == 8'd0) ? {1'd0, B[22:0]} : {1'b1, B[22:0]};
                        state      <= ALIGN;
                    end
                end

                // Align operands
                ALIGN: begin
                    if(exp_a >= exp_b) begin
                        exp_common <= exp_a;
                        aligned_a  <= {1'b0, mant_a};
                        aligned_b  <= {1'b0, mant_b} >> (exp_a - exp_b);
                    end
                    else begin
                        exp_common <= exp_b;
                        aligned_a  <= {1'b0, mant_a} >> (exp_b - exp_a);
                        aligned_b  <= {1'b0, mant_b};
                    end
                    state <= ADD_SUB;
                end

                // Execute effective addition / subtraction
                ADD_SUB: begin
                    if(sign_a == sign_b_eff) begin
                        sum_mant <= aligned_a + aligned_b;
                        sign_res <= sign_a;
                    end
                    else begin
                        if(aligned_a >= aligned_b) begin
                            sum_mant <= aligned_a - aligned_b;
                            sign_res <= sign_a;
                        end
                        else begin
                            sum_mant <= aligned_b - aligned_a;
                            sign_res <= sign_b_eff;
                        end
                    end
                    state <= NORM;
                end

                // Normalization State
                NORM: begin
                    if(sum_mant == 25'd0) begin // Exact Zero result
                        is_zero   <= 1'b1;
                        norm_mant <= 24'd0;
                        exp_res   <= 10'sd0;
                    end
                    else if(sum_mant[24]) begin // Carry-Out Overflow (Shift right, exp + 1)
                        is_zero   <= 1'b0;
                        norm_mant <= sum_mant[24:1];
                        exp_res   <= $signed({2'b0, exp_common}) + 10'sd1;
                    end
                    else if(sum_mant[23]) begin // Already Normalized (1.x format)
                        is_zero   <= 1'b0;
                        norm_mant <= sum_mant[23:0];
                        exp_res   <= $signed({2'b0, exp_common});
                    end
                    else begin // Normalization Left Shift (Underflow Check)
                        is_zero <= 1'b0;
                        lzc = 0;
                        for(i = 22; i >= 0; i = i-1) begin
                            if(sum_mant[i] && lzc == 0) begin
                                lzc = 23 - i;
                            end
                        end
                        norm_mant <= sum_mant[23:0] << lzc;
                        
                        // CHANGE 2: Explicit signed calculation to handle negative exponents
                        exp_res   <= $signed({2'b0, exp_common}) - $signed({5'b0, lzc});
                    end
                    state <= PACK;
                end

                // Pack Result & Assert Exception Flags
                PACK: begin
                    valid <= 1'b1;
                    if(is_zero) begin
                        result <= 32'd0;
                        zero   <= 1'b1;
                    end
                    // CHANGE 3: Updated to 10-bit signed boundary evaluations
                    else if(exp_res >= 10'sd255) begin // Exponent Overflow / Infinity
                        result   <= {sign_res, 8'hFF, 23'd0}; 
                        overflow <= 1'b1;
                    end
                    else if(exp_res <= 10'sd0) begin // Exponent Underflow
                        result    <= {sign_res, 8'h00, norm_mant[22:0]};
                        underflow <= 1'b1;
                    end
                    else begin
                        result <= {sign_res, exp_res[7:0], norm_mant[22:0]};
                    end
                    state <= IDLE;
                end

                default: state <= IDLE;
            endcase
        end
    end
endmodule

Day 059/tb.v
`timescale 1ns / 1ps

module tb_ieee754_adder_fsm();

    parameter CLK_PERIOD = 10;

    reg        clk;
    reg        nreset;
    reg        start;
    reg        sub;
    wire       valid;
    reg [31:0] A, B;
    wire [31:0] result;
    wire       overflow, underflow, zero;

    integer errors = 0;

    // Instantiate FSM Core
    ieee754_adder_fsm uut (
        .clk(clk),
        .nreset(nreset),
        .start(start),
        .sub(sub),
        .valid(valid),
        .A(A),
        .B(B),
        .result(result),
        .overflow(overflow),
        .underflow(underflow),
        .zero(zero)
    );

    // 100 MHz Clock Generator
    always #(CLK_PERIOD / 2) clk = ~clk;

    initial begin
        $dumpfile("dump.vcd");
        $dumpvars(0);

        clk    = 0;
        nreset = 0;
        start  = 0;
        sub    = 0;
        A      = 0;
        B      = 0;

        #(CLK_PERIOD * 2);
        nreset = 1;
        #(CLK_PERIOD);

        $display("\n====================================================");
        $display("   DAY 59: FSM FP32 ADDER CORE FULL VERIFICATION");
        $display("====================================================\n");

        // -------------------------------------------------------------
        // TEST 1: Standard Addition (16.0 + 6.0 = 22.0)
        // -------------------------------------------------------------
        $display("--- TEST 1: Addition (16.0 + 6.0 = 22.0) ---");
        @(negedge clk);
        start = 1; sub = 0;
        A = 32'h4180_0000; // +16.0
        B = 32'h40C0_0000; // +6.0
        @(negedge clk); start = 0;

        wait(valid); #1;
        if (result === 32'h41B0_0000)
            $display("[PASS] 16.0 + 6.0 = 22.0 (Hex: 0x%08h)", result);
        else begin
            $display("[FAIL] Expected 0x41B00000, Got 0x%08h", result);
            errors = errors + 1;
        end

        // -------------------------------------------------------------
        // TEST 2: Exact Zero Result (20.0 - 20.0 = 0.0) -> Tests Zero Flag
        // -------------------------------------------------------------
        $display("\n--- TEST 2: Subtraction to Zero (20.0 - 20.0 = 0.0) ---");
        @(negedge clk);
        start = 1; sub = 1; // Perform A - B
        A = 32'h41A0_0000; // +20.0
        B = 32'h41A0_0000; // +20.0
        @(negedge clk); start = 0;

        wait(valid); #1;
        if (result === 32'h0000_0000 && zero)
            $display("[PASS] 20.0 - 20.0 = 0.0 (Hex: 0x%08h, Zero Flag Z=%0d)", result, zero);
        else begin
            $display("[FAIL] Expected 0x00000000, Got 0x%08h (zero=%b)", result, zero);
            errors = errors + 1;
        end

        // -------------------------------------------------------------
        // TEST 3: Catastrophic Cancellation (1.5 - 1.25 = 0.25) -> LZC Check
        // -------------------------------------------------------------
        $display("\n--- TEST 3: Normalization Check (1.5 - 1.25 = 0.25) ---");
        @(negedge clk);
        start = 1; sub = 0;
        A = 32'h3FC0_0000; // +1.5
        B = 32'hBFA0_0000; // -1.25
        @(negedge clk); start = 0;

        wait(valid); #1;
        if (result === 32'h3E80_0000)
            $display("[PASS] 1.5 + (-1.25) = 0.25 (Hex: 0x%08h)", result);
        else begin
            $display("[FAIL] Expected 0x3E800000 (0.25), Got 0x%08h", result);
            errors = errors + 1;
        end

        // -------------------------------------------------------------
        // TEST 4: Overflow Check (Max Float + Max Float -> Infinity)
        // -------------------------------------------------------------
        $display("\n--- TEST 4: Overflow Check (Max FP32 + Max FP32) ---");
        @(negedge clk);
        start = 1; sub = 0;
        A = 32'h7F7F_FFFF; // ~3.4028235e38 (Max Normal FP32)
        B = 32'h7F7F_FFFF; // ~3.4028235e38
        @(negedge clk); start = 0;

        wait(valid); #1;
        if (overflow)
            $display("[PASS] Overflow detected correctly! (Hex: 0x%08h, Overflow Flag V=%0d)", result, overflow);
        else begin
            $display("[FAIL] Expected Overflow flag V=1, Got V=%b (Result: 0x%08h)", overflow, result);
            errors = errors + 1;
        end

        // -------------------------------------------------------------
        // TEST 5: Underflow Check (Exponent underflows past E=1)
        // -------------------------------------------------------------
        $display("\n--- TEST 5: Underflow Check (Min Normal Subtraction) ---");
        @(negedge clk);
        start = 1; sub = 1;
        A = 32'h00C0_0000; // 1.5 * 2^-126 (Exp = 1)
        B = 32'h00B8_0000; // 1.4375 * 2^-126 (Exp = 1)
        @(negedge clk); start = 0;

        wait(valid); #1;
        if (underflow)
            $display("[PASS] Underflow detected correctly! (Hex: 0x%08h, Underflow Flag U=%0d)", result, underflow);
        else begin
            $display("[FAIL] Expected Underflow flag U=1, Got U=%b (Result: 0x%08h)", underflow, result);
            errors = errors + 1;
        end

        // SUMMARY
        $display("\n====================================================");
        if (errors == 0) $display(" ALL MULTI-CYCLE FSM FP32 ADDER TESTS PASSED!");
        else             $display(" VERIFICATION FAILED WITH %0d ERROR(S)", errors);
        $display("====================================================\n");
        #20;
        $finish;
    end

endmodule

Day 059/dump.vcd
$date
	Fri Aug 07 16:32:45 2026
$end
$version
	Icarus Verilog
$end
$timescale
	1ps
$end
$scope module tb_ieee754_adder_fsm $end
$var wire 1 ! zero $end
$var wire 1 " valid $end
$var wire 1 # underflow $end
$var wire 32 $ result [31:0] $end
$var wire 1 % overflow $end
$var parameter 32 & CLK_PERIOD $end
$var reg 32 ' A [31:0] $end
$var reg 32 ( B [31:0] $end
$var reg 1 ) clk $end
$var reg 1 * nreset $end
$var reg 1 + start $end
$var reg 1 , sub $end
$var integer 32 - errors [31:0] $end
$scope module uut $end
$var wire 32 . A [31:0] $end
$var wire 32 / B [31:0] $end
$var wire 1 ) clk $end
$var wire 1 * nreset $end
$var wire 1 + start $end
$var wire 1 , sub $end
$var parameter 3 0 ADD_SUB $end
$var parameter 3 1 ALIGN $end
$var parameter 3 2 IDLE $end
$var parameter 3 3 NORM $end
$var parameter 3 4 PACK $end
$var reg 25 5 aligned_a [24:0] $end
$var reg 25 6 aligned_b [24:0] $end
$var reg 8 7 exp_a [7:0] $end
$var reg 8 8 exp_b [7:0] $end
$var reg 8 9 exp_common [7:0] $end
$var reg 10 : exp_res [9:0] $end
$var reg 1 ; is_zero $end
$var reg 5 < lzc [4:0] $end
$var reg 24 = mant_a [23:0] $end
$var reg 24 > mant_b [23:0] $end
$var reg 24 ? norm_mant [23:0] $end
$var reg 1 % overflow $end
$var reg 32 @ result [31:0] $end
$var reg 1 A sign_a $end
$var reg 1 B sign_b_eff $end
$var reg 1 C sign_res $end
$var reg 3 D state [2:0] $end
$var reg 25 E sum_mant [24:0] $end
$var reg 1 # underflow $end
$var reg 1 " valid $end
$var reg 1 ! zero $end
$var integer 32 F i [31:0] $end
$upscope $end
$upscope $end
$enddefinitions $end
$comment Show the parameter values. $end
$dumpall
b100 4
b11 3
b0 2
b1 1
b10 0
b1010 &
$end
#0
$dumpvars
bx F
b0 E
b0 D
0C
0B
0A
b0 @
b0 ?
b0 >
b0 =
bx <
0;
b0 :
b0 9
b0 8
b0 7
b0 6
b0 5
b0 /
b0 .
b0 -
0,
0+
0*
0)
b0 (
b0 '
0%
b0 $
0#
0"
0!
$end
#5000
1)
#10000
0)
#15000
1)
#20000
0)
1*
#25000
1)
#30000
b1000000110000000000000000000000 (
b1000000110000000000000000000000 /
b1000001100000000000000000000000 '
b1000001100000000000000000000000 .
1+
0)
#35000
b1 D
b110000000000000000000000 >
b100000000000000000000000 =
b10000001 8
b10000011 7
1)
#40000
0+
0)
#45000
b10 D
b1100000000000000000000 6
b100000000000000000000000 5
b10000011 9
1)
#50000
0)
#55000
b11 D
b101100000000000000000000 E
1)
#60000
0)
#65000
b100 D
b10000011 :
b101100000000000000000000 ?
1)
#70000
0)
#75000
b0 D
b1000001101100000000000000000000 $
b1000001101100000000000000000000 @
1"
1)
#80000
b1000001101000000000000000000000 (
b1000001101000000000000000000000 /
b1000001101000000000000000000000 '
b1000001101000000000000000000000 .
1,
1+
0)
#85000
b1 D
b101000000000000000000000 >
b101000000000000000000000 =
b10000011 8
1B
0"
1)
#90000
0+
0)
#95000
b10 D
b101000000000000000000000 6
b101000000000000000000000 5
1)
#100000
0)
#105000
b11 D
b0 E
1)
#110000
0)
#115000
b100 D
b0 :
b0 ?
1;
1)
#120000
0)
#125000
b0 D
1!
b0 $
b0 @
1"
1)
#130000
b10111111101000000000000000000000 (
b10111111101000000000000000000000 /
b111111110000000000000000000000 '
b111111110000000000000000000000 .
0,
1+
0)
#135000
b1 D
b110000000000000000000000 =
b1111111 8
b1111111 7
0!
0"
1)
#140000
0+
0)
#145000
b10 D
b110000000000000000000000 5
b1111111 9
1)
#150000
0)
#155000
b11 D
b1000000000000000000000 E
1)
#160000
0)
#165000
b100 D
b1111101 :
b100000000000000000000000 ?
0;
b11111111111111111111111111111111 F
b10 <
1)
#170000
0)
#175000
b0 D
b111110100000000000000000000000 $
b111110100000000000000000000000 @
1"
1)
#180000
b1111111011111111111111111111111 (
b1111111011111111111111111111111 /
b1111111011111111111111111111111 '
b1111111011111111111111111111111 .
1+
0)
#185000
b1 D
b111111111111111111111111 >
b111111111111111111111111 =
b11111110 8
b11111110 7
0B
0"
1)
#190000
0+
0)
#195000
b10 D
b111111111111111111111111 6
b111111111111111111111111 5
b11111110 9
1)
#200000
0)
#205000
b11 D
b1111111111111111111111110 E
1)
#210000
0)
#215000
b100 D
b11111111 :
b111111111111111111111111 ?
1)
#220000
0)
#225000
b0 D
1%
b1111111100000000000000000000000 $
b1111111100000000000000000000000 @
1"
1)
#230000
b101110000000000000000000 (
b101110000000000000000000 /
b110000000000000000000000 '
b110000000000000000000000 .
1,
1+
0)
#235000
b1 D
b101110000000000000000000 >
b110000000000000000000000 =
b1 8
b1 7
1B
0%
0"
1)
#240000
0+
0)
#245000
b10 D
b101110000000000000000000 6
b110000000000000000000000 5
b1 9
1)
#250000
0)
#255000
b11 D
b10000000000000000000 E
1)
#260000
0)
#265000
b100 D
b1111111101 :
b100000000000000000000000 ?
b11111111111111111111111111111111 F
b100 <
1)
#270000
0)
#275000
b0 D
1#
b0 $
b0 @
1"
1)
#280000
0)
#285000
0#
0"
1)
