Day 080/riscv_if_stage.v
module riscv_if_stage #(
    parameter [31:0] RESET_VECTOR = 32'h0000_0000
)(
    input clk, nreset,

    //Hazard & control inputs from EX/Hazard Unit
    input stall_if, // 1 = FREEZE PC and IF/ID Pipeline register
    input flush_if, // 1 = Insert NOP into IF/ID reg
    input pc_src_ex,// Select line for mux: 0 = PC+4, 1 = Branch/Jump target
    input [31:0] pc_target_ex, // Target address(For jump)

    //Memory Interface(To Instruction memory)
    output [31:0] imem_addr,
    input [31:0] imem_rdata,

    //IF/ID pipeline register outputs(Driven to ID Stage)
    output reg [31:0] if_id_pc, if_id_pc_plus_4,
    output reg [31:0] if_id_instr
);
    // RV32I NOP Encoding: addi x0, x0, 0
    localparam [31:0] NOP_INSTRUCTION = 32'h0000_0000;

    //Internal Regs
    reg [31:0] pc_reg, pc_next;
    wire [31:0] pc_plus_4;

    assign pc_plus_4 = pc_reg + 32'd4;
    assign imem_addr = pc_reg;

    //MUX for next PC
    always@(*) begin
        if(pc_src_ex) pc_next = pc_target_ex;
        else pc_next = pc_plus_4;
    end

    //PC reg
    always@(posedge clk or negedge nreset) begin
        if(!nreset) pc_reg <= RESET_VECTOR;
        else if(!stall_if || pc_src_ex) pc_reg <= pc_next;
    end

    always@(posedge clk or negedge nreset) begin
        if(!nreset) begin
            if_id_pc <= RESET_VECTOR;
            if_id_pc_plus_4 <= RESET_VECTOR + 32'd4;
            if_id_instr <= NOP_INSTRUCTION;
        end
        else if(flush_if) begin
            if_id_pc <= 32'd0;
            if_id_pc_plus_4 <= 32'd0;
            if_id_instr <= NOP_INSTRUCTION;
        end
        else if(!stall_if) begin
            if_id_pc <= pc_reg;
            if_id_pc_plus_4 <= pc_plus_4;
            if_id_instr <= imem_rdata;  
        end
    end 
endmodule

Day 080/instruction_mem.v
module instruction_mem #(
    parameter MEM_DEPTH = 64,
    parameter MEM_FILE = "program.mem"
)(
    input [31:0] addr,
    output [31:0] rdata
);
    localparam ADDR_WIDTH = $clog2(MEM_DEPTH);

    reg [31:0] rom [0: MEM_DEPTH-1];
    assign rdata = rom[addr[ADDR_WIDTH+1:2]];

    integer i;

    initial begin
        for(i=0; i < MEM_DEPTH; i = i+1) begin
            rom[i] = 32'h0000_0013;
        end

        if(MEM_FILE != "") begin
            $readmemh(MEM_FILE, rom);
        end
    end
endmodule

Day 080/tb.v
`timescale 1ns / 1ps

module tb_riscv_if_stage();

    parameter CLK_PERIOD = 10; // 100 MHz clock

    reg         clk;
    reg         nreset;

    // Control Inputs
    reg         stall_if;
    reg         flush_if;
    reg         pc_src_ex;
    reg  [31:0] pc_target_ex;

    // Memory & Pipeline Interconnects
    wire [31:0] imem_addr;
    wire [31:0] imem_rdata;
    wire [31:0] if_id_pc;
    wire [31:0] if_id_pc_plus_4;
    wire [31:0] if_id_instr;

    integer errors = 0;

    // Instantiate Instruction Memory
    instruction_mem #(
        .MEM_DEPTH(64)
    ) u_imem (
        .addr(imem_addr),
        .rdata(imem_rdata)
    );

    // Instantiate UUT
    riscv_if_stage #(
        .RESET_VECTOR(32'h0000_0000)
    ) uut (
        .clk(clk),
        .nreset(nreset),
        .stall_if(stall_if),
        .flush_if(flush_if),
        .pc_src_ex(pc_src_ex),
        .pc_target_ex(pc_target_ex),
        .imem_addr(imem_addr),
        .imem_rdata(imem_rdata),
        .if_id_pc(if_id_pc),
        .if_id_pc_plus_4(if_id_pc_plus_4),
        .if_id_instr(if_id_instr)
    );

    // Clock Generation
    always #(CLK_PERIOD / 2) clk = ~clk;

    initial begin
        $dumpfile("dump.vcd");
        $dumpvars(0, tb_riscv_if_stage);

        clk          = 0;
        nreset        = 0;
        stall_if     = 0;
        flush_if     = 0;
        pc_src_ex    = 0;
        pc_target_ex = 32'd0;

        #(CLK_PERIOD * 3);
        @(negedge clk);
        nreset = 1;

        $display("\n=======================================================================================================");
        $display("                   DAY 80: RISC-V INSTRUCTION FETCH (IF) STAGE VERIFICATION                            ");
        $display("=======================================================================================================");

        // --- TEST 1: Normal Sequential Fetch (PC + 4 Progression) ---
        $display("\n--- TEST 1: Sequential Instruction Fetching ---");
        @(posedge clk); // Allow pipeline to latch instruction at PC = 0x00
        #(1);
        if (if_id_pc !== 32'h0000_0000 || if_id_instr !== 32'h00500093) begin
            $display("[FAIL] Cycle 1 Mismatch! PC=0x%08h, Instr=0x%08h", if_id_pc, if_id_instr);
            errors = errors + 1;
        end else begin
            $display("[PASS] Cycle 1: PC=0x00, Fetched: 0x%08h", if_id_instr);
        end

        @(posedge clk); // PC = 0x04
        #(1);
        if (if_id_pc !== 32'h0000_0004 || if_id_instr !== 32'h00A00113) begin
            $display("[FAIL] Cycle 2 Mismatch! PC=0x%08h, Instr=0x%08h", if_id_pc, if_id_instr);
            errors = errors + 1;
        end else begin
            $display("[PASS] Cycle 2: PC=0x04, Fetched: 0x%08h", if_id_instr);
        end

        @(posedge clk); // PC = 0x08
        #(1);
        if (if_id_pc !== 32'h0000_0008 || if_id_instr !== 32'h002081B3) begin
            $display("[FAIL] Cycle 3 Mismatch! PC=0x%08h, Instr=0x%08h", if_id_pc, if_id_instr);
            errors = errors + 1;
        end else begin
            $display("[PASS] Cycle 3: PC=0x08, Fetched: 0x%08h", if_id_instr);
        end

        // --- TEST 2: Pipeline Stall Assertion (Load-Use Dependency Emulation) ---
        $display("\n--- TEST 2: Pipeline Stall Verification (Freeze PC and IF/ID) ---");
        @(negedge clk);
        stall_if = 1'b1; // Stall pipeline while fetching PC = 0x0C

        // Hold stall for 2 cycles
        repeat (2) begin
            @(posedge clk);
            #(1);
            if (if_id_pc !== 32'h0000_0008 || if_id_instr !== 32'h002081B3) begin
                $display("[FAIL] Pipeline drifted during stall! PC=0x%08h", if_id_pc);
                errors = errors + 1;
            end
        end
        $display("[PASS] Pipeline correctly held static across 2 stall cycles!");

        @(negedge clk);
        stall_if = 1'b0; // Release stall

        @(posedge clk);
        #(1);
        if (if_id_pc !== 32'h0000_000C || if_id_instr !== 32'h40110233) begin
            $display("[FAIL] Failed to resume fetch after stall! PC=0x%08h", if_id_pc);
            errors = errors + 1;
        end else begin
            $display("[PASS] Pipeline cleanly resumed: PC=0x0C, Fetched: 0x%08h", if_id_instr);
        end

        // --- TEST 3: Branch / Jump Redirection with Flush ---
        $display("\n--- TEST 3: Branch Redirection & Pipeline Flush ---");
        @(negedge clk);
        pc_src_ex    = 1'b1;
        pc_target_ex = 32'h0000_0020; // Jump to target address 0x20
        flush_if     = 1'b1;          // Invalidate instruction currently entering IF/ID

        @(posedge clk);
        #(1);
        // The flushed cycle must present a NOP to the ID stage
        if (if_id_instr !== 32'h0000_0000) begin
            $display("[FAIL] Flush failed to inject NOP bubble! Got: 0x%08h", if_id_instr);
            errors = errors + 1;
        end else begin
            $display("[PASS] Flush cycle: NOP (0x00000000) injected into IF/ID register!");
        end

        @(negedge clk);
        pc_src_ex = 1'b0;
        flush_if  = 1'b0;

        @(posedge clk);
        #(1);
        // Verify target address instruction is captured in IF/ID
        if (if_id_pc !== 32'h0000_0020 || if_id_instr !== 32'h11111113) begin
            $display("[FAIL] Branch target fetch failed! PC=0x%08h, Got: 0x%08h (Expected 0x11111113)",
                     if_id_pc, if_id_instr);
            errors = errors + 1;
        end else begin
            $display("[PASS] Branch target arrived: PC=0x20, Fetched Target Instr: 0x%08h", if_id_instr);
        end

        // --- TEST 4: Flush Priority Over Stall ---
        $display("\n--- TEST 4: Flush Priority Over Stall Conflict ---");
        @(negedge clk);
        stall_if     = 1'b1;
        flush_if     = 1'b1;
        pc_src_ex    = 1'b1;
        pc_target_ex = 32'h0000_0020;

        @(posedge clk);
        #(1);
        if (if_id_instr !== 32'h0000_0000) begin
            $display("[FAIL] Flush did not inject NOP bubble! Got: 0x%08h", if_id_instr);
            errors = errors + 1;
        end else if (imem_addr !== 32'h0000_0020) begin
            $display("[FAIL] PC did not jump to branch target under stall! PC=0x%08h", imem_addr);
            errors = errors + 1;
        end else begin
            $display("[PASS] Flush successfully overrode stall: NOP injected AND PC redirected to 0x20!");
        end

        #(CLK_PERIOD * 5);
        $display("\n=======================================================================================================");
        if (errors == 0)
            $display("   DAY 80 RISC-V IF STAGE VERIFICATION SUCCESSFUL");
        else
            $display("   VERIFICATION FAILED WITH %0d ERROR(S)!", errors);
        $display("=======================================================================================================\n");

        $finish;
    end

endmodule

Day 080/dump.vcd
$date
	Sat Sep 26 13:20:08 2026
$end
$version
	Icarus Verilog
$end
$timescale
	1ps
$end
$scope module tb_riscv_if_stage $end
$var wire 32 ! imem_rdata [31:0] $end
$var wire 32 " imem_addr [31:0] $end
$var wire 32 # if_id_pc_plus_4 [31:0] $end
$var wire 32 $ if_id_pc [31:0] $end
$var wire 32 % if_id_instr [31:0] $end
$var parameter 32 & CLK_PERIOD $end
$var reg 1 ' clk $end
$var reg 1 ( flush_if $end
$var reg 1 ) nreset $end
$var reg 1 * pc_src_ex $end
$var reg 32 + pc_target_ex [31:0] $end
$var reg 1 , stall_if $end
$var integer 32 - errors [31:0] $end
$scope module u_imem $end
$var wire 32 . rdata [31:0] $end
$var wire 32 / addr [31:0] $end
$var parameter 32 0 ADDR_WIDTH $end
$var parameter 32 1 MEM_DEPTH $end
$var parameter 88 2 MEM_FILE $end
$var integer 32 3 i [31:0] $end
$upscope $end
$scope module uut $end
$var wire 1 ' clk $end
$var wire 1 ( flush_if $end
$var wire 32 4 imem_addr [31:0] $end
$var wire 32 5 imem_rdata [31:0] $end
$var wire 1 ) nreset $end
$var wire 1 * pc_src_ex $end
$var wire 32 6 pc_target_ex [31:0] $end
$var wire 1 , stall_if $end
$var wire 32 7 pc_plus_4 [31:0] $end
$var parameter 32 8 NOP_INSTRUCTION $end
$var parameter 32 9 RESET_VECTOR $end
$var reg 32 : if_id_instr [31:0] $end
$var reg 32 ; if_id_pc [31:0] $end
$var reg 32 < if_id_pc_plus_4 [31:0] $end
$var reg 32 = pc_next [31:0] $end
$var reg 32 > pc_reg [31:0] $end
$upscope $end
$upscope $end
$enddefinitions $end
$comment Show the parameter values. $end
$dumpall
b0 9
b0 8
b111000001110010011011110110011101110010011000010110110100101110011011010110010101101101 2
b1000000 1
b110 0
b1010 &
$end
#0
$dumpvars
b0 >
b100 =
b100 <
b0 ;
b0 :
b100 7
b0 6
b10100000000000010010011 5
b0 4
b1000000 3
b0 /
b10100000000000010010011 .
b0 -
0,
b0 +
0*
0)
0(
0'
b0 %
b0 $
b100 #
b0 "
b10100000000000010010011 !
$end
#5000
1'
#10000
0'
#15000
1'
#20000
0'
#25000
1'
#30000
1)
0'
#35000
b1000 =
b101000000000000100010011 !
b101000000000000100010011 .
b101000000000000100010011 5
b1000 7
b100 "
b100 /
b100 4
b100 >
b10100000000000010010011 %
b10100000000000010010011 :
1'
#40000
0'
#45000
b1100 =
b1000001000000110110011 !
b1000001000000110110011 .
b1000001000000110110011 5
b101000000000000100010011 %
b101000000000000100010011 :
b1000 #
b1000 <
b100 $
b100 ;
b1100 7
b1000 "
b1000 /
b1000 4
b1000 >
1'
#50000
0'
#55000
b10000 =
b1000000000100010000001000110011 !
b1000000000100010000001000110011 .
b1000000000100010000001000110011 5
b10000 7
b1100 "
b1100 /
b1100 4
b1100 >
b1000001000000110110011 %
b1000001000000110110011 :
b1100 #
b1100 <
b1000 $
b1000 ;
1'
#60000
1,
0'
#65000
1'
#70000
0'
#75000
1'
#80000
0,
0'
#85000
b10100 =
b1101111 !
b1101111 .
b1101111 5
b1000000000100010000001000110011 %
b1000000000100010000001000110011 :
b10000 #
b10000 <
b1100 $
b1100 ;
b10100 7
b10000 "
b10000 /
b10000 4
b10000 >
1'
#90000
b100000 =
1(
b100000 +
b100000 6
1*
0'
#95000
b10001000100010001000100010011 !
b10001000100010001000100010011 .
b10001000100010001000100010011 5
b100100 7
b100000 "
b100000 /
b100000 4
b100000 >
b0 %
b0 :
b0 #
b0 <
b0 $
b0 ;
1'
#100000
b100100 =
0(
0*
0'
#105000
b101000 =
b10011 !
b10011 .
b10011 5
b10001000100010001000100010011 %
b10001000100010001000100010011 :
b100100 #
b100100 <
b100000 $
b100000 ;
b101000 7
b100100 "
b100100 /
b100100 4
b100100 >
1'
#110000
b100000 =
1*
1(
1,
0'
#115000
b10001000100010001000100010011 !
b10001000100010001000100010011 .
b10001000100010001000100010011 5
b100100 7
b100000 "
b100000 /
b100000 4
b100000 >
b0 %
b0 :
b0 #
b0 <
b0 $
b0 ;
1'
