Day 015/code_converter.v
// A bidirectional code converter, i.e. both gray code to binary and vice versa
// Mode = 0 for binary to gray, Mode = 1 for gray to binary
// Idea: For converting binary to gray, use G[i] = B[i] ^ B[i+1]
//       For gray to binary, use B[MSB] = G[MSB], B[MSB - 1] = B[MSB] ^ G[MSB-1], B[MSB-2] = B[MSB-1] ^ G[MSB-2], B[MSB-3] = B[MSB-2] ^ G[MSB-3]

module code_converter(input [3:0] data_in, input mode, output [3:0] converted);
    wire [3:0] gray_to_binary_out, binary_to_gray_out;

    assign binary_to_gray_out = data_in ^  (data_in >> 1); 
    assign gray_to_binary_out[3] = data_in[3];
    assign gray_to_binary_out[2] = gray_to_binary_out[3] ^ data_in[2];
    assign gray_to_binary_out[1] = gray_to_binary_out[2] ^ data_in[1];
    assign gray_to_binary_out[0] = gray_to_binary_out[1] ^ data_in[0];

    assign converted = mode ? gray_to_binary_out : binary_to_gray_out;
endmodule

Day 015/tb.v
`timescale 1ns / 1ps

module tb_code_converter;

    reg [3:0] data_in;
    reg mode;
    wire [3:0] converted;

    // Workaround tracking net for safe iverilog $monitor tracking
    wire [87:0] mode_str = mode ? "GRAY_TO_BIN" : "BIN_TO_GRAY";

    // Instantiate the Device Under Test (DUT)
    code_converter uut (
        .data_in(data_in),
        .mode(mode),
        .converted(converted)
    );

    // Automated Console Logger
    initial begin
        $dumpfile("dump.vcd");
        $dumpvars(0);
        $monitor("Time = %0d ns | Mode = %s | Input_Bus = %b (Dec:%2d) | Output_Bus = %b (Dec:%2d)", 
                 $time, mode_str, data_in, data_in, converted, converted);
    end

    integer i;

    initial begin
        // --- State Initialization at Time Zero ---
        data_in = 4'b0000; mode = 1'b0; #10;
        
        // =================================================================
        // PHASE 1: BINARY TO GRAY SWEEP (mode = 0)
        // =================================================================
        $display("--- Starting Binary to Gray Conversion Verification ---");
        for (i = 0; i < 16; i = i + 1) begin
            data_in = i;
            #10;
        end
        data_in = 0;
        // =================================================================
        // PHASE 2: GRAY TO BINARY SWEEP (mode = 1)
        // =================================================================
        $display("--- Starting Gray to Binary Conversion Verification ---");
        mode = 1'b1;
        #10;
        
        for (i = 1; i < 16; i = i + 1) begin
            data_in = i;
            #10;
        end

        // --- Return to Idle State ---
        mode = 1'b0; data_in = 4'b0000; #10;
        
        $display("--- Day 15 Bidirectional Code Converter Verification Complete ---");
        $finish;
    end

endmodule

Day 015/dump.vcd
$date
	Sat Jun 20 17:55:39 2026
$end
$version
	Icarus Verilog
$end
$timescale
	1ps
$end
$scope module tb_code_converter $end
$var wire 88 ! mode_str [87:0] $end
$var wire 4 " converted [3:0] $end
$var reg 4 # data_in [3:0] $end
$var reg 1 $ mode $end
$var integer 32 % i [31:0] $end
$scope module uut $end
$var wire 4 & binary_to_gray_out [3:0] $end
$var wire 4 ' data_in [3:0] $end
$var wire 1 $ mode $end
$var wire 4 ( gray_to_binary_out [3:0] $end
$var wire 4 ) converted [3:0] $end
$upscope $end
$upscope $end
$enddefinitions $end
$comment Show the parameter values. $end
$dumpall
$end
#0
$dumpvars
b0 )
b0 (
b0 '
b0 &
bx %
0$
b0 #
b0 "
b100001001001001010011100101111101010100010011110101111101000111010100100100000101011001 !
$end
#10000
b0 %
#20000
b1 "
b1 )
b1 (
b1 &
b1 #
b1 '
b1 %
#30000
b11 "
b11 )
b11 (
b11 &
b10 #
b10 '
b10 %
#40000
b10 "
b10 )
b10 (
b10 &
b11 #
b11 '
b11 %
#50000
b110 "
b110 )
b111 (
b110 &
b100 #
b100 '
b100 %
#60000
b111 "
b111 )
b110 (
b111 &
b101 #
b101 '
b101 %
#70000
b101 "
b101 )
b100 (
b101 &
b110 #
b110 '
b110 %
#80000
b100 "
b100 )
b101 (
b100 &
b111 #
b111 '
b111 %
#90000
b1100 "
b1100 )
b1100 &
b1111 (
b1000 #
b1000 '
b1000 %
#100000
b1101 "
b1101 )
b1110 (
b1101 &
b1001 #
b1001 '
b1001 %
#110000
b1111 "
b1111 )
b1100 (
b1111 &
b1010 #
b1010 '
b1010 %
#120000
b1110 "
b1110 )
b1101 (
b1110 &
b1011 #
b1011 '
b1011 %
#130000
b1010 "
b1010 )
b1000 (
b1010 &
b1100 #
b1100 '
b1100 %
#140000
b1011 "
b1011 )
b1001 (
b1011 &
b1101 #
b1101 '
b1101 %
#150000
b1001 "
b1001 )
b1011 (
b1001 &
b1110 #
b1110 '
b1110 %
#160000
b1000 "
b1000 )
b1010 (
b1000 &
b1111 #
b1111 '
b1111 %
#170000
b100011101010010010000010101100101011111010101000100111101011111010000100100100101001110 !
b0 "
b0 )
b0 &
b0 (
1$
b0 #
b0 '
b10000 %
#180000
b1 "
b1 )
b1 (
b1 &
b1 #
b1 '
b1 %
#190000
b11 "
b11 )
b11 (
b11 &
b10 #
b10 '
b10 %
#200000
b10 "
b10 )
b10 (
b10 &
b11 #
b11 '
b11 %
#210000
b111 "
b111 )
b111 (
b110 &
b100 #
b100 '
b100 %
#220000
b110 "
b110 )
b110 (
b111 &
b101 #
b101 '
b101 %
#230000
b100 "
b100 )
b100 (
b101 &
b110 #
b110 '
b110 %
#240000
b101 "
b101 )
b101 (
b100 &
b111 #
b111 '
b111 %
#250000
b1111 "
b1111 )
b1100 &
b1111 (
b1000 #
b1000 '
b1000 %
#260000
b1110 "
b1110 )
b1110 (
b1101 &
b1001 #
b1001 '
b1001 %
#270000
b1100 "
b1100 )
b1100 (
b1111 &
b1010 #
b1010 '
b1010 %
#280000
b1101 "
b1101 )
b1101 (
b1110 &
b1011 #
b1011 '
b1011 %
#290000
b1000 "
b1000 )
b1000 (
b1010 &
b1100 #
b1100 '
b1100 %
#300000
b1001 "
b1001 )
b1001 (
b1011 &
b1101 #
b1101 '
b1101 %
#310000
b1011 "
b1011 )
b1011 (
b1001 &
b1110 #
b1110 '
b1110 %
#320000
b1010 "
b1010 )
b1010 (
b1000 &
b1111 #
b1111 '
b1111 %
#330000
b0 &
b0 (
b100001001001001010011100101111101010100010011110101111101000111010100100100000101011001 !
b0 "
b0 )
b0 #
b0 '
0$
b10000 %
