Day 083/riscv_data_mem.v
module riscv_data_mem #(
    parameter MEM_DEPTH = 1024
)(
    input clk, en,
    input [3:0] wstrb, 
    input [31:0] addr, wdata,
    output [31:0] rdata
);
    reg [31:0] mem[0:MEM_DEPTH-1];

    localparam ADDR_WIDTH = $clog2(MEM_DEPTH);
    wire [ADDR_WIDTH-1:0] word_idx = addr[ADDR_WIDTH+1:2];

    always@(posedge clk) begin
        if(en) begin
            if(wstrb[0]) mem[word_idx][7:0] <= wdata[7:0];
            if(wstrb[1]) mem[word_idx][15:8] <= wdata[15:8];
            if(wstrb[2]) mem[word_idx][23:16] <= wdata[23:16];
            if(wstrb[3]) mem[word_idx][31:24] <= wdata[31:24];
        end
    end

    assign rdata = en ? mem[word_idx] : 32'd0;
endmodule

Day 083/riscv_mem_stage.v
module riscv_mem_stage (
    input clk, nreset,

    input stall_wb, flush_wb,

    //Inputs from EX/MEM Register
    input [31:0] ex_mem_alu_result,
    input [31:0] ex_mem_wdata,
    input [4:0] ex_mem_rd,
    input [2:0] ex_mem_funct3,
    input [6:0] ex_mem_opcode,
    input ex_mem_reg_write,
    input ex_mem_mem_write, ex_mem_mem_read,

    //External Data Memory Interface
    output [31:0] dmem_addr,
    output reg [31:0] dmem_wdata,
    output reg [3:0] dmem_wstrb,
    output dmem_en,
    input [31:0] dmem_rdata,

    // Exception/Trap Flags
    output trap_store_misaligned, trap_load_misaligned,

    //Outputs from MEM/WB register
    output reg [31:0] mem_wb_wdata,
    output reg [4:0] mem_wb_rd,
    output reg [6:0] mem_wb_opcode,
    output reg mem_wb_reg_write
);
    wire [1:0] byte_offset = ex_mem_alu_result[1:0];

    //Word Aligned address(LSBs zero)
    assign dmem_addr = {ex_mem_alu_result[31:2], 2'b00};

    //Misaligned detection
    wire misaligned_half = (ex_mem_funct3[1:0] == 2'b01) && (byte_offset[0] != 1'b0);
    wire misaligned_word = (ex_mem_funct3[1:0] == 2'b10) && (byte_offset != 2'b00);
    wire is_misaligned = (ex_mem_mem_read | ex_mem_mem_write) && (misaligned_half | misaligned_word);

    assign trap_load_misaligned = ex_mem_mem_read & is_misaligned & ~flush_wb;
    assign trap_store_misaligned = ex_mem_mem_write & is_misaligned & ~flush_wb;

    //Suppress enable if misaligned to protext memory
    assign dmem_en = (ex_mem_mem_write | ex_mem_mem_read) & ~is_misaligned & ~flush_wb;

    //Data Steering: Raw combinational path
    always @(*) begin
        case (ex_mem_funct3)
            3'b000:  dmem_wdata = {4{ex_mem_wdata[7:0]}};
            3'b001:  dmem_wdata = {2{ex_mem_wdata[15:0]}};
            default: dmem_wdata = ex_mem_wdata;
        endcase
    end
    //Strobe Generation
    always @(*) begin
        if (ex_mem_mem_write && !is_misaligned && !flush_wb) begin
            case (ex_mem_funct3)
                3'b000:  dmem_wstrb = 4'b0001 << byte_offset;
                3'b001:  dmem_wstrb = byte_offset[1] ? 4'b1100 : 4'b0011;
                3'b010:  dmem_wstrb = 4'b1111;
                default: dmem_wstrb = 4'b0000;
            endcase
        end else begin
            dmem_wstrb = 4'b0000;
        end
    end

    //Load Alignment and Sign/zero extension
    reg [7:0] loaded_byte;
    reg [15:0] loaded_half;

    always@(*) begin
        case(byte_offset)
            2'b00: loaded_byte = dmem_rdata[7:0];
            2'b01: loaded_byte = dmem_rdata[15:8];
            2'b10: loaded_byte = dmem_rdata[23:16];
            2'b11: loaded_byte = dmem_rdata[31:24];
        endcase
    end
    always@(*) begin
        loaded_half = byte_offset[1] ? dmem_rdata[31:16] : dmem_rdata[15:0];      
    end

    reg [31:0] load_data;
    always@(*) begin
        if(is_misaligned) load_data = 32'd0;
        else begin
            case(ex_mem_funct3)
                3'b000: load_data = {{24{loaded_byte[7]}}, loaded_byte}; //LB(signed byte)
                3'b001: load_data = {{16{loaded_half[15]}}, loaded_half}; //LH(signed half)
                3'b010: load_data = dmem_rdata; //LW(load word)
                3'b100: load_data = {24'd0, loaded_byte}; //LBU(unsigned byte)
                3'b101: load_data = {16'd0, loaded_half}; //LHU(unsigned halfword)
                default: load_data = dmem_rdata; //Anyother will do LW
            endcase
        end
    end

    //Writeback MUX
    wire [31:0] mem_stage_result = (ex_mem_mem_read) ? load_data : ex_mem_alu_result;

    //MEM/WB Regs
    always@(posedge clk or negedge nreset) begin
        if(!nreset) begin
            mem_wb_wdata <= 32'd0;
            mem_wb_rd <= 5'd0;
            mem_wb_opcode <= 7'b0010011; //NOP
            mem_wb_reg_write <= 1'b0;
        end
        else if(flush_wb) begin
            mem_wb_wdata <= 32'd0;
            mem_wb_rd <= 5'd0;
            mem_wb_opcode <= 7'b0010011; //NOP
            mem_wb_reg_write <= 1'b0;
        end
        else if(!stall_wb) begin
            mem_wb_wdata <= mem_stage_result;
            mem_wb_rd <= ex_mem_rd;
            mem_wb_opcode <= ex_mem_opcode;
            mem_wb_reg_write <= ex_mem_reg_write & ~is_misaligned;
        end
    end
endmodule

Day 083/tb.v
`timescale 1ns / 1ps

module tb_riscv_mem_stage();

    parameter CLK_PERIOD = 10;

    reg         clk;
    reg         nreset;
    reg         stall_wb;
    reg         flush_wb;

    reg  [31:0] ex_mem_alu_result;
    reg  [31:0] ex_mem_wdata;
    reg  [4:0]  ex_mem_rd;
    reg  [2:0]  ex_mem_funct3;
    reg  [6:0]  ex_mem_opcode;
    reg         ex_mem_reg_write;
    reg         ex_mem_mem_read;
    reg         ex_mem_mem_write;

    wire [31:0] dmem_addr;
    wire [31:0] dmem_wdata;
    wire [3:0]  dmem_wstrb;
    wire        dmem_en;
    wire [31:0] dmem_rdata;

    wire        trap_load_misaligned;
    wire        trap_store_misaligned;

    wire [31:0] mem_wb_wdata;
    wire [4:0]  mem_wb_rd;
    wire [6:0]  mem_wb_opcode;
    wire        mem_wb_reg_write;

    integer errors = 0;

    // Instantiate MEM Stage UUT
    riscv_mem_stage u_mem_stage (
        .clk                  (clk),
        .nreset               (nreset),
        .stall_wb             (stall_wb),
        .flush_wb             (flush_wb),
        .ex_mem_alu_result    (ex_mem_alu_result),
        .ex_mem_wdata         (ex_mem_wdata),
        .ex_mem_rd            (ex_mem_rd),
        .ex_mem_funct3        (ex_mem_funct3),
        .ex_mem_opcode        (ex_mem_opcode),
        .ex_mem_reg_write     (ex_mem_reg_write),
        .ex_mem_mem_read      (ex_mem_mem_read),
        .ex_mem_mem_write     (ex_mem_mem_write),
        .dmem_addr            (dmem_addr),
        .dmem_wdata           (dmem_wdata),
        .dmem_wstrb           (dmem_wstrb),
        .dmem_en              (dmem_en),
        .dmem_rdata           (dmem_rdata),
        .trap_load_misaligned (trap_load_misaligned),
        .trap_store_misaligned(trap_store_misaligned),
        .mem_wb_wdata         (mem_wb_wdata),
        .mem_wb_rd            (mem_wb_rd),
        .mem_wb_opcode        (mem_wb_opcode),
        .mem_wb_reg_write     (mem_wb_reg_write)
    );

    // Instantiate Companion Data Memory
    riscv_data_mem #(.MEM_DEPTH(256)) u_data_mem (
        .clk   (clk),
        .en    (dmem_en),
        .wstrb (dmem_wstrb),
        .addr  (dmem_addr),
        .wdata (dmem_wdata),
        .rdata (dmem_rdata)
    );

    always #(CLK_PERIOD / 2) clk = ~clk;

    initial begin
        $dumpfile("dump.vcd");
        $dumpvars(0, tb_riscv_mem_stage);

        clk               = 0;
        nreset            = 0;
        stall_wb          = 0;
        flush_wb          = 0;
        ex_mem_alu_result = 32'd0;
        ex_mem_wdata      = 32'd0;
        ex_mem_rd         = 5'd0;
        ex_mem_funct3     = 3'd0;
        ex_mem_opcode     = 7'b0010011;
        ex_mem_reg_write  = 0;
        ex_mem_mem_read   = 0;
        ex_mem_mem_write  = 0;

        #(CLK_PERIOD * 3);
        @(negedge clk);
        nreset = 1;

        $display("\n=======================================================================================================");
        $display("                   DAY 83: RISC-V MEMORY (MEM) STAGE VERIFICATION                                       ");
        $display("=======================================================================================================");

        // --- TEST 1: ALU Pass-Through (Non-Memory Instructions) ---
        $display("\n--- TEST 1: ALU Computation Pass-Through (ADD/SUB/etc.) ---");
        @(negedge clk);
        ex_mem_alu_result = 32'hDEAD_BEEF;
        ex_mem_rd         = 5'd10;
        ex_mem_reg_write  = 1'b1;
        ex_mem_mem_read   = 1'b0;
        ex_mem_mem_write  = 1'b0;

        @(posedge clk);
        #(1);
        if (mem_wb_wdata !== 32'hDEAD_BEEF || mem_wb_rd !== 5'd10 || mem_wb_reg_write !== 1'b1) begin
            $display("[FAIL] ALU bypass failed! Got wdata: 0x%08h, rd: %0d", mem_wb_wdata, mem_wb_rd);
            errors = errors + 1;
        end else begin
            $display("[PASS] ALU result 0x%08h cleanly latched to WB port", mem_wb_wdata);
        end

        // --- TEST 2: Word Store & Word Load (SW & LW) ---
        $display("\n--- TEST 2: Word Store & Word Load (SW & LW) ---");
        @(negedge clk);
        ex_mem_alu_result = 32'h0000_0040;
        ex_mem_wdata      = 32'h1234_5678;
        ex_mem_funct3     = 3'b010; // SW
        ex_mem_mem_write  = 1'b1;
        ex_mem_mem_read   = 1'b0;
        ex_mem_reg_write  = 1'b0;

        @(posedge clk);
        #(1);
        @(negedge clk);
        ex_mem_mem_write  = 1'b0;
        ex_mem_mem_read   = 1'b1;
        ex_mem_rd         = 5'd5;
        ex_mem_reg_write  = 1'b1;

        @(posedge clk);
        #(1);
        if (mem_wb_wdata !== 32'h1234_5678 || mem_wb_rd !== 5'd5) begin
            $display("[FAIL] LW failed! Got: 0x%08h, Expected: 0x12345678", mem_wb_wdata);
            errors = errors + 1;
        end else begin
            $display("[PASS] SW followed by LW verified: 0x%08h", mem_wb_wdata);
        end

        // --- TEST 3: Byte Steering across All 4 Lanes (SB) ---
        $display("\n--- TEST 3: Byte Steering & Strobe Verification (SB) ---");
        // Assemble word 0xDDCCBBAA at address 0x00000050
        @(negedge clk);
        ex_mem_funct3    = 3'b000; // SB
        ex_mem_mem_write = 1'b1;
        ex_mem_mem_read  = 1'b0;
        ex_mem_reg_write = 1'b0;

        ex_mem_alu_result = 32'h0000_0050; ex_mem_wdata = 32'h0000_00AA; @(posedge clk);
        @(negedge clk);
        ex_mem_alu_result = 32'h0000_0051; ex_mem_wdata = 32'h0000_00BB; @(posedge clk);
        @(negedge clk);
        ex_mem_alu_result = 32'h0000_0052; ex_mem_wdata = 32'h0000_00CC; @(posedge clk);
        @(negedge clk);
        ex_mem_alu_result = 32'h0000_0053; ex_mem_wdata = 32'h0000_00DD; @(posedge clk);

        @(negedge clk);
        ex_mem_mem_write  = 1'b0;
        ex_mem_mem_read   = 1'b1;
        ex_mem_alu_result = 32'h0000_0050;
        ex_mem_funct3     = 3'b010; // LW
        ex_mem_rd         = 5'd7;

        @(posedge clk);
        #(1);
        if (mem_wb_wdata !== 32'hDDCC_BBAA) begin
            $display("[FAIL] 4-byte assembly failed! Got: 0x%08h, Expected: 0xDDCCBBAA", mem_wb_wdata);
            errors = errors + 1;
        end else begin
            $display("[PASS] Byte writes assembled to full word: 0x%08h", mem_wb_wdata);
        end

        // --- TEST 4: Signed vs Unsigned Byte Loads (LB vs LBU) ---
        $display("\n--- TEST 4: Byte Sign Extension (LB vs LBU) ---");
        // Read byte at 0x50 (0xAA = 8'b10101010 -> MSB is 1)
        @(negedge clk);
        ex_mem_alu_result = 32'h0000_0050;
        ex_mem_funct3     = 3'b000; // LB
        ex_mem_mem_read   = 1'b1;
        ex_mem_rd         = 5'd1;

        @(posedge clk);
        #(1);
        if (mem_wb_wdata !== 32'hFFFF_FFAA) begin
            $display("[FAIL] LB sign-extension failed! Got: 0x%08h, Expected: 0xFFFFFFAA", mem_wb_wdata);
            errors = errors + 1;
        end else begin
            $display("[PASS] LB signed extension: 0xAA -> 0x%08h", mem_wb_wdata);
        end

        @(negedge clk);
        ex_mem_funct3 = 3'b100; // LBU
        @(posedge clk);
        #(1);
        if (mem_wb_wdata !== 32'h0000_00AA) begin
            $display("[FAIL] LBU zero-extension failed! Got: 0x%08h, Expected: 0x000000AA", mem_wb_wdata);
            errors = errors + 1;
        end else begin
            $display("[PASS] LBU unsigned extension: 0xAA -> 0x%08h", mem_wb_wdata);
        end

        // --- TEST 5: Aligned Halfword Loads (LH vs LHU) ---
        $display("\n--- TEST 5: Aligned Halfword Sign Extension (LH vs LHU) ---");
        // Upper halfword at 0x52 contains 0xDDCC (MSB of 0xDD is 1)
        // Tests byte_offset[1] == 1 selection and 16-bit sign-extension
        @(negedge clk);
        ex_mem_alu_result = 32'h0000_0052; // Aligned halfword offset 2
        ex_mem_funct3     = 3'b001;        // LH
        ex_mem_mem_read   = 1'b1;
        ex_mem_mem_write  = 1'b0;
        ex_mem_reg_write  = 1'b1;
        ex_mem_rd         = 5'd2;

        @(posedge clk);
        #(1);
        if (mem_wb_wdata !== 32'hFFFF_DDCC) begin
            $display("[FAIL] LH sign-extension failed! Got: 0x%08h, Expected: 0xFFFFDDCC", mem_wb_wdata);
            errors = errors + 1;
        end else begin
            $display("[PASS] LH upper-halfword signed extension: 0xDDCC -> 0x%08h", mem_wb_wdata);
        end

        @(negedge clk);
        ex_mem_funct3 = 3'b101; // LHU
        @(posedge clk);
        #(1);
        if (mem_wb_wdata !== 32'h0000_DDCC) begin
            $display("[FAIL] LHU zero-extension failed! Got: 0x%08h, Expected: 0x0000DDCC", mem_wb_wdata);
            errors = errors + 1;
        end else begin
            $display("[PASS] LHU upper-halfword unsigned extension: 0xDDCC -> 0x%08h", mem_wb_wdata);
        end

        // Lower halfword at 0x50 contains 0xBBAA (MSB of 0xBB is 1)
        // Tests byte_offset[1] == 0 selection
        @(negedge clk);
        ex_mem_alu_result = 32'h0000_0050; // Aligned halfword offset 0
        ex_mem_funct3     = 3'b001;        // LH
        @(posedge clk);
        #(1);
        if (mem_wb_wdata !== 32'hFFFF_BBAA) begin
            $display("[FAIL] LH lower-halfword failed! Got: 0x%08h, Expected: 0xFFFFBBAA", mem_wb_wdata);
            errors = errors + 1;
        end else begin
            $display("[PASS] LH lower-halfword signed extension: 0xBBAA -> 0x%08h", mem_wb_wdata);
        end

        // --- TEST 6: Address Misalignment Traps & Strobe Zeroing ---
        $display("\n--- TEST 6: Misalignment Detection & Strobe Zeroing ---");
        // Test 6a: Misaligned SW to 0x0000_0061 (offset 1)
        @(negedge clk);
        ex_mem_alu_result = 32'h0000_0061;
        ex_mem_wdata      = 32'hA5A5_A5A5;
        ex_mem_funct3     = 3'b010; // SW
        ex_mem_mem_write  = 1'b1;
        ex_mem_mem_read   = 1'b0;

        #(1);
        if (trap_store_misaligned !== 1'b1 || dmem_wstrb !== 4'b0000 || dmem_en !== 1'b0) begin
            $display("[FAIL] Misaligned SW was not trapped! trap=%b, wstrb=%b, dmem_en=%b",
                     trap_store_misaligned, dmem_wstrb, dmem_en);
            errors = errors + 1;
        end else begin
            $display("[PASS] Misaligned SW trapped: trap_store_misaligned=1, dmem_wstrb=0000, dmem_en=0");
        end

        // Test 6b: Misaligned LH to 0x0000_0063 (offset 3)
        @(negedge clk);
        ex_mem_alu_result = 32'h0000_0063;
        ex_mem_funct3     = 3'b001; // LH
        ex_mem_mem_write  = 1'b0;
        ex_mem_mem_read   = 1'b1;
        ex_mem_rd         = 5'd8;
        ex_mem_reg_write  = 1'b1;

        #(1);
        if (trap_load_misaligned !== 1'b1 || dmem_en !== 1'b0) begin
            $display("[FAIL] Misaligned LH was not trapped! trap=%b, dmem_en=%b",
                     trap_load_misaligned, dmem_en);
            errors = errors + 1;
        end else begin
            $display("[PASS] Misaligned LH trapped: trap_load_misaligned=1, dmem_en=0");
        end

        @(posedge clk);
        #(1);
        if (mem_wb_reg_write !== 1'b0) begin
            $display("[FAIL] mem_wb_reg_write remained active during trapped access!");
            errors = errors + 1;
        end else begin
            $display("[PASS] RegWrite suppressed in MEM/WB register during trap condition");
        end

        // --- TEST 7: Pipeline Stall & Flush ---
        $display("\n--- TEST 7: MEM/WB Register Stall & Flush ---");
        @(negedge clk);
        stall_wb          = 1'b1;
        ex_mem_alu_result = 32'hCAFE_CAFE;
        ex_mem_mem_read   = 1'b0;
        ex_mem_mem_write  = 1'b0;
        ex_mem_reg_write  = 1'b1;
        ex_mem_rd         = 5'd20;

        @(posedge clk);
        #(1);
        if (mem_wb_rd === 5'd20) begin
            $display("[FAIL] MEM/WB drifted during stall_wb!");
            errors = errors + 1;
        end else begin
            $display("[PASS] MEM/WB held state during stall_wb");
        end

        @(negedge clk);
        stall_wb = 1'b0;
        flush_wb = 1'b1;

        @(posedge clk);
        #(1);
        if (mem_wb_reg_write !== 1'b0 || mem_wb_rd !== 5'd0) begin
            $display("[FAIL] Flush failed to inject bubble! reg_write=%b, rd=%0d", mem_wb_reg_write, mem_wb_rd);
            errors = errors + 1;
        end else begin
            $display("[PASS] MEM/WB successfully cleared to NOP bubble on flush_wb");
        end

        // --- TEST 8: Store Squashed by Concurrent Flush (Memory Immutability) ---
        $display("\n--- TEST 8: Store Squashed Concurrently by flush_wb ---");
        @(negedge clk);
        flush_wb          = 1'b0;
        ex_mem_alu_result = 32'h0000_0070;
        ex_mem_wdata      = 32'h1122_3344;
        ex_mem_funct3     = 3'b010; // SW
        ex_mem_mem_write  = 1'b1;
        ex_mem_mem_read   = 1'b0;
        ex_mem_reg_write  = 1'b0;

        @(posedge clk);
        #(1);

        // Attempt squashed store with flush_wb asserted
        @(negedge clk);
        flush_wb          = 1'b1;
        ex_mem_alu_result = 32'h0000_0070;
        ex_mem_wdata      = 32'hBAD0_C0FF;
        ex_mem_funct3     = 3'b010; // SW
        ex_mem_mem_write  = 1'b1;

        #(1);
        if (dmem_en !== 1'b0 || dmem_wstrb !== 4'b0000) begin
            $display("[FAIL] Flushed store failed to suppress strobes! dmem_en=%b, dmem_wstrb=%b",
                     dmem_en, dmem_wstrb);
            errors = errors + 1;
        end

        @(posedge clk);
        #(1);
        flush_wb         = 1'b0;
        ex_mem_mem_write = 1'b0;

        // Verify memory was not overwritten
        @(negedge clk);
        ex_mem_alu_result = 32'h0000_0070;
        ex_mem_mem_read   = 1'b1;
        ex_mem_funct3     = 3'b010; // LW
        ex_mem_rd         = 5'd12;
        ex_mem_reg_write  = 1'b1;

        @(posedge clk);
        #(1);
        if (mem_wb_wdata !== 32'h1122_3344) begin
            $display("[FAIL] Memory corrupted during squashed store! Got: 0x%08h, Expected: 0x11223344", mem_wb_wdata);
            errors = errors + 1;
        end else begin
            $display("[PASS] Memory remained immutable across squashed store: 0x%08h", mem_wb_wdata);
        end

        // --- TEST 9: Misalignment Trap Suppression under Concurrent Flush ---
        $display("\n--- TEST 9: Misalignment Trap Suppression during flush_wb ---");
        @(negedge clk);
        flush_wb          = 1'b1;
        ex_mem_alu_result = 32'h0000_0071; // Misaligned store
        ex_mem_funct3     = 3'b010;        // SW
        ex_mem_mem_write  = 1'b1;
        ex_mem_mem_read   = 1'b0;

        #(1);
        if (trap_store_misaligned !== 1'b0 || dmem_en !== 1'b0) begin
            $display("[FAIL] Phantom trap_store_misaligned fired under flush! trap=%b", trap_store_misaligned);
            errors = errors + 1;
        end else begin
            $display("[PASS] Phantom store trap suppressed under flush_wb: trap_store_misaligned=0");
        end

        @(negedge clk);
        ex_mem_alu_result = 32'h0000_0073; // Misaligned load
        ex_mem_funct3     = 3'b001;        // LH
        ex_mem_mem_write  = 1'b0;
        ex_mem_mem_read   = 1'b1;

        #(1);
        if (trap_load_misaligned !== 1'b0 || dmem_en !== 1'b0) begin
            $display("[FAIL] Phantom trap_load_misaligned fired under flush! trap=%b", trap_load_misaligned);
            errors = errors + 1;
        end else begin
            $display("[PASS] Phantom load trap suppressed under flush_wb: trap_load_misaligned=0");
        end

        @(posedge clk);
        #(CLK_PERIOD * 5);
        $display("\n=======================================================================================================");
        if (errors == 0)
            $display("   DAY 83 RISC-V MEM STAGE VERIFICATION SUCCESSFUL");
        else
            $display("   VERIFICATION FAILED WITH %0d ERROR(S)!", errors);
        $display("=======================================================================================================\n");

        $finish;
    end

endmodule

Day 083/dump.vcd
$date
	Sat Sep 26 03:03:52 2026
$end
$version
	Icarus Verilog
$end
$timescale
	1ps
$end
$scope module tb_riscv_mem_stage $end
$var wire 1 ! trap_store_misaligned $end
$var wire 1 " trap_load_misaligned $end
$var wire 32 # mem_wb_wdata [31:0] $end
$var wire 1 $ mem_wb_reg_write $end
$var wire 5 % mem_wb_rd [4:0] $end
$var wire 7 & mem_wb_opcode [6:0] $end
$var wire 4 ' dmem_wstrb [3:0] $end
$var wire 32 ( dmem_wdata [31:0] $end
$var wire 32 ) dmem_rdata [31:0] $end
$var wire 1 * dmem_en $end
$var wire 32 + dmem_addr [31:0] $end
$var parameter 32 , CLK_PERIOD $end
$var reg 1 - clk $end
$var reg 32 . ex_mem_alu_result [31:0] $end
$var reg 3 / ex_mem_funct3 [2:0] $end
$var reg 1 0 ex_mem_mem_read $end
$var reg 1 1 ex_mem_mem_write $end
$var reg 7 2 ex_mem_opcode [6:0] $end
$var reg 5 3 ex_mem_rd [4:0] $end
$var reg 1 4 ex_mem_reg_write $end
$var reg 32 5 ex_mem_wdata [31:0] $end
$var reg 1 6 flush_wb $end
$var reg 1 7 nreset $end
$var reg 1 8 stall_wb $end
$var integer 32 9 errors [31:0] $end
$scope module u_data_mem $end
$var wire 1 - clk $end
$var wire 4 : wstrb [3:0] $end
$var wire 8 ; word_idx [7:0] $end
$var wire 32 < wdata [31:0] $end
$var wire 32 = rdata [31:0] $end
$var wire 1 * en $end
$var wire 32 > addr [31:0] $end
$var parameter 32 ? ADDR_WIDTH $end
$var parameter 32 @ MEM_DEPTH $end
$upscope $end
$scope module u_mem_stage $end
$var wire 1 - clk $end
$var wire 1 * dmem_en $end
$var wire 32 A dmem_rdata [31:0] $end
$var wire 32 B ex_mem_alu_result [31:0] $end
$var wire 3 C ex_mem_funct3 [2:0] $end
$var wire 1 0 ex_mem_mem_read $end
$var wire 1 1 ex_mem_mem_write $end
$var wire 7 D ex_mem_opcode [6:0] $end
$var wire 5 E ex_mem_rd [4:0] $end
$var wire 1 4 ex_mem_reg_write $end
$var wire 32 F ex_mem_wdata [31:0] $end
$var wire 1 6 flush_wb $end
$var wire 1 G is_misaligned $end
$var wire 1 H misaligned_half $end
$var wire 1 I misaligned_word $end
$var wire 1 7 nreset $end
$var wire 1 8 stall_wb $end
$var wire 1 " trap_load_misaligned $end
$var wire 1 ! trap_store_misaligned $end
$var wire 32 J mem_stage_result [31:0] $end
$var wire 32 K dmem_addr [31:0] $end
$var wire 2 L byte_offset [1:0] $end
$var reg 32 M dmem_wdata [31:0] $end
$var reg 4 N dmem_wstrb [3:0] $end
$var reg 32 O load_data [31:0] $end
$var reg 8 P loaded_byte [7:0] $end
$var reg 16 Q loaded_half [15:0] $end
$var reg 7 R mem_wb_opcode [6:0] $end
$var reg 5 S mem_wb_rd [4:0] $end
$var reg 1 $ mem_wb_reg_write $end
$var reg 32 T mem_wb_wdata [31:0] $end
$upscope $end
$upscope $end
$enddefinitions $end
$comment Show the parameter values. $end
$dumpall
b100000000 @
b1000 ?
b1010 ,
$end
#0
$dumpvars
b0 T
b0 S
b10011 R
b0 Q
b0 P
b0 O
b0 N
b0 M
b0 L
b0 K
b0 J
0I
0H
0G
b0 F
b0 E
b10011 D
b0 C
b0 B
b0 A
b0 >
b0 =
b0 <
b0 ;
b0 :
b0 9
08
07
06
b0 5
04
b0 3
b10011 2
01
00
b0 /
b0 .
0-
b0 +
0*
b0 )
b0 (
b0 '
b10011 &
b0 %
0$
b0 #
0"
0!
$end
#5000
1-
#10000
0-
#15000
1-
#20000
0-
#25000
1-
#30000
17
0-
#35000
1-
#40000
b10111011 ;
b11 L
b11011110101011011011111011101100 +
b11011110101011011011111011101100 >
b11011110101011011011111011101100 K
b11011110101011011011111011101111 J
14
b1010 3
b1010 E
b11011110101011011011111011101111 .
b11011110101011011011111011101111 B
0-
#45000
1$
b1010 %
b1010 S
b11011110101011011011111011101111 #
b11011110101011011011111011101111 T
1-
#50000
bx O
bx P
bx Q
bx )
bx =
bx A
1*
b10000 ;
b1111 '
b1111 :
b1111 N
b10010001101000101011001111000 (
b10010001101000101011001111000 <
b10010001101000101011001111000 M
b0 L
b1000000 +
b1000000 >
b1000000 K
b1000000 J
04
11
b10 /
b10 C
b10010001101000101011001111000 5
b10010001101000101011001111000 F
b1000000 .
b1000000 B
0-
#55000
b10010001101000101011001111000 O
b101011001111000 Q
b1111000 P
b10010001101000101011001111000 )
b10010001101000101011001111000 =
b10010001101000101011001111000 A
0$
b1000000 #
b1000000 T
1-
#60000
b10010001101000101011001111000 J
b0 '
b0 :
b0 N
14
b101 3
b101 E
10
01
0-
#65000
1$
b101 %
b101 S
b10010001101000101011001111000 #
b10010001101000101011001111000 T
1-
#70000
bx P
bx Q
bx )
bx =
bx A
b10100 ;
b1010000 +
b1010000 >
b1010000 K
b1010000 J
bx O
b1 '
b1 :
b1 N
b10101010101010101010101010101010 (
b10101010101010101010101010101010 <
b10101010101010101010101010101010 M
b10101010 5
b10101010 F
b1010000 .
b1010000 B
04
00
11
b0 /
b0 C
0-
#75000
b11111111111111111111111110101010 O
bx10101010 Q
b10101010 P
bx10101010 )
bx10101010 =
bx10101010 A
0$
b1010000 #
b1010000 T
1-
#80000
bx O
bx P
b10 '
b10 :
b10 N
b10111011101110111011101110111011 (
b10111011101110111011101110111011 <
b10111011101110111011101110111011 M
b1 L
b1010001 J
b10111011 5
b10111011 F
b1010001 .
b1010001 B
0-
#85000
b11111111111111111111111110111011 O
b1011101110101010 Q
b10111011 P
bx1011101110101010 )
bx1011101110101010 =
bx1011101110101010 A
b1010001 #
b1010001 T
1-
#90000
bx O
bx P
bx Q
b100 '
b100 :
b100 N
b11001100110011001100110011001100 (
b11001100110011001100110011001100 <
b11001100110011001100110011001100 M
b10 L
b1010010 J
b11001100 5
b11001100 F
b1010010 .
b1010010 B
0-
#95000
b11111111111111111111111111001100 O
bx11001100 Q
b11001100 P
bx110011001011101110101010 )
bx110011001011101110101010 =
bx110011001011101110101010 A
b1010010 #
b1010010 T
1-
#100000
bx O
bx P
b1000 '
b1000 :
b1000 N
b11011101110111011101110111011101 (
b11011101110111011101110111011101 <
b11011101110111011101110111011101 M
b11 L
b1010011 J
b11011101 5
b11011101 F
b1010011 .
b1010011 B
0-
#105000
b11111111111111111111111111011101 O
b1101110111001100 Q
b11011101 P
b11011101110011001011101110101010 )
b11011101110011001011101110101010 =
b11011101110011001011101110101010 A
b1010011 #
b1010011 T
1-
#110000
b10101010 P
b1011101110101010 Q
b11011101110011001011101110101010 O
b11011101 (
b11011101 <
b11011101 M
b0 L
b11011101110011001011101110101010 J
b0 '
b0 :
b0 N
b111 3
b111 E
b10 /
b10 C
b1010000 .
b1010000 B
10
01
0-
#115000
b111 %
b111 S
b11011101110011001011101110101010 #
b11011101110011001011101110101010 T
1-
#120000
b11111111111111111111111110101010 J
b11111111111111111111111110101010 O
b11011101110111011101110111011101 (
b11011101110111011101110111011101 <
b11011101110111011101110111011101 M
b1 3
b1 E
b0 /
b0 C
0-
#125000
b1 %
b1 S
b11111111111111111111111110101010 #
b11111111111111111111111110101010 T
1-
#130000
b10101010 J
b10101010 O
b11011101 (
b11011101 <
b11011101 M
b100 /
b100 C
0-
#135000
b10101010 #
b10101010 T
1-
#140000
b11111111111111111101110111001100 J
b1101110111001100 Q
b11001100 P
b11111111111111111101110111001100 O
b110111010000000011011101 (
b110111010000000011011101 <
b110111010000000011011101 M
b10 L
b10 3
b10 E
14
b1 /
b1 C
b1010010 .
b1010010 B
0-
#145000
1$
b10 %
b10 S
b11111111111111111101110111001100 #
b11111111111111111101110111001100 T
1-
#150000
b1101110111001100 J
b1101110111001100 O
b11011101 (
b11011101 <
b11011101 M
b101 /
b101 C
0-
#155000
b1101110111001100 #
b1101110111001100 T
1-
#160000
b11111111111111111011101110101010 J
b10101010 P
b1011101110101010 Q
b11111111111111111011101110101010 O
b110111010000000011011101 (
b110111010000000011011101 <
b110111010000000011011101 M
b0 L
b1 /
b1 C
b1010000 .
b1010000 B
0-
#165000
b11111111111111111011101110101010 #
b11111111111111111011101110101010 T
1-
#170000
0*
1!
1G
b0 Q
b0 )
b0 =
b0 A
1I
b0 P
b11000 ;
b1100001 J
b0 O
b0 '
b0 :
b0 N
b10100101101001011010010110100101 (
b10100101101001011010010110100101 <
b10100101101001011010010110100101 M
b1 L
b1100000 +
b1100000 >
b1100000 K
00
11
b10 /
b10 C
b10100101101001011010010110100101 5
b10100101101001011010010110100101 F
b1100001 .
b1100001 B
0-
#175000
0$
b1100001 #
b1100001 T
1-
#180000
1"
0!
1H
0I
b11 L
b0 J
b1000 3
b1000 E
10
01
b1 /
b1 C
b1100011 .
b1100011 B
0-
#185000
b1000 %
b1000 S
b0 #
b0 T
1-
#190000
0H
0G
0"
b10111111 ;
b11001010111111101100101011111110 J
b10 L
b11001010111111101100101011111100 +
b11001010111111101100101011111100 >
b11001010111111101100101011111100 K
b10100 3
b10100 E
00
b11001010111111101100101011111110 .
b11001010111111101100101011111110 B
18
0-
#195000
1-
#200000
16
08
0-
#205000
b0 %
b0 S
1-
#210000
bx O
bx Q
bx P
bx )
bx =
bx A
1*
b11100 ;
b10001001000100011001101000100 (
b10001001000100011001101000100 <
b10001001000100011001101000100 M
b0 L
b1110000 +
b1110000 >
b1110000 K
b1110000 J
b1111 '
b1111 :
b1111 N
04
11
b10 /
b10 C
b10001001000100011001101000100 5
b10001001000100011001101000100 F
b1110000 .
b1110000 B
06
0-
#215000
b10001001000100011001101000100 O
b1000100 P
b11001101000100 Q
b10001001000100011001101000100 )
b10001001000100011001101000100 =
b10001001000100011001101000100 A
b10100 %
b10100 S
b1110000 #
b1110000 T
1-
