Day 076/i2c_master.v
module i2c_master #(
    parameter SYS_CLK_FREQ = 50_000_000,
    parameter I2C_BUS_FREQ = 100_000
)(
    input clk, nreset,

    input cmd_start,
    input cmd_stop,
    input cmd_read, 
    input cmd_write,
    input ack_in,
    input [7:0] tx_data,

    output reg [7:0] rx_data,
    output reg rx_ack,  // 0 -> ACK, 1 -> NACK
    output reg busy,
    output reg done,

    inout scl, sda
);

    localparam QUARTER_DIV = SYS_CLK_FREQ/(I2C_BUS_FREQ * 4);
    localparam CNT_WIDTH = $clog2(QUARTER_DIV);

    reg [CNT_WIDTH-1:0] q_cnt;
    reg [1:0] phase;
    
    wire quarter_tick = (q_cnt == (QUARTER_DIV-1));

    //Bus input synchronizer
    reg [1:0] scl_sync, sda_sync;
    always@(posedge clk or negedge nreset) begin
        if(!nreset) begin
            scl_sync <= 2'b11;
            sda_sync <= 2'b11;
        end
        else begin
            scl_sync <= {scl_sync[0], scl};
            sda_sync <= {sda_sync[0], sda};
        end
    end
    wire scl_in = scl_sync[1];
    wire sda_in = sda_sync[1];

    //Open drain driver registers(0 -> Drive LOW, 1 -> Release(HiZ state))
    reg scl_oen, sda_oen;

    assign scl = (scl_oen == 1'b0) ? 1'b0 : 1'bz;
    assign sda = (sda_oen == 1'b0) ? 1'b0 : 1'bz;

    //FSM States
    localparam S_IDLE = 3'd0;
    localparam S_START = 3'd1;
    localparam S_WRITE_BYTE = 3'd2;
    localparam S_READ_BYTE = 3'd3;
    localparam S_SLAVE_ACK = 3'd4;
    localparam S_MASTER_ACK = 3'd5;
    localparam S_STOP = 3'd6;

    reg [2:0] state, next_state;
    reg [2:0] bit_cnt;
    reg [7:0] shreg;
    reg stretch_active;

    always@(posedge clk or negedge nreset) begin
        if(!nreset) begin
            q_cnt <= 0;
            phase <= 2'd0;
            stretch_active <= 1'b0;
        end
        else begin
            if(state == S_IDLE) begin
                q_cnt <= 0;
                phase <= 2'd0;
                stretch_active <= 1'b0;
            end
            else begin
                //Freeze the prescaler if slave holds SCL low during phase 1
                if(phase == 2'd1 && scl_oen == 1'b1 && scl_in == 1'b0) begin
                    stretch_active <= 1'b1;
                end
                else begin
                    stretch_active <= 1'b0;
                    if(quarter_tick) begin
                        q_cnt <= 0;
                        phase <= phase + 1'b1;
                    end
                    else q_cnt <= q_cnt + 1'b1;
                end
            end
        end
    end 

    //Next State Logic
    always@(*) begin
        next_state = state;
        case(state) 
            S_IDLE: begin
                if(cmd_start) next_state = S_START;
                else if(cmd_write) next_state = S_WRITE_BYTE;
                else if(cmd_read) next_state = S_READ_BYTE;
                else if(cmd_stop) next_state = S_STOP;
            end
            
            S_START: begin
                if(quarter_tick && phase == 2'd3) 
                    next_state = S_IDLE;
            end

            S_WRITE_BYTE: begin
                if(quarter_tick && (phase == 2'd3) && (bit_cnt == 3'd0)) 
                    next_state = S_SLAVE_ACK;
            end

            S_SLAVE_ACK: begin
                if(quarter_tick && phase == 2'd3)
                    next_state = S_IDLE;
            end

            S_READ_BYTE: begin
                if(quarter_tick && phase == 2'd3 && bit_cnt == 3'd0)
                    next_state = S_MASTER_ACK;
            end

            S_MASTER_ACK: begin
                if(quarter_tick && phase == 2'd3)
                    next_state = S_IDLE;
            end

            S_STOP: begin
                if(quarter_tick && phase == 2'd3) 
                    next_state = S_IDLE;
            end

            default: next_state = S_IDLE;
        endcase 
    end

    //State Transition
    always@(posedge clk or negedge nreset) begin
        if(!nreset) state <= S_IDLE;
        else state <= next_state;
    end

    //Register updates
    always@(posedge clk or negedge nreset) begin
        if(!nreset) begin
            scl_oen <= 1'b1;
            sda_oen <= 1'b1;
            done <= 1'b0;
            rx_data <= 8'd0;
            rx_ack <= 1'b1;
            bit_cnt <= 3'd7;
            shreg <= 8'd0;
        end
        else begin
            done <= 1'b0;

            case(state)
                S_IDLE: begin
                    if(cmd_start || cmd_write) begin
                        shreg <= tx_data;
                        bit_cnt <= 3'd7;
                    end
                    else if(cmd_read) begin
                        bit_cnt <= 3'd7;
                    end
                end

                S_START: begin
                    if(quarter_tick) begin
                        case(phase)
                            2'd0: begin
                                sda_oen <= 1'b1; //Ensure SDA high before SCL goes high
                                //SCL is usually pulled LOW at the end of preceding byte or ACK cycle
                                //Hence it must remain LOW in phase 0 while SDA is floated high
                                //Otherwise floating SDA while SCL high will trigger a FALSE STOP condition
                            end
                            2'd1: begin
                                scl_oen <= 1'b1; //SCL goes HIGH
                            end
                            2'd2: begin
                                sda_oen <= 1'b0; //SDA pulled LOW while SCL HIGH(START condition)
                            end
                            2'd3: begin
                                scl_oen <= 1'b0; //SCL pulled LOW to lock bus
                                done <= 1'b1;
                            end
                        endcase
                    end
                end

                S_WRITE_BYTE: begin
                    if(quarter_tick) begin
                        case(phase)
                            2'd0: begin
                                scl_oen <= 1'b0;
                                sda_oen <= shreg[bit_cnt]; //Drive bit when SCL is low
                            end
                            2'd1: begin
                                scl_oen <= 1'b1; //Release SCL high
                            end
                            2'd2: begin
                                //  Hold data during phase 2 when SCL is high
                            end
                            2'd3: begin
                                scl_oen <= 1'b0; //Drive SCL low 
                                if(bit_cnt != 3'd0) bit_cnt <= bit_cnt - 1'b1;
                            end
                        endcase
                    end
                end

                S_SLAVE_ACK: begin
                    if(quarter_tick) begin
                        case(phase)
                            2'd0: begin
                                scl_oen <= 1'b0;
                                sda_oen <= 1'b1; //Release SDA for slave response
                            end
                            2'd1: begin
                                scl_oen <= 1'b1;
                            end
                            2'd2: begin
                                rx_ack <= sda_in; //Sample ACK
                            end
                            2'd3: begin
                                scl_oen <= 1'b0;
                                done <= 1'b1;
                            end
                        endcase
                    end
                end

                S_READ_BYTE: begin
                    if(quarter_tick) begin
                        case(phase) 
                            2'd0: begin
                                scl_oen <= 1'b0;
                                sda_oen <= 1'b1; //Release SDA so that slave can drive
                            end
                            2'd1: begin
                                scl_oen <= 1'b1;
                            end
                            2'd2: begin
                                shreg[bit_cnt] <= sda_in; //Sample incoming bit
                            end
                            2'd3: begin
                                scl_oen <= 1'b0;
                                if(bit_cnt == 3'd0) 
                                    rx_data <= {shreg[7:1], sda_in};
                                else bit_cnt <= bit_cnt - 1'b1;
                            end
                        endcase
                    end
                end

                S_MASTER_ACK: begin
                    if(quarter_tick) begin
                        case(phase)
                            2'd0: begin
                                scl_oen <= 1'b0;
                                sda_oen <= ack_in;  //Drive ACK(0) or NACK(1)
                            end
                            2'd1: begin
                                scl_oen <= 1'b1;
                            end
                            2'd2: begin
                                //Hold ACK/NACK stable
                            end
                            2'd3: begin
                                scl_oen <= 1'b0;
                                sda_oen <= 1'b1;
                                done <= 1'b1;
                            end
                        endcase
                    end 
                end

                //In stop we want the sda to rise while scl is high
                S_STOP: begin
                    if(quarter_tick) begin
                        case(phase)
                            2'd0: begin
                                scl_oen <= 1'b0;
                                sda_oen <= 1'd0;
                            end
                            2'd1: begin
                                scl_oen <= 1'b1;
                            end
                            2'd2: begin
                                sda_oen <= 1'b1; //SDA rise while SCL 1(STOP condition)
                            end
                            2'd3: begin
                                done <= 1'b1;
                            end
                        endcase
                    end
                end
                default: ;
            endcase
        end
    end

    always@(*) begin
        busy = (state != S_IDLE);
    end
    
endmodule

Day 076/tb.v
`timescale 1ns / 1ps

module tb_i2c_master();

    parameter CLK_PERIOD   = 20;         // 50 MHz System Clock (20 ns)
    parameter SYS_CLK_FREQ = 50_000_000;
    parameter I2C_BUS_FREQ = 1_000_000;  // 1 MHz Fast-Mode for accelerated simulation

    reg        clk;
    reg        nreset;

    reg        cmd_start;
    reg        cmd_stop;
    reg        cmd_read;
    reg        cmd_write;
    reg  [7:0] tx_data;
    reg        ack_in;

    wire [7:0] rx_data;
    wire       rx_ack;
    wire       busy;
    wire       done;

    wire       scl;
    wire       sda;

    // Physical Open-Drain Pull-Up Resistors
    pullup(scl);
    pullup(sda);

    integer errors = 0;

    // Instantiate I2C Master UUT
    i2c_master #(
        .SYS_CLK_FREQ(SYS_CLK_FREQ),
        .I2C_BUS_FREQ(I2C_BUS_FREQ)
    ) uut (
        .clk(clk),
        .nreset(nreset),
        .cmd_start(cmd_start),
        .cmd_stop(cmd_stop),
        .cmd_read(cmd_read),
        .cmd_write(cmd_write),
        .tx_data(tx_data),
        .ack_in(ack_in),
        .rx_data(rx_data),
        .rx_ack(rx_ack),
        .busy(busy),
        .done(done),
        .scl(scl),
        .sda(sda)
    );

    // 50 MHz System Clock Generator
    always #(CLK_PERIOD / 2) clk = ~clk;

    // -----------------------------------------------------------------
    // Behavioral Emulated I2C Slave Model
    // -----------------------------------------------------------------
    reg slave_sda_driver;
    reg slave_scl_driver;
    reg slave_stretch_en;

    assign sda = (slave_sda_driver == 1'b0) ? 1'b0 : 1'bz;
    assign scl = (slave_scl_driver == 1'b0) ? 1'b0 : 1'bz;

    reg [7:0] slave_received_byte;
    reg [7:0] slave_send_byte;

    task slave_listen_and_ack(input [7:0] expected_data);
        integer i;
        begin
            slave_sda_driver = 1'b1; // Release SDA
            for (i = 7; i >= 0; i = i - 1) begin
                @(posedge scl);
                slave_received_byte[i] = sda;
                @(negedge scl);
            end

            // Verify Data
            if (slave_received_byte !== expected_data) begin
                $display("[FAIL] Slave received 0x%02h, Expected: 0x%02h", slave_received_byte, expected_data);
                errors = errors + 1;
            end else begin
                $display("[PASS] Slave successfully received byte: 0x%02h", slave_received_byte);
            end

            // Drive ACK (0) on 9th SCL cycle
            slave_sda_driver = 1'b0;
            @(negedge scl);
            slave_sda_driver = 1'b1; // Release
        end
    endtask

    task slave_transmit_and_receive_ack(input [7:0] byte_to_send);
        integer i;
        begin
            slave_send_byte = byte_to_send;
            for (i = 7; i >= 0; i = i - 1) begin
                slave_sda_driver = slave_send_byte[i];
                @(posedge scl);
                @(negedge scl);
            end

            // Release SDA for Master ACK
            slave_sda_driver = 1'b1;
            @(posedge scl);
            $display("[INFO] Slave sampled Master ACK/NACK: %0b", sda);
            @(negedge scl);
        end
    endtask

    // -----------------------------------------------------------------
    // Slave Listener with Mid-Byte Clock Stretch Injection
    // -----------------------------------------------------------------
    task slave_listen_with_stretch(input [7:0] expected_data);
        integer i;
        begin
            slave_sda_driver = 1'b1; // Release SDA

            for (i = 7; i >= 0; i = i - 1) begin
                @(posedge scl);
                slave_received_byte[i] = sda;
                @(negedge scl);

                // Inject clock stretch right after Bit 4
                if (i == 4) begin
                    slave_scl_driver = 1'b0; // Clamp SCL low
                    $display("[INFO] Slave asserted clock stretch (SCL held low)");
                    #(CLK_PERIOD * 40);      // Hold low for 40 system clock cycles
                    slave_scl_driver = 1'b1; // Release SCL
                    $display("[INFO] Slave released clock stretch");
                end
            end

            // Verify Data
            if (slave_received_byte !== expected_data) begin
                $display("[FAIL] Slave received 0x%02h, Expected: 0x%02h", slave_received_byte, expected_data);
                errors = errors + 1;
            end else begin
                $display("[PASS] Slave successfully received byte with stretch: 0x%02h", slave_received_byte);
            end

            // Drive ACK on 9th SCL cycle
            slave_sda_driver = 1'b0;
            @(negedge scl);
            slave_sda_driver = 1'b1;
        end
    endtask

    // -----------------------------------------------------------------
    // Master Host Test Program
    // -----------------------------------------------------------------
    initial begin
        $dumpfile("dump.vcd");
        $dumpvars(0, tb_i2c_master);

        clk              = 0;
        nreset           = 0;
        cmd_start        = 0;
        cmd_stop         = 0;
        cmd_read         = 0;
        cmd_write        = 0;
        tx_data          = 8'h00;
        ack_in           = 0;
        slave_sda_driver = 1;
        slave_scl_driver = 1;
        slave_stretch_en = 0;

        #(CLK_PERIOD * 5);
        @(negedge clk);
        nreset = 1;
        #(CLK_PERIOD * 5);

        $display("\n=======================================================================================================");
        $display("                   DAY 76: I2C MASTER PROTOCOL ENGINE VERIFICATION SUITE                                ");
        $display("=======================================================================================================");

        // --- TEST 1: START + Write Slave Device Address (0x50 << 1 | 0 = 0xA0) ---
        $display("\n--- TEST 1: Generate START Condition and Write Device Address (0xA0) ---");
        @(negedge clk);
        cmd_start = 1;
        @(negedge clk);
        cmd_start = 0;
        @(posedge done);

        fork
            begin
                @(negedge clk);
                cmd_write = 1;
                tx_data   = 8'hA0;
                @(negedge clk);
                cmd_write = 0;
                @(posedge done);
            end
            begin
                slave_listen_and_ack(8'hA0);
            end
        join

        if (rx_ack == 1'b0)
            $display("[PASS] Master successfully captured Slave ACK for Address 0xA0");
        else begin
            $display("[FAIL] Master captured NACK for Address 0xA0!");
            errors = errors + 1;
        end

        // --- TEST 2: Write Internal Register Data (0x3C) ---
        $display("\n--- TEST 2: Write Payload Data Byte (0x3C) ---");
        fork
            begin
                @(negedge clk);
                cmd_write = 1;
                tx_data   = 8'h3C;
                @(negedge clk);
                cmd_write = 0;
                @(posedge done);
            end
            begin
                slave_listen_and_ack(8'h3C);
            end
        join

        // --- TEST 3: Repeated START + Read Mode (0x50 << 1 | 1 = 0xA1) ---
        $display("\n--- TEST 3: Repeated START + Read Device Address (0xA1) ---");
        @(negedge clk);
        cmd_start = 1; // Repeated START
        @(negedge clk);
        cmd_start = 0;
        @(posedge done);

        fork
            begin
                @(negedge clk);
                cmd_write = 1;
                tx_data   = 8'hA1;
                @(negedge clk);
                cmd_write = 0;
                @(posedge done);
            end
            begin
                slave_listen_and_ack(8'hA1);
            end
        join

        // --- TEST 4: Read Byte from Slave (Slave transmits 0xE7, Master returns NACK) ---
        $display("\n--- TEST 4: Read Byte (0xE7) with Master NACK ---");
        fork
            begin
                @(negedge clk);
                cmd_read = 1;
                ack_in   = 1'b1; // Send NACK at end of read
                @(negedge clk);
                cmd_read = 0;
                @(posedge done);
            end
            begin
                slave_transmit_and_receive_ack(8'hE7);
            end
        join

        if (rx_data === 8'hE7)
            $display("[PASS] Master successfully captured Read Data: 0x%02h", rx_data);
        else begin
            $display("[FAIL] Master Read mismatch! Got: 0x%02h, Expected: 0xE7", rx_data);
            errors = errors + 1;
        end

        // --- TEST 5: Clock Stretching Verification ---
        $display("\n--- TEST 5: Clock Stretching Recovery Test ---");
        fork
            begin
                @(negedge clk);
                cmd_write = 1;
                tx_data   = 8'h55;
                @(negedge clk);
                cmd_write = 0;
                @(posedge done);
            end
            begin
                slave_listen_with_stretch(8'h55);
            end
        join

        // --- TEST 6: STOP Condition ---
        $display("\n--- TEST 6: Generate STOP Condition ---");
        @(negedge clk);
        cmd_stop = 1;
        @(negedge clk);
        cmd_stop = 0;
        @(posedge done);

        #(CLK_PERIOD * 20);
        $display("\n=======================================================================================================");
        if (errors == 0)
            $display("   DAY 76 I2C MASTER VERIFICATION SUCCESSFUL: 0 ERRORS DETECTED! (PASSED)");
        else
            $display("   VERIFICATION FAILED WITH %0d ERROR(S)!", errors);
        $display("=======================================================================================================\n");

        $finish;
    end

endmodule

Day 076/dump.vcd
$date
	Fri Sep 18 15:38:40 2026
$end
$version
	Icarus Verilog
$end
$timescale
	1ps
$end
$scope module tb_i2c_master $end
$var wire 1 ! scl $end
$var wire 1 " sda $end
$var wire 8 # rx_data [7:0] $end
$var wire 1 $ rx_ack $end
$var wire 1 % done $end
$var wire 1 & busy $end
$var parameter 32 ' CLK_PERIOD $end
$var parameter 32 ( I2C_BUS_FREQ $end
$var parameter 32 ) SYS_CLK_FREQ $end
$var reg 1 * ack_in $end
$var reg 1 + clk $end
$var reg 1 , cmd_read $end
$var reg 1 - cmd_start $end
$var reg 1 . cmd_stop $end
$var reg 1 / cmd_write $end
$var reg 1 0 nreset $end
$var reg 8 1 slave_received_byte [7:0] $end
$var reg 1 2 slave_scl_driver $end
$var reg 1 3 slave_sda_driver $end
$var reg 8 4 slave_send_byte [7:0] $end
$var reg 1 5 slave_stretch_en $end
$var reg 8 6 tx_data [7:0] $end
$var integer 32 7 errors [31:0] $end
$scope module uut $end
$var wire 1 * ack_in $end
$var wire 1 + clk $end
$var wire 1 , cmd_read $end
$var wire 1 - cmd_start $end
$var wire 1 . cmd_stop $end
$var wire 1 / cmd_write $end
$var wire 1 0 nreset $end
$var wire 1 ! scl $end
$var wire 1 " sda $end
$var wire 8 8 tx_data [7:0] $end
$var wire 1 9 sda_in $end
$var wire 1 : scl_in $end
$var wire 1 ; quarter_tick $end
$var parameter 32 < CNT_WIDTH $end
$var parameter 32 = I2C_BUS_FREQ $end
$var parameter 64 > QUARTER_DIV $end
$var parameter 32 ? SYS_CLK_FREQ $end
$var parameter 3 @ S_IDLE $end
$var parameter 3 A S_MASTER_ACK $end
$var parameter 3 B S_READ_BYTE $end
$var parameter 3 C S_SLAVE_ACK $end
$var parameter 3 D S_START $end
$var parameter 3 E S_STOP $end
$var parameter 3 F S_WRITE_BYTE $end
$var reg 3 G bit_cnt [2:0] $end
$var reg 1 & busy $end
$var reg 1 % done $end
$var reg 3 H next_state [2:0] $end
$var reg 2 I phase [1:0] $end
$var reg 4 J q_cnt [3:0] $end
$var reg 1 $ rx_ack $end
$var reg 8 K rx_data [7:0] $end
$var reg 1 L scl_oen $end
$var reg 2 M scl_sync [1:0] $end
$var reg 1 N sda_oen $end
$var reg 2 O sda_sync [1:0] $end
$var reg 8 P shreg [7:0] $end
$var reg 3 Q state [2:0] $end
$var reg 1 R stretch_active $end
$upscope $end
$scope task slave_listen_and_ack $end
$var reg 8 S expected_data [7:0] $end
$var integer 32 T i [31:0] $end
$upscope $end
$scope task slave_listen_with_stretch $end
$var reg 8 U expected_data [7:0] $end
$var integer 32 V i [31:0] $end
$upscope $end
$scope task slave_transmit_and_receive_ack $end
$var reg 8 W byte_to_send [7:0] $end
$var integer 32 X i [31:0] $end
$upscope $end
$upscope $end
$enddefinitions $end
$comment Show the parameter values. $end
$dumpall
b10 F
b110 E
b1 D
b100 C
b11 B
b101 A
b0 @
b10111110101111000010000000 ?
b1100 >
b11110100001001000000 =
b100 <
b10111110101111000010000000 )
b11110100001001000000 (
b10100 '
$end
#0
$dumpvars
bx X
bx W
bx V
bx U
bx T
bx S
0R
b0 Q
b0 P
b11 O
1N
b11 M
1L
b0 K
b0 J
b0 I
b0 H
b111 G
0;
1:
19
b0 8
b0 7
b0 6
05
bx 4
13
12
bx 1
00
0/
0.
0-
0,
0+
0*
0&
0%
1$
b0 #
1"
1!
$end
#10000
1+
#20000
0+
#30000
1+
#40000
0+
#50000
1+
#60000
0+
#70000
1+
#80000
0+
#90000
1+
#100000
10
0+
#110000
1+
#120000
0+
#130000
1+
#140000
0+
#150000
1+
#160000
0+
#170000
1+
#180000
0+
#190000
1+
#200000
b1 H
1-
0+
#210000
1&
b1 Q
1+
#220000
0-
0+
#230000
b1 J
1+
#240000
0+
#250000
b10 J
1+
#260000
0+
#270000
b11 J
1+
#280000
0+
#290000
b100 J
1+
#300000
0+
#310000
b101 J
1+
#320000
0+
#330000
b110 J
1+
#340000
0+
#350000
b111 J
1+
#360000
0+
#370000
b1000 J
1+
#380000
0+
#390000
b1001 J
1+
#400000
0+
#410000
b1010 J
1+
#420000
0+
#430000
1;
b1011 J
1+
#440000
0+
#450000
b1 I
0;
b0 J
1+
#460000
0+
#470000
b1 J
1+
#480000
0+
#490000
b10 J
1+
#500000
0+
#510000
b11 J
1+
#520000
0+
#530000
b100 J
1+
#540000
0+
#550000
b101 J
1+
#560000
0+
#570000
b110 J
1+
#580000
0+
#590000
b111 J
1+
#600000
0+
#610000
b1000 J
1+
#620000
0+
#630000
b1001 J
1+
#640000
0+
#650000
b1010 J
1+
#660000
0+
#670000
1;
b1011 J
1+
#680000
0+
#690000
b10 I
0;
b0 J
1+
#700000
0+
#710000
b1 J
1+
#720000
0+
#730000
b10 J
1+
#740000
0+
#750000
b11 J
1+
#760000
0+
#770000
b100 J
1+
#780000
0+
#790000
b101 J
1+
#800000
0+
#810000
b110 J
1+
#820000
0+
#830000
b111 J
1+
#840000
0+
#850000
b1000 J
1+
#860000
0+
#870000
b1001 J
1+
#880000
0+
#890000
b1010 J
1+
#900000
0+
#910000
1;
b1011 J
1+
#920000
0+
#930000
0"
0N
b11 I
0;
b0 J
1+
#940000
0+
#950000
b10 O
b1 J
1+
#960000
0+
#970000
09
b10 J
b0 O
1+
#980000
0+
#990000
b11 J
1+
#1000000
0+
#1010000
b100 J
1+
#1020000
0+
#1030000
b101 J
1+
#1040000
0+
#1050000
b110 J
1+
#1060000
0+
#1070000
b111 J
1+
#1080000
0+
#1090000
b1000 J
1+
#1100000
0+
#1110000
b1001 J
1+
#1120000
0+
#1130000
b1010 J
1+
#1140000
0+
#1150000
b0 H
1;
b1011 J
1+
#1160000
0+
#1170000
0!
b111 T
b10100000 S
0&
1%
0L
b0 Q
b0 I
0;
b0 J
1+
#1180000
b10 H
b10100000 6
b10100000 8
1/
0+
#1190000
1&
b10 M
b10 Q
b10100000 P
0%
1+
#1200000
0/
0+
#1210000
0:
b1 J
b0 M
1+
#1220000
0+
#1230000
b10 J
1+
#1240000
0+
#1250000
b11 J
1+
#1260000
0+
#1270000
b100 J
1+
#1280000
0+
#1290000
b101 J
1+
#1300000
0+
#1310000
b110 J
1+
#1320000
0+
#1330000
b111 J
1+
#1340000
0+
#1350000
b1000 J
1+
#1360000
0+
#1370000
b1001 J
1+
#1380000
0+
#1390000
b1010 J
1+
#1400000
0+
#1410000
1;
b1011 J
1+
#1420000
0+
#1430000
1"
b1 I
0;
b0 J
1N
1+
#1440000
0+
#1450000
b1 J
b1 O
1+
#1460000
0+
#1470000
19
b11 O
b10 J
1+
#1480000
0+
#1490000
b11 J
1+
#1500000
0+
#1510000
b100 J
1+
#1520000
0+
#1530000
b101 J
1+
#1540000
0+
#1550000
b110 J
1+
#1560000
0+
#1570000
b111 J
1+
#1580000
0+
#1590000
b1000 J
1+
#1600000
0+
#1610000
b1001 J
1+
#1620000
0+
#1630000
b1010 J
1+
#1640000
0+
#1650000
1;
b1011 J
1+
#1660000
0+
#1670000
b1xxxxxxx 1
1!
b10 I
0;
b0 J
1L
1+
#1680000
0+
#1690000
b1 J
b1 M
1+
#1700000
0+
#1710000
1:
b11 M
b10 J
1+
#1720000
0+
#1730000
b11 J
1+
#1740000
0+
#1750000
b100 J
1+
#1760000
0+
#1770000
b101 J
1+
#1780000
0+
#1790000
b110 J
1+
#1800000
0+
#1810000
b111 J
1+
#1820000
0+
#1830000
b1000 J
1+
#1840000
0+
#1850000
b1001 J
1+
#1860000
0+
#1870000
b1010 J
1+
#1880000
0+
#1890000
1;
b1011 J
1+
#1900000
0+
#1910000
b11 I
0;
b0 J
1+
#1920000
0+
#1930000
b1 J
1+
#1940000
0+
#1950000
b10 J
1+
#1960000
0+
#1970000
b11 J
1+
#1980000
0+
#1990000
b100 J
1+
#2000000
0+
#2010000
b101 J
1+
#2020000
0+
#2030000
b110 J
1+
#2040000
0+
#2050000
b111 J
1+
#2060000
0+
#2070000
b1000 J
1+
#2080000
0+
#2090000
b1001 J
1+
#2100000
0+
#2110000
b1010 J
1+
#2120000
0+
#2130000
1;
b1011 J
1+
#2140000
0+
#2150000
b110 T
0!
b0 I
0;
b0 J
b110 G
0L
1+
#2160000
0+
#2170000
b1 J
b10 M
1+
#2180000
0+
#2190000
0:
b0 M
b10 J
1+
#2200000
0+
#2210000
b11 J
1+
#2220000
0+
#2230000
b100 J
1+
#2240000
0+
#2250000
b101 J
1+
#2260000
0+
#2270000
b110 J
1+
#2280000
0+
#2290000
b111 J
1+
#2300000
0+
#2310000
b1000 J
1+
#2320000
0+
#2330000
b1001 J
1+
#2340000
0+
#2350000
b1010 J
1+
#2360000
0+
#2370000
1;
b1011 J
1+
#2380000
0+
#2390000
0"
b1 I
0;
b0 J
0N
1+
#2400000
0+
#2410000
b1 J
b10 O
1+
#2420000
0+
#2430000
09
b0 O
b10 J
1+
#2440000
0+
#2450000
b11 J
1+
#2460000
0+
#2470000
b100 J
1+
#2480000
0+
#2490000
b101 J
1+
#2500000
0+
#2510000
b110 J
1+
#2520000
0+
#2530000
b111 J
1+
#2540000
0+
#2550000
b1000 J
1+
#2560000
0+
#2570000
b1001 J
1+
#2580000
0+
#2590000
b1010 J
1+
#2600000
0+
#2610000
1;
b1011 J
1+
#2620000
0+
#2630000
b10xxxxxx 1
1!
b10 I
0;
b0 J
1L
1+
#2640000
0+
#2650000
b1 J
b1 M
1+
#2660000
0+
#2670000
1:
b11 M
b10 J
1+
#2680000
0+
#2690000
b11 J
1+
#2700000
0+
#2710000
b100 J
1+
#2720000
0+
#2730000
b101 J
1+
#2740000
0+
#2750000
b110 J
1+
#2760000
0+
#2770000
b111 J
1+
#2780000
0+
#2790000
b1000 J
1+
#2800000
0+
#2810000
b1001 J
1+
#2820000
0+
#2830000
b1010 J
1+
#2840000
0+
#2850000
1;
b1011 J
1+
#2860000
0+
#2870000
b11 I
0;
b0 J
1+
#2880000
0+
#2890000
b1 J
1+
#2900000
0+
#2910000
b10 J
1+
#2920000
0+
#2930000
b11 J
1+
#2940000
0+
#2950000
b100 J
1+
#2960000
0+
#2970000
b101 J
1+
#2980000
0+
#2990000
b110 J
1+
#3000000
0+
#3010000
b111 J
1+
#3020000
0+
#3030000
b1000 J
1+
#3040000
0+
#3050000
b1001 J
1+
#3060000
0+
#3070000
b1010 J
1+
#3080000
0+
#3090000
1;
b1011 J
1+
#3100000
0+
#3110000
b101 T
0!
b0 I
0;
b0 J
b101 G
0L
1+
#3120000
0+
#3130000
b1 J
b10 M
1+
#3140000
0+
#3150000
0:
b0 M
b10 J
1+
#3160000
0+
#3170000
b11 J
1+
#3180000
0+
#3190000
b100 J
1+
#3200000
0+
#3210000
b101 J
1+
#3220000
0+
#3230000
b110 J
1+
#3240000
0+
#3250000
b111 J
1+
#3260000
0+
#3270000
b1000 J
1+
#3280000
0+
#3290000
b1001 J
1+
#3300000
0+
#3310000
b1010 J
1+
#3320000
0+
#3330000
1;
b1011 J
1+
#3340000
0+
#3350000
1"
b1 I
0;
b0 J
1N
1+
#3360000
0+
#3370000
b1 J
b1 O
1+
#3380000
0+
#3390000
19
b11 O
b10 J
1+
#3400000
0+
#3410000
b11 J
1+
#3420000
0+
#3430000
b100 J
1+
#3440000
0+
#3450000
b101 J
1+
#3460000
0+
#3470000
b110 J
1+
#3480000
0+
#3490000
b111 J
1+
#3500000
0+
#3510000
b1000 J
1+
#3520000
0+
#3530000
b1001 J
1+
#3540000
0+
#3550000
b1010 J
1+
#3560000
0+
#3570000
1;
b1011 J
1+
#3580000
0+
#3590000
b101xxxxx 1
1!
b10 I
0;
b0 J
1L
1+
#3600000
0+
#3610000
b1 J
b1 M
1+
#3620000
0+
#3630000
1:
b11 M
b10 J
1+
#3640000
0+
#3650000
b11 J
1+
#3660000
0+
#3670000
b100 J
1+
#3680000
0+
#3690000
b101 J
1+
#3700000
0+
#3710000
b110 J
1+
#3720000
0+
#3730000
b111 J
1+
#3740000
0+
#3750000
b1000 J
1+
#3760000
0+
#3770000
b1001 J
1+
#3780000
0+
#3790000
b1010 J
1+
#3800000
0+
#3810000
1;
b1011 J
1+
#3820000
0+
#3830000
b11 I
0;
b0 J
1+
#3840000
0+
#3850000
b1 J
1+
#3860000
0+
#3870000
b10 J
1+
#3880000
0+
#3890000
b11 J
1+
#3900000
0+
#3910000
b100 J
1+
#3920000
0+
#3930000
b101 J
1+
#3940000
0+
#3950000
b110 J
1+
#3960000
0+
#3970000
b111 J
1+
#3980000
0+
#3990000
b1000 J
1+
#4000000
0+
#4010000
b1001 J
1+
#4020000
0+
#4030000
b1010 J
1+
#4040000
0+
#4050000
1;
b1011 J
1+
#4060000
0+
#4070000
b100 T
0!
b0 I
0;
b0 J
b100 G
0L
1+
#4080000
0+
#4090000
b1 J
b10 M
1+
#4100000
0+
#4110000
0:
b0 M
b10 J
1+
#4120000
0+
#4130000
b11 J
1+
#4140000
0+
#4150000
b100 J
1+
#4160000
0+
#4170000
b101 J
1+
#4180000
0+
#4190000
b110 J
1+
#4200000
0+
#4210000
b111 J
1+
#4220000
0+
#4230000
b1000 J
1+
#4240000
0+
#4250000
b1001 J
1+
#4260000
0+
#4270000
b1010 J
1+
#4280000
0+
#4290000
1;
b1011 J
1+
#4300000
0+
#4310000
0"
b1 I
0;
b0 J
0N
1+
#4320000
0+
#4330000
b1 J
b10 O
1+
#4340000
0+
#4350000
09
b0 O
b10 J
1+
#4360000
0+
#4370000
b11 J
1+
#4380000
0+
#4390000
b100 J
1+
#4400000
0+
#4410000
b101 J
1+
#4420000
0+
#4430000
b110 J
1+
#4440000
0+
#4450000
b111 J
1+
#4460000
0+
#4470000
b1000 J
1+
#4480000
0+
#4490000
b1001 J
1+
#4500000
0+
#4510000
b1010 J
1+
#4520000
0+
#4530000
1;
b1011 J
1+
#4540000
0+
#4550000
b1010xxxx 1
1!
b10 I
0;
b0 J
1L
1+
#4560000
0+
#4570000
b1 J
b1 M
1+
#4580000
0+
#4590000
1:
b11 M
b10 J
1+
#4600000
0+
#4610000
b11 J
1+
#4620000
0+
#4630000
b100 J
1+
#4640000
0+
#4650000
b101 J
1+
#4660000
0+
#4670000
b110 J
1+
#4680000
0+
#4690000
b111 J
1+
#4700000
0+
#4710000
b1000 J
1+
#4720000
0+
#4730000
b1001 J
1+
#4740000
0+
#4750000
b1010 J
1+
#4760000
0+
#4770000
1;
b1011 J
1+
#4780000
0+
#4790000
b11 I
0;
b0 J
1+
#4800000
0+
#4810000
b1 J
1+
#4820000
0+
#4830000
b10 J
1+
#4840000
0+
#4850000
b11 J
1+
#4860000
0+
#4870000
b100 J
1+
#4880000
0+
#4890000
b101 J
1+
#4900000
0+
#4910000
b110 J
1+
#4920000
0+
#4930000
b111 J
1+
#4940000
0+
#4950000
b1000 J
1+
#4960000
0+
#4970000
b1001 J
1+
#4980000
0+
#4990000
b1010 J
1+
#5000000
0+
#5010000
1;
b1011 J
1+
#5020000
0+
#5030000
b11 T
0!
b0 I
0;
b0 J
b11 G
0L
1+
#5040000
0+
#5050000
b1 J
b10 M
1+
#5060000
0+
