Day 058/alu.v
module alu#(parameter DATA_WIDTH = 16
)(
    input clk, nreset, 
    input [3:0] alu_op,
    input [DATA_WIDTH-1:0] A, B,
    output zero, negative,
    output reg carry, overflow,
    output reg [DATA_WIDTH-1:0] result
);
    // Different opcodes
    localparam ADD = 4'd0;
    localparam SUB = 4'd1;
    localparam INC = 4'd2;
    localparam DEC = 4'd3;
    localparam AND = 4'd4;
    localparam OR  = 4'd5;
    localparam XOR = 4'd6;
    localparam NOT = 4'd7;
    localparam NAND= 4'd8;
    localparam NOR = 4'd9;
    localparam SLL = 4'd10; //Logical Left Shift
    localparam SRL = 4'd11; //Logical Right Shift
    localparam SRA = 4'd12; //Arithmetic Right Shift
    localparam ROL = 4'd13; //Rotate A left by B
    localparam ROR = 4'd14; //Rotate A right by B
    localparam PASS= 4'd15;

    //Shift bits
    localparam SHIFT_BITS = $clog2(DATA_WIDTH);
    wire [SHIFT_BITS-1:0] shift_amt = B[SHIFT_BITS-1:0];

    //Select B_eff and C_in for different cases of Opcodes
    reg [DATA_WIDTH-1:0] B_eff;
    reg C_in;
    always@(*) begin
        case(alu_op)
            ADD: begin
                B_eff = B;
                C_in = 1'b0;
            end
            SUB: begin
                B_eff = ~B;
                C_in = 1'b1;
            end
            INC: begin
                B_eff = 0;
                C_in = 1'b1;
            end
            DEC: begin
                B_eff = {DATA_WIDTH{1'b1}};
                C_in = 0;
            end
            default: begin
                B_eff = 0;
                C_in = 0;
            end
        endcase
    end

    //Adder
    wire [DATA_WIDTH:0] arith_full = A + B_eff + C_in;
    wire [DATA_WIDTH-1:0] arith_result = arith_full[DATA_WIDTH-1:0];
    wire arith_carry = arith_full[DATA_WIDTH];
    wire arith_overflow = (A[DATA_WIDTH-1] == B_eff[DATA_WIDTH-1]) && (arith_result[DATA_WIDTH-1] != A[DATA_WIDTH-1]);

    //Full operational mux
    reg [DATA_WIDTH-1:0] result_comb;
    reg carry_comb, overflow_comb;

    always@(*) begin
        carry_comb = 0;
        overflow_comb = 0;

        case(alu_op) 
            ADD, SUB, INC, DEC: begin
                result_comb = arith_result;
                carry_comb = arith_carry;
                overflow_comb = arith_overflow;
            end
            AND: result_comb = A & B;
            OR: result_comb = A | B;
            XOR: result_comb = A ^ B;
            NOT: result_comb = ~A;
            NAND: result_comb = ~(A & B);
            NOR: result_comb = ~(A | B);

            SLL: result_comb = A << shift_amt;
            SRL: result_comb = A >> shift_amt;
            SRA: result_comb = $signed(A) >>> shift_amt;
            ROL: result_comb = (A << shift_amt) | (A >> (DATA_WIDTH - shift_amt));
            ROR: result_comb = (A >> shift_amt) | (A << (DATA_WIDTH - shift_amt));

            PASS: result_comb = A;
            default: result_comb = 0;
        endcase
    end

    //Output Flipflop
    always@(posedge clk or negedge nreset) begin
        if(!nreset) begin
            result <= 0;
            carry <= 0;
            overflow <= 0;
        end
        else begin
            result <= result_comb;
            carry <= carry_comb;
            overflow <= overflow_comb;
        end
    end

    //Output assignments
    assign zero = (result == {DATA_WIDTH{1'b0}});
    assign negative = result[DATA_WIDTH-1];
endmodule

Day 058/tb.v
`timescale 1ns / 1ps

module tb_alu();

    parameter DATA_WIDTH = 16;
    parameter CLK_PERIOD = 10;

    reg                  clk;
    reg                  nreset;
    reg  [3:0]           alu_op;
    reg  [DATA_WIDTH-1:0] A, B;
    wire                 zero, negative, carry, overflow;
    wire [DATA_WIDTH-1:0] result;

    integer errors = 0;

    // Instantiate ALU
    alu #(
        .DATA_WIDTH(DATA_WIDTH)
    ) uut (
        .clk(clk),
        .nreset(nreset),
        .alu_op(alu_op),
        .A(A),
        .B(B),
        .zero(zero),
        .negative(negative),
        .carry(carry),
        .overflow(overflow),
        .result(result)
    );

    // 100 MHz Clock Generator
    always #(CLK_PERIOD / 2) clk = ~clk;

    initial begin
        $dumpfile("dump.vcd");
        $dumpvars(0);

        clk    = 0;
        nreset = 0;
        alu_op = 0;
        A      = 0;
        B      = 0;

        // Apply Reset
        #(CLK_PERIOD * 2);
        nreset = 1;
        #(CLK_PERIOD);

        $display("\n====================================================");
        $display("   DAY 58: FULL 16-OPERATION ALU CORE VERIFICATION");
        $display("====================================================\n");

        // -------------------------------------------------------------
        // GROUP 1: ARITHMETIC OPERATIONS (Opcodes 0 to 3)
        // -------------------------------------------------------------
        $display("--- Group 1: Arithmetic Operations ---");

        // Op 0: ADD (50 + 25 = 75)
        @(negedge clk); alu_op = 4'd0; A = 16'd50; B = 16'd25;
        @(posedge clk); #1;
        if (result === 16'd75 && !zero && !negative && !carry && !overflow)
            $display("[PASS] Op  0 (ADD) :  50 + 25 = %0d", result);
        else begin $display("[FAIL] Op 0 (ADD) Mismatch!"); errors = errors + 1; end

        // Op 1: SUB (100 - 100 = 0) -> Tests Zero Flag (Z)
        @(negedge clk); alu_op = 4'd1; A = 16'd100; B = 16'd100;
        @(posedge clk); #1;
        if (result === 16'd0 && zero)
            $display("[PASS] Op  1 (SUB) : 100 - 100 = %0d (Zero Flag Z=1 Asserted)", result);
        else begin $display("[FAIL] Op 1 (SUB) Mismatch!"); errors = errors + 1; end

        // Op 2: INC (15 + 1 = 16)
        @(negedge clk); alu_op = 4'd2; A = 16'h000F; B = 16'h1234; // B should be ignored
        @(posedge clk); #1;
        if (result === 16'h0010)
            $display("[PASS] Op  2 (INC) : 0x000F + 1 = 0x%04h", result);
        else begin $display("[FAIL] Op 2 (INC) Mismatch!"); errors = errors + 1; end

        // Op 3: DEC (0 - 1 = 0xFFFF / -1) -> Tests Negative Flag (N)
        @(negedge clk); alu_op = 4'd3; A = 16'h0000; B = 16'h1234;
        @(posedge clk); #1;
        if (result === 16'hFFFF && negative)
            $display("[PASS] Op  3 (DEC) : 0x0000 - 1 = 0x%04h (Negative Flag N=1)", result);
        else begin $display("[FAIL] Op 3 (DEC) Mismatch!"); errors = errors + 1; end

        // Extra Arithmetic Check: Signed Overflow Flag (V=1)
        @(negedge clk); alu_op = 4'd0; A = 16'h7FFF; B = 16'h0001; // +32767 + 1 = -32768
        @(posedge clk); #1;
        if (result === 16'h8000 && overflow && negative)
            $display("[PASS] Edge Case    : 0x7FFF + 1 = 0x%04h (Signed Overflow V=1, N=1)", result);
        else begin $display("[FAIL] Signed Overflow Check Failed!"); errors = errors + 1; end

        // -------------------------------------------------------------
        // GROUP 2: BITWISE LOGIC OPERATIONS (Opcodes 4 to 9)
        // -------------------------------------------------------------
        $display("\n--- Group 2: Bitwise Logic Operations ---");

        // Op 4: AND
        @(negedge clk); alu_op = 4'd4; A = 16'hFF00; B = 16'h0F0F;
        @(posedge clk); #1;
        if (result === 16'h0F00)
            $display("[PASS] Op  4 (AND) : 0xFF00 & 0x0F0F = 0x%04h", result);
        else begin $display("[FAIL] Op 4 (AND) Mismatch!"); errors = errors + 1; end

        // Op 5: OR
        @(negedge clk); alu_op = 4'd5; A = 16'hFF00; B = 16'h00FF;
        @(posedge clk); #1;
        if (result === 16'hFFFF)
            $display("[PASS] Op  5 (OR)  : 0xFF00 | 0x00FF = 0x%04h", result);
        else begin $display("[FAIL] Op 5 (OR) Mismatch!"); errors = errors + 1; end

        // Op 6: XOR
        @(negedge clk); alu_op = 4'd6; A = 16'hAAAA; B = 16'h5555;
        @(posedge clk); #1;
        if (result === 16'hFFFF)
            $display("[PASS] Op  6 (XOR) : 0xAAAA ^ 0x5555 = 0x%04h", result);
        else begin $display("[FAIL] Op 6 (XOR) Mismatch!"); errors = errors + 1; end

        // Op 7: NOT
        @(negedge clk); alu_op = 4'd7; A = 16'h1234; B = 16'h0000;
        @(posedge clk); #1;
        if (result === 16'hEDCB)
            $display("[PASS] Op  7 (NOT) : ~0x1234 = 0x%04h", result);
        else begin $display("[FAIL] Op 7 (NOT) Mismatch!"); errors = errors + 1; end

        // Op 8: NAND
        @(negedge clk); alu_op = 4'd8; A = 16'hFFFF; B = 16'hF000;
        @(posedge clk); #1;
        if (result === 16'h0FFF)
            $display("[PASS] Op  8 (NAND): ~(0xFFFF & 0xF000) = 0x%04h", result);
        else begin $display("[FAIL] Op 8 (NAND) Mismatch!"); errors = errors + 1; end

        // Op 9: NOR
        @(negedge clk); alu_op = 4'd9; A = 16'h00FF; B = 16'h0000;
        @(posedge clk); #1;
        if (result === 16'hFF00)
            $display("[PASS] Op  9 (NOR) : ~(0x00FF | 0x0000) = 0x%04h", result);
        else begin $display("[FAIL] Op 9 (NOR) Mismatch!"); errors = errors + 1; end

        // -------------------------------------------------------------
        // GROUP 3: SHIFT & ROTATE OPERATIONS (Opcodes 10 to 14)
        // -------------------------------------------------------------
        $display("\n--- Group 3: Shift & Rotate Operations ---");

        // Op 10: SLL (Logical Shift Left)
        @(negedge clk); alu_op = 4'd10; A = 16'h0001; B = 16'd8;
        @(posedge clk); #1;
        if (result === 16'h0100)
            $display("[PASS] Op 10 (SLL) : 0x0001 << 8 = 0x%04h", result);
        else begin $display("[FAIL] Op 10 (SLL) Mismatch!"); errors = errors + 1; end

        // Op 11: SRL (Logical Shift Right)
        @(negedge clk); alu_op = 4'd11; A = 16'h8000; B = 16'd4;
        @(posedge clk); #1;
        if (result === 16'h0800)
            $display("[PASS] Op 11 (SRL) : 0x8000 >> 4 = 0x%04h", result);
        else begin $display("[FAIL] Op 11 (SRL) Mismatch!"); errors = errors + 1; end

        // Op 12: SRA (Arithmetic Shift Right - Sign Extended)
        @(negedge clk); alu_op = 4'd12; A = 16'h8000; B = 16'd4; // -32768 >>> 4 = -2048 (0xF800)
        @(posedge clk); #1;
        if (result === 16'hF800 && negative)
            $display("[PASS] Op 12 (SRA) : 0x8000 >>> 4 = 0x%04h (Sign preserved N=1)", result);
        else begin $display("[FAIL] Op 12 (SRA) Mismatch! Got 0x%04h", result); errors = errors + 1; end

        // Op 13: ROL (Rotate Left)
        @(negedge clk); alu_op = 4'd13; A = 16'hC001; B = 16'd2; // 1100_0000_0000_0001 << 2 rot -> 0000_0000_0000_0111 (0x0007)
        @(posedge clk); #1;
        if (result === 16'h0007)
            $display("[PASS] Op 13 (ROL) : Rotate Left 0xC001 by 2 = 0x%04h", result);
        else begin $display("[FAIL] Op 13 (ROL) Mismatch! Got 0x%04h", result); errors = errors + 1; end

        // Op 14: ROR (Rotate Right)
        @(negedge clk); alu_op = 4'd14; A = 16'h0003; B = 16'd2; // 0000_0000_0000_0011 >> 2 rot -> 1100_0000_0000_0000 (0xC000)
        @(posedge clk); #1;
        if (result === 16'hC000 && negative)
            $display("[PASS] Op 14 (ROR) : Rotate Right 0x0003 by 2 = 0x%04h", result);
        else begin $display("[FAIL] Op 14 (ROR) Mismatch! Got 0x%04h", result); errors = errors + 1; end

        // -------------------------------------------------------------
        // GROUP 4: PASS-THROUGH (Opcode 15)
        // -------------------------------------------------------------
        $display("\n--- Group 4: Pass-Through Operation ---");

        // Op 15: PASS
        @(negedge clk); alu_op = 4'd15; A = 16'hA5A5; B = 16'h1234;
        @(posedge clk); #1;
        if (result === 16'hA5A5)
            $display("[PASS] Op 15 (PASS): Output = 0x%04h (Operand A passed unchanged)", result);
        else begin $display("[FAIL] Op 15 (PASS) Mismatch!"); errors = errors + 1; end

        // SUMMARY
        $display("\n====================================================");
        if (errors == 0) $display(" ALL 16 ALU CORE OPERATIONS PASSED SUCCESSFULLY!");
        else             $display(" VERIFICATION FAILED WITH %0d ERROR(S)", errors);
        $display("====================================================\n");

        $finish;
    end

endmodule

Day 058/dump.vcd
$date
	Thu Aug 06 23:01:50 2026
$end
$version
	Icarus Verilog
$end
$timescale
	1ps
$end
$scope module tb_alu $end
$var wire 1 ! zero $end
$var wire 16 " result [15:0] $end
$var wire 1 # overflow $end
$var wire 1 $ negative $end
$var wire 1 % carry $end
$var parameter 32 & CLK_PERIOD $end
$var parameter 32 ' DATA_WIDTH $end
$var reg 16 ( A [15:0] $end
$var reg 16 ) B [15:0] $end
$var reg 4 * alu_op [3:0] $end
$var reg 1 + clk $end
$var reg 1 , nreset $end
$var integer 32 - errors [31:0] $end
$scope module uut $end
$var wire 16 . A [15:0] $end
$var wire 16 / B [15:0] $end
$var wire 4 0 alu_op [3:0] $end
$var wire 1 1 arith_overflow $end
$var wire 1 + clk $end
$var wire 1 , nreset $end
$var wire 1 ! zero $end
$var wire 4 2 shift_amt [3:0] $end
$var wire 1 $ negative $end
$var wire 16 3 arith_result [15:0] $end
$var wire 17 4 arith_full [16:0] $end
$var wire 1 5 arith_carry $end
$var parameter 4 6 ADD $end
$var parameter 4 7 AND $end
$var parameter 32 8 DATA_WIDTH $end
$var parameter 4 9 DEC $end
$var parameter 4 : INC $end
$var parameter 4 ; NAND $end
$var parameter 4 < NOR $end
$var parameter 4 = NOT $end
$var parameter 4 > OR $end
$var parameter 4 ? PASS $end
$var parameter 4 @ ROL $end
$var parameter 4 A ROR $end
$var parameter 32 B SHIFT_BITS $end
$var parameter 4 C SLL $end
$var parameter 4 D SRA $end
$var parameter 4 E SRL $end
$var parameter 4 F SUB $end
$var parameter 4 G XOR $end
$var reg 16 H B_eff [15:0] $end
$var reg 1 I C_in $end
$var reg 1 % carry $end
$var reg 1 J carry_comb $end
$var reg 1 # overflow $end
$var reg 1 K overflow_comb $end
$var reg 16 L result [15:0] $end
$var reg 16 M result_comb [15:0] $end
$upscope $end
$upscope $end
$enddefinitions $end
$comment Show the parameter values. $end
$dumpall
b110 G
b1 F
b1011 E
b1100 D
b1010 C
b100 B
b1110 A
b1101 @
b1111 ?
b101 >
b111 =
b1001 <
b1000 ;
b10 :
b11 9
b10000 8
b100 7
b0 6
b10000 '
b1010 &
$end
#0
$dumpvars
b0 M
b0 L
0K
0J
0I
b0 H
05
b0 4
b0 3
b0 2
01
b0 0
b0 /
b0 .
b0 -
0,
0+
b0 *
b0 )
b0 (
0%
0$
0#
b0 "
1!
$end
#5000
1+
#10000
0+
#15000
1+
#20000
0+
1,
#25000
1+
#30000
b11001 H
b1001 2
b1001011 M
b1001011 3
b11001 )
b11001 /
b1001011 4
b110010 (
b110010 .
0+
#35000
0!
b1001011 "
b1001011 L
1+
#40000
1J
b0 M
15
b100 2
b0 3
1I
b1111111110011011 H
b1100100 )
b1100100 /
b10000000000000000 4
b1100100 (
b1100100 .
b1 *
b1 0
0+
#45000
1%
1!
b0 "
b0 L
1+
#50000
b10000 M
b10000 3
05
0J
b0 H
b1001000110100 )
b1001000110100 /
b10000 4
b1111 (
b1111 .
b10 *
b10 0
0+
#55000
0%
0!
b10000 "
b10000 L
1+
#60000
b1111111111111111 M
b1111111111111111 3
0I
b1111111111111111 H
b1111111111111111 4
b0 (
b0 .
b11 *
b11 0
0+
#65000
1$
b1111111111111111 "
b1111111111111111 L
1+
#70000
1K
11
b1000000000000000 M
b1 2
b1000000000000000 3
b1 H
b1 )
b1 /
b1000000000000000 4
b111111111111111 (
b111111111111111 .
b0 *
b0 0
0+
#75000
1#
b1000000000000000 "
b1000000000000000 L
1+
#80000
01
b1111 2
b1111111100000000 3
b111100000000 M
0K
b0 H
b111100001111 )
b111100001111 /
b1111111100000000 4
b1111111100000000 (
b1111111100000000 .
b100 *
b100 0
0+
#85000
0$
0#
b111100000000 "
b111100000000 L
1+
#90000
b1111111111111111 M
b11111111 )
b11111111 /
b101 *
b101 0
0+
#95000
1$
b1111111111111111 "
b1111111111111111 L
1+
#100000
b101 2
b1010101010101010 3
b101010101010101 )
b101010101010101 /
b1010101010101010 4
b1010101010101010 (
b1010101010101010 .
b110 *
b110 0
0+
#105000
1+
#110000
01
b0 2
b1001000110100 3
b1110110111001011 M
b0 )
b0 /
b1001000110100 4
b1001000110100 (
b1001000110100 .
b111 *
b111 0
0+
#115000
b1110110111001011 "
b1110110111001011 L
1+
#120000
b1111111111111111 3
b111111111111 M
b1111000000000000 )
b1111000000000000 /
b1111111111111111 4
b1111111111111111 (
b1111111111111111 .
b1000 *
b1000 0
0+
#125000
0$
b111111111111 "
b111111111111 L
1+
#130000
01
b11111111 3
b1111111100000000 M
b0 )
b0 /
b11111111 4
b11111111 (
b11111111 .
b1001 *
b1001 0
0+
#135000
1$
b1111111100000000 "
b1111111100000000 L
1+
#140000
b1000 2
b1 3
b100000000 M
b1000 )
b1000 /
b1 4
b1 (
b1 .
b1010 *
b1010 0
0+
#145000
0$
b100000000 "
b100000000 L
1+
#150000
b100 2
b1000000000000000 3
b100000000000 M
b100 )
b100 /
b1000000000000000 4
b1000000000000000 (
b1000000000000000 .
b1011 *
b1011 0
0+
#155000
b100000000000 "
b100000000000 L
1+
#160000
b1111100000000000 M
b1100 *
b1100 0
0+
#165000
1$
b1111100000000000 "
b1111100000000000 L
1+
#170000
b10 2
b1100000000000001 3
b111 M
b10 )
b10 /
b1100000000000001 4
b1100000000000001 (
b1100000000000001 .
b1101 *
b1101 0
0+
#175000
0$
b111 "
b111 L
1+
#180000
01
b11 3
b1100000000000000 M
b11 4
b11 (
b11 .
b1110 *
b1110 0
0+
#185000
1$
b1100000000000000 "
b1100000000000000 L
1+
#190000
b100 2
b1010010110100101 3
b1010010110100101 M
b1001000110100 )
b1001000110100 /
b1010010110100101 4
b1010010110100101 (
b1010010110100101 .
b1111 *
b1111 0
0+
#195000
b1010010110100101 "
b1010010110100101 L
1+
