Day 041/booth_multiplier.v
module booth_multiplier#(parameter WIDTH = 4
)(
    input clk, nreset, start,
    input [WIDTH-1:0] A, B,
    output [2*WIDTH-1:0] result,
    output valid
);
    localparam IDLE = 2'd0;
    localparam COMPUTE = 2'd1;
    localparam DONE = 2'd2;

    reg [$clog2(WIDTH):0] count;

    reg [1:0] state, next_state;
    wire compute_done;

    //Next state logic
    always@(*) begin
        next_state = state;
        case(state) 
            IDLE: begin
                if(start) next_state = COMPUTE;
            end
            COMPUTE: begin
                if(compute_done) next_state = DONE;
            end
            DONE: begin
                next_state = IDLE;
            end
            default: next_state = IDLE;
        endcase
    end

    //State transition
    always@(posedge clk or negedge nreset) begin
        if(!nreset) begin
            state <= IDLE;
        end
        else state <= next_state;
    end

    //Datapath combinational logic
    reg [2*WIDTH:0] booth_reg;
    reg [WIDTH-1:0] next_A;
    reg [2*WIDTH:0] shifted_vec;
    always@(*) begin
        next_A = booth_reg[2*WIDTH : WIDTH+1];

        case({booth_reg[1:0]})
            2'b01: next_A = booth_reg[2*WIDTH: WIDTH+1] + A;
            2'b10: next_A = booth_reg[2*WIDTH: WIDTH+1] - A;
            default: next_A = booth_reg[2*WIDTH: WIDTH+1];
        endcase

        shifted_vec = {next_A[WIDTH-1], next_A, booth_reg[WIDTH:1]};
    end
    
    //Synchronous Register Updates
    always@(posedge clk or negedge nreset) begin
        if(!nreset) begin
            count <= 0;
            booth_reg <= 0;
        end
        else begin
            case(state)
                IDLE: begin
                    if(start) begin
                        booth_reg[2*WIDTH: WIDTH+1] <= 0;
                        booth_reg[WIDTH:1] <= B;
                        booth_reg[0] <= 1'b0;
                        count <= 0;
                    end
                end
                COMPUTE: begin
                    booth_reg <= shifted_vec;
                    count <= count + 1;
                end
                DONE: begin
                    count <= 0;
                end
            endcase
        end
    end
    //Combinational flag assigning
    assign compute_done = (count == WIDTH - 1);
    assign valid = (state == DONE);
    assign result = booth_reg[2*WIDTH:1];
endmodule

Day 041/tb.v
`timescale 1ns / 1ps

module tb_booth_multiplier;
    parameter WIDTH = 4;

    reg clk;
    reg nreset;
    reg start;
    reg [WIDTH-1:0] A;
    reg [WIDTH-1:0] B;

    wire [2*WIDTH-1:0] result;
    wire valid;

    // Instantiate Core Under Test
    booth_multiplier #(.WIDTH(WIDTH)) uut (
        .clk(clk),
        .nreset(nreset),
        .start(start),
        .A(A),
        .B(B),
        .result(result),
        .valid(valid)
    );

    // 100MHz Clock Generation
    initial begin
        clk = 1'b0;
        forever #5 clk = ~clk;
    end

    // Verification Driver Task
    task test_signed_mult(input signed [WIDTH-1:0] multi_A, input signed [WIDTH-1:0] multi_B);
        reg signed [2*WIDTH-1:0] expected_product;
        begin
            @(posedge clk);
            A = multi_A;
            B = multi_B;
            start = 1'b1;
            @(posedge clk);
            start = 1'b0;
            
            expected_product = multi_A * multi_B;

            @(posedge valid); // Wait for core finish strobe
            #1; // For the signal to settle, so that printing will be accurate
            $display("[TEST] Time = %0d | Inputs: A=%0d, B=%0d | Hardware Product=%0d (Expected=%0d)", 
                     $time, multi_A, multi_B, $signed(result), expected_product);
            #20;
        end
    endtask

    initial begin
        $dumpfile("dump.vcd");
        $dumpvars(0);

        // System Initialization Reset
        nreset = 1'b0;
        start  = 1'b0;
        A      = 0;
        B      = 0;
        #20;
        nreset = 1'b1;
        #20;

        $display("==================================================");
        $display("RUNNING SIGNED RADIX-2 BOOTH MULTIPLIER TESTS     ");
        $display("==================================================");

        // Test Case 1: Negative * Positive (Your manual example: -6 * 3 = -18)
        test_signed_mult(4'b1010, 4'b0011); 

        // Test Case 2: Positive * Positive (5 * 2 = 10)
        test_signed_mult(4'b0101, 4'b0010);

        // Test Case 3: Negative * Negative (-3 * -2 = 6)
        test_signed_mult(4'b1101, 4'b1110);

        // Test Case 4: Zero Operand Identity (-7 * 0 = 0)
        test_signed_mult(4'b1001, 4'b0000);

        $display("==================================================");
        $finish;
    end
endmodule

Day 041/dump.vcd
$date
	Fri Jul 17 20:34:05 2026
$end
$version
	Icarus Verilog
$end
$timescale
	1ps
$end
$scope module tb_booth_multiplier $end
$var wire 1 ! valid $end
$var wire 8 " result [7:0] $end
$var parameter 32 # WIDTH $end
$var reg 4 $ A [3:0] $end
$var reg 4 % B [3:0] $end
$var reg 1 & clk $end
$var reg 1 ' nreset $end
$var reg 1 ( start $end
$scope module uut $end
$var wire 4 ) A [3:0] $end
$var wire 4 * B [3:0] $end
$var wire 1 & clk $end
$var wire 1 ' nreset $end
$var wire 1 ( start $end
$var wire 1 ! valid $end
$var wire 8 + result [7:0] $end
$var wire 1 , compute_done $end
$var parameter 2 - COMPUTE $end
$var parameter 2 . DONE $end
$var parameter 2 / IDLE $end
$var parameter 32 0 WIDTH $end
$var reg 9 1 booth_reg [8:0] $end
$var reg 3 2 count [2:0] $end
$var reg 4 3 next_A [3:0] $end
$var reg 2 4 next_state [1:0] $end
$var reg 9 5 shifted_vec [8:0] $end
$var reg 2 6 state [1:0] $end
$upscope $end
$scope task test_signed_mult $end
$var reg 8 7 expected_product [7:0] $end
$var reg 4 8 multi_A [3:0] $end
$var reg 4 9 multi_B [3:0] $end
$upscope $end
$upscope $end
$enddefinitions $end
$comment Show the parameter values. $end
$dumpall
b100 0
b0 /
b10 .
b1 -
b100 #
$end
#0
$dumpvars
bx 9
bx 8
bx 7
b0 6
b0 5
b0 4
b0 3
b0 2
b0 1
0,
b0 +
b0 *
b0 )
0(
0'
0&
b0 %
b0 $
b0 "
0!
$end
#5000
1&
#10000
0&
#15000
1&
#20000
0&
1'
#25000
1&
#30000
0&
#35000
1&
#40000
0&
b11 9
b1010 8
#45000
b1100011 5
b110 3
b11 "
b11 +
b110 1
b1 4
1(
b11 %
b11 *
b1010 $
b1010 )
1&
#50000
0&
#55000
b1 6
b1 4
b11101110 7
0(
1&
#60000
0&
#65000
b110001 5
b11 3
b110001 "
b110001 +
b1 2
b1100011 1
1&
#70000
0&
#75000
b110111000 5
b1011 3
b11000 "
b11000 +
b10 2
b110001 1
1&
#80000
0&
#85000
b10 4
b111011100 5
b1101 3
b11011100 "
b11011100 +
1,
b11 2
b110111000 1
1&
#90000
0&
#95000
b0 4
b111101110 5
b1110 3
b11101110 "
b11101110 +
1!
b10 6
0,
b100 2
b111011100 1
1&
#100000
0&
#105000
b0 2
0!
b0 6
1&
#110000
0&
#115000
1&
#116000
b10 9
b101 8
#120000
0&
#125000
b10 5
b0 3
b10 "
b10 +
b100 1
b1 4
1(
b10 %
b10 *
b101 $
b101 )
1&
#130000
0&
#135000
b1 6
b1 4
b1010 7
0(
1&
#140000
0&
#145000
b110110001 5
b1011 3
b1 "
b1 +
b1 2
b10 1
1&
#150000
0&
#155000
b101000 5
b10 3
b11011000 "
b11011000 +
b10 2
b110110001 1
1&
#160000
0&
#165000
b10 4
b10100 5
b1 3
b10100 "
b10100 +
1,
b11 2
b101000 1
1&
#170000
0&
#175000
b0 4
b1010 5
b0 3
b1010 "
b1010 +
1!
b10 6
0,
b100 2
b10100 1
1&
#180000
0&
#185000
b0 2
0!
b0 6
1&
#190000
0&
#195000
1&
#196000
b1110 9
b1101 8
#200000
0&
#205000
b1110 5
b1110 "
b1110 +
b11100 1
b1 4
1(
b1110 %
b1110 *
b1101 $
b1101 )
1&
#210000
0&
#215000
b1 6
b1 4
b110 7
0(
1&
#220000
0&
#225000
b110111 5
b11 3
b111 "
b111 +
b1 2
b1110 1
1&
#230000
0&
#235000
b11011 5
b1 3
b11011 "
b11011 +
b10 2
b110111 1
1&
#240000
0&
#245000
b10 4
b1101 5
b0 3
b1101 "
b1101 +
1,
b11 2
b11011 1
1&
#250000
0&
#255000
b0 4
b111010110 5
b1101 3
b110 "
b110 +
1!
b10 6
0,
b100 2
b1101 1
1&
#260000
0&
#265000
b0 2
0!
b0 6
1&
#270000
0&
#275000
1&
#276000
b0 9
b1001 8
#280000
0&
#285000
b0 "
b0 +
b0 1
b1 4
b0 5
b0 3
1(
b0 %
b0 *
b1001 $
b1001 )
1&
#290000
0&
#295000
b1 6
b1 4
b0 7
0(
1&
#300000
0&
#305000
b1 2
1&
#310000
0&
#315000
b10 2
1&
#320000
0&
#325000
b10 4
1,
b11 2
1&
#330000
0&
#335000
b0 4
1!
b10 6
0,
b100 2
1&
#340000
0&
#345000
b0 2
0!
b0 6
1&
