Day 056/sync_2ff.v
module sync_2ff#(parameter DATA_WIDTH = 8
)(
    input clk, nreset,
    input [DATA_WIDTH-1:0] data_in,
    output reg [DATA_WIDTH-1:0] data_out
);
    //Forces synthesis engine to place both FFs adjacent on silicon
    (* ASYNC_REG = "TRUE" *) reg [DATA_WIDTH-1:0] sync_stage1;

    always@(posedge clk or negedge nreset) begin
        if(!nreset) begin
            sync_stage1 <= 0;
            data_out <= 0;
        end
        else begin
            sync_stage1 <= data_in;
            data_out <= sync_stage1;
        end
    end 
endmodule

Day 056/async_fifo.v
module asyn_fifo #(
    parameter DEPTH = 16,
    parameter DATA_WIDTH = 8,
    parameter ADDR_WIDTH = $clog2(DEPTH)
)(
    //Write Domain
    input wr_clk,
    input wr_rst_n,
    input wr_en,
    input [DATA_WIDTH-1:0] data_in,
    output full,

    //Read Domain
    input rd_clk,
    input rd_rst_n,
    input rd_en,
    output reg [DATA_WIDTH-1:0] data_out,
    output empty
);

    //Pointers for both domains
    reg [ADDR_WIDTH:0] wr_ptr_bin;
    wire [ADDR_WIDTH:0] wr_ptr_gray;
    reg [ADDR_WIDTH:0] rd_ptr_bin;
    wire [ADDR_WIDTH:0] rd_ptr_gray;

    assign wr_ptr_gray = wr_ptr_bin ^ (wr_ptr_bin >> 1);
    assign rd_ptr_gray = rd_ptr_bin ^ (rd_ptr_bin >> 1);

    //Synchronizer for write pointer(from write domain to read domain)
    wire [ADDR_WIDTH:0] wr_ptr_gray_rd_domain;
    sync_2ff #(.DATA_WIDTH(ADDR_WIDTH+1)) sync_wr2rd(.clk(rd_clk), .nreset(rd_rst_n), .data_in(wr_ptr_gray), .data_out(wr_ptr_gray_rd_domain));

    //Synchronizer for read pointer(from read domain to write domain)
    wire [ADDR_WIDTH:0] rd_ptr_gray_wr_domain;
    sync_2ff #(.DATA_WIDTH(ADDR_WIDTH+1)) sync_rd2wr(.clk(wr_clk), .nreset(wr_rst_n), .data_in(rd_ptr_gray), .data_out(rd_ptr_gray_wr_domain));

    //Memory Array
    reg [DATA_WIDTH-1:0] mem[0:DEPTH-1];

    //Write operation
    wire wr_valid = wr_en && !full;
    always@(posedge wr_clk) begin
        if(wr_valid) mem[wr_ptr_bin[ADDR_WIDTH-1:0]] <= data_in;
    end

    //Write Pointer Advancement
    always@(posedge wr_clk or negedge wr_rst_n) begin
        if(!wr_rst_n) wr_ptr_bin <= 0;
        else if(wr_valid) wr_ptr_bin <= wr_ptr_bin + 1'b1;
    end

    //Full condition: Two MSBs 0 and rest 1(In binary, only MSB will be inverted, but in gray code 2 MSBs will be inverted)
    assign full = (wr_ptr_gray == {~rd_ptr_gray_wr_domain[ADDR_WIDTH:ADDR_WIDTH-1], rd_ptr_gray_wr_domain[ADDR_WIDTH-2:0]});

    //Read Domain
    wire rd_valid = rd_en && !empty;
    always@(posedge rd_clk or negedge rd_rst_n) begin
        if(!rd_rst_n) begin
            rd_ptr_bin <= 0;
            data_out <= 0;
        end
        else if(rd_valid) begin
            data_out <= mem[rd_ptr_bin[ADDR_WIDTH-1:0]];
            rd_ptr_bin <= rd_ptr_bin + 1'b1;
        end
    end 

    assign empty = (rd_ptr_gray == wr_ptr_gray_rd_domain);
endmodule

Day 056/tb.v
`timescale 1ns / 1ps

module tb_asyn_fifo();

    parameter DEPTH      = 16;
    parameter DATA_WIDTH = 8;
    parameter WR_PERIOD  = 10; // 100 MHz Write Clock
    parameter RD_PERIOD  = 25; // 40 MHz Read Clock

    reg                  wr_clk, wr_rst_n, wr_en;
    reg  [DATA_WIDTH-1:0] data_in;
    wire                 full;

    reg                  rd_clk, rd_rst_n, rd_en;
    wire [DATA_WIDTH-1:0] data_out;
    wire                 empty;

    integer errors = 0;
    integer i;

    // Instantiate Asynchronous FIFO
    asyn_fifo #(
        .DEPTH(DEPTH),
        .DATA_WIDTH(DATA_WIDTH)
    ) uut (
        .wr_clk(wr_clk), .wr_rst_n(wr_rst_n), .wr_en(wr_en), .data_in(data_in), .full(full),
        .rd_clk(rd_clk), .rd_rst_n(rd_rst_n), .rd_en(rd_en), .data_out(data_out), .empty(empty)
    );

    // Generate Independent Asynchronous Clocks
    always #(WR_PERIOD / 2) wr_clk = ~wr_clk;
    always #(RD_PERIOD / 2) rd_clk = ~rd_clk;

    initial begin
        $dumpfile("dump.vcd");
        $dumpvars(0);

        wr_clk   = 0; wr_rst_n = 0; wr_en = 0; data_in = 0;
        rd_clk   = 0; rd_rst_n = 0; rd_en = 0;

        // Apply Active-Low Reset to both domains
        #(WR_PERIOD * 2);
        wr_rst_n = 1; rd_rst_n = 1;
        #(WR_PERIOD * 2);

        $display("\n====================================================");
        $display("   DAY 56: ASYNCHRONOUS DUAL-CLOCK FIFO VERIFICATION");
        $display("   wr_clk = 100 MHz | rd_clk = 40 MHz");
        $display("====================================================\n");

        // -------------------------------------------------------------
        // TEST 1: Check Initial Reset State
        // -------------------------------------------------------------
        if (empty && !full) begin
            $display("[PASS] TEST 1: Reset State Verified (EMPTY = 1, FULL = 0).");
        end else begin
            $display("[FAIL] TEST 1: Reset flag state mismatch!");
            errors = errors + 1;
        end

        // -------------------------------------------------------------
        // TEST 2: High-Speed Burst Write at 100 MHz (16 entries)
        // -------------------------------------------------------------
        $display("\n--- TEST 2: High-Speed Burst Write (100 MHz) ---");
        for (i = 1; i <= DEPTH; i = i + 1) begin
            @(negedge wr_clk);
            wr_en   = 1;
            data_in = i[7:0];
        end

        @(negedge wr_clk);
        wr_en = 0; // Deassert write strobe

        // Allow 2FF synchronization latency cycles for full flag to update
        #(WR_PERIOD * 3);
        if (full) begin
            $display("[PASS] TEST 2: FIFO accurately asserted FULL flag across CDC boundary.");
        end else begin
            $display("[FAIL] TEST 2: FULL flag failed to assert!");
            errors = errors + 1;
        end

        // -------------------------------------------------------------
        // TEST 3: Slow Consumer Read at 40 MHz & Verify Data Integrity
        // -------------------------------------------------------------
        $display("\n--- TEST 3: Slow Consumer Drain (40 MHz) & Data Ordering ---");
        for (i = 1; i <= DEPTH; i = i + 1) begin
            @(negedge rd_clk);
            rd_en = 1;

            @(posedge rd_clk); #1;
            if (data_out === i[7:0]) begin
                $display("[PASS] Sample %2d Read: 0x%02h", i, data_out);
            end else begin
                $display("[FAIL] Data Mismatch at sample %0d! Got 0x%02h, Exp 0x%02h", i, data_out, i[7:0]);
                errors = errors + 1;
            end
        end

        @(negedge rd_clk);
        rd_en = 0; // Deassert read strobe

        // Allow 2FF synchronization latency cycles for empty flag to update
        #(RD_PERIOD * 3);
        if (empty) begin
            $display("[PASS] TEST 3: FIFO cleanly returned to EMPTY state.");
        end else begin
            $display("[FAIL] TEST 3: EMPTY flag failed to assert!");
            errors = errors + 1;
        end

        // SUMMARY
        $display("\n====================================================");
        if (errors == 0) $display(" ALL ASYNCHRONOUS CDC FIFO TESTS PASSED!");
        else             $display(" VERIFICATION FAILED WITH %0d ERROR(S)", errors);
        $display("====================================================\n");

        $finish;
    end

endmodule

Day 056/dump.vcd
$date
	Tue Aug 04 22:38:48 2026
$end
$version
	Icarus Verilog
$end
$timescale
	1ps
$end
$scope module tb_asyn_fifo $end
$var wire 1 ! full $end
$var wire 1 " empty $end
$var wire 8 # data_out [7:0] $end
$var parameter 32 $ DATA_WIDTH $end
$var parameter 32 % DEPTH $end
$var parameter 32 & RD_PERIOD $end
$var parameter 32 ' WR_PERIOD $end
$var reg 8 ( data_in [7:0] $end
$var reg 1 ) rd_clk $end
$var reg 1 * rd_en $end
$var reg 1 + rd_rst_n $end
$var reg 1 , wr_clk $end
$var reg 1 - wr_en $end
$var reg 1 . wr_rst_n $end
$var integer 32 / errors [31:0] $end
$var integer 32 0 i [31:0] $end
$scope module uut $end
$var wire 8 1 data_in [7:0] $end
$var wire 1 ) rd_clk $end
$var wire 1 * rd_en $end
$var wire 5 2 rd_ptr_gray [4:0] $end
$var wire 1 + rd_rst_n $end
$var wire 1 3 rd_valid $end
$var wire 1 , wr_clk $end
$var wire 1 - wr_en $end
$var wire 5 4 wr_ptr_gray [4:0] $end
$var wire 1 . wr_rst_n $end
$var wire 1 5 wr_valid $end
$var wire 5 6 wr_ptr_gray_rd_domain [4:0] $end
$var wire 5 7 rd_ptr_gray_wr_domain [4:0] $end
$var wire 1 ! full $end
$var wire 1 " empty $end
$var parameter 32 8 ADDR_WIDTH $end
$var parameter 32 9 DATA_WIDTH $end
$var parameter 32 : DEPTH $end
$var reg 8 ; data_out [7:0] $end
$var reg 5 < rd_ptr_bin [4:0] $end
$var reg 5 = wr_ptr_bin [4:0] $end
$scope module sync_rd2wr $end
$var wire 1 , clk $end
$var wire 5 > data_in [4:0] $end
$var wire 1 . nreset $end
$var parameter 33 ? DATA_WIDTH $end
$var reg 5 @ data_out [4:0] $end
$var reg 5 A sync_stage1 [4:0] $end
$upscope $end
$scope module sync_wr2rd $end
$var wire 1 ) clk $end
$var wire 5 B data_in [4:0] $end
$var wire 1 + nreset $end
$var parameter 33 C DATA_WIDTH $end
$var reg 5 D data_out [4:0] $end
$var reg 5 E sync_stage1 [4:0] $end
$upscope $end
$upscope $end
$upscope $end
$enddefinitions $end
$comment Show the parameter values. $end
$dumpall
b101 C
b101 ?
b10000 :
b1000 9
b100 8
b1010 '
b11001 &
b10000 %
b1000 $
$end
#0
$dumpvars
b0 E
b0 D
b0 B
b0 A
b0 @
b0 >
b0 =
b0 <
b0 ;
b0 7
b0 6
05
b0 4
03
b0 2
b0 1
bx 0
b0 /
0.
0-
0,
0+
0*
0)
b0 (
b0 #
1"
0!
$end
#5000
1,
#10000
0,
#12000
1)
#15000
1,
#20000
0,
1+
1.
#24000
0)
#25000
1,
#30000
0,
#35000
1,
#36000
1)
#40000
15
b1 (
b1 1
1-
0,
b10 0
#45000
b1 4
b1 B
b1 =
1,
#48000
0)
#50000
b11 0
b10 (
b10 1
0,
#55000
b11 4
b11 B
b10 =
1,
#60000
b11 E
b100 0
b11 (
b11 1
0,
1)
#65000
b10 4
b10 B
b11 =
1,
#70000
b101 0
b100 (
b100 1
0,
#72000
0)
#75000
b110 4
b110 B
b100 =
1,
#80000
b110 0
b101 (
b101 1
0,
#84000
0"
b11 6
b11 D
b110 E
1)
#85000
b111 4
b111 B
b101 =
1,
#90000
b111 0
b110 (
b110 1
0,
#95000
b101 4
b101 B
b110 =
1,
#96000
0)
#100000
b1000 0
b111 (
b111 1
0,
#105000
b100 4
b100 B
b111 =
1,
#108000
b110 6
b110 D
b100 E
1)
#110000
b1001 0
b1000 (
b1000 1
0,
#115000
b1100 4
b1100 B
b1000 =
1,
#120000
b1010 0
b1001 (
b1001 1
0,
0)
#125000
b1101 4
b1101 B
b1001 =
1,
#130000
b1011 0
b1010 (
b1010 1
0,
#132000
b100 6
b100 D
b1101 E
1)
#135000
b1111 4
b1111 B
b1010 =
1,
#140000
b1100 0
b1011 (
b1011 1
0,
#144000
0)
#145000
b1110 4
b1110 B
b1011 =
1,
#150000
b1101 0
b1100 (
b1100 1
0,
#155000
b1010 4
b1010 B
b1100 =
1,
#156000
b1101 6
b1101 D
b1010 E
1)
#160000
b1110 0
b1101 (
b1101 1
0,
#165000
b1011 4
b1011 B
b1101 =
1,
#168000
0)
#170000
b1111 0
b1110 (
b1110 1
0,
#175000
b1001 4
b1001 B
b1110 =
1,
#180000
b1010 6
b1010 D
b1001 E
b10000 0
b1111 (
b1111 1
0,
1)
#185000
b1000 4
b1000 B
b1111 =
1,
#190000
b10001 0
b10000 (
b10000 1
0,
#192000
0)
#195000
05
1!
b11000 4
b11000 B
b10000 =
1,
#200000
0-
0,
#204000
b1001 6
b1001 D
b11000 E
1)
#205000
1,
#210000
0,
#215000
1,
#216000
0)
#220000
0,
#225000
1,
#228000
b11000 6
b11000 D
1)
#230000
0,
b1 0
#235000
1,
#240000
13
1*
0,
0)
#245000
1,
#250000
0,
#252000
b1 2
b1 >
b1 <
b1 #
b1 ;
1)
#253000
b10 0
#255000
b1 A
1,
#260000
0,
#264000
0)
#265000
0!
b1 7
b1 @
1,
#270000
0,
#275000
1,
#276000
b11 2
b11 >
b10 <
b10 #
b10 ;
1)
#277000
b11 0
#280000
0,
#285000
b11 A
1,
#288000
0)
#290000
0,
#295000
b11 7
b11 @
1,
#300000
b10 2
b10 >
b11 <
b11 #
b11 ;
0,
1)
#301000
b100 0
#305000
b10 A
1,
#310000
0,
#312000
0)
#315000
b10 7
b10 @
1,
#320000
0,
#324000
b110 2
b110 >
b100 <
b100 #
b100 ;
1)
#325000
b110 A
b101 0
1,
#330000
0,
#335000
b110 7
b110 @
1,
#336000
0)
#340000
0,
#345000
1,
#348000
b111 2
b111 >
b101 <
b101 #
b101 ;
1)
#349000
b110 0
#350000
0,
#355000
b111 A
1,
#360000
0,
0)
#365000
b111 7
b111 @
1,
#370000
0,
#372000
b101 2
b101 >
b110 <
b110 #
b110 ;
1)
#373000
b111 0
#375000
b101 A
1,
#380000
0,
#384000
0)
#385000
b101 7
b101 @
1,
#390000
0,
#395000
1,
#396000
b100 2
b100 >
b111 <
b111 #
b111 ;
1)
#397000
b1000 0
#400000
0,
#405000
b100 A
1,
#408000
0)
#410000
0,
#415000
b100 7
b100 @
1,
#420000
b1100 2
b1100 >
b1000 <
b1000 #
b1000 ;
0,
1)
#421000
b1001 0
#425000
b1100 A
1,
#430000
0,
#432000
0)
#435000
b1100 7
b1100 @
1,
#440000
0,
#444000
b1101 2
b1101 >
b1001 <
b1001 #
b1001 ;
1)
#445000
b1101 A
b1010 0
1,
#450000
0,
#455000
b1101 7
b1101 @
1,
#456000
0)
#460000
0,
#465000
1,
#468000
b1111 2
b1111 >
b1010 <
b1010 #
b1010 ;
1)
#469000
b1011 0
#470000
0,
#475000
b1111 A
1,
#480000
0,
0)
#485000
b1111 7
b1111 @
1,
#490000
0,
#492000
b1110 2
b1110 >
b1011 <
b1011 #
b1011 ;
1)
#493000
b1100 0
#495000
b1110 A
1,
#500000
0,
#504000
0)
#505000
b1110 7
b1110 @
1,
#510000
0,
#515000
1,
#516000
b1010 2
b1010 >
b1100 <
b1100 #
b1100 ;
1)
#517000
b1101 0
#520000
0,
#525000
b1010 A
1,
#528000
0)
#530000
0,
#535000
b1010 7
b1010 @
1,
#540000
b1011 2
b1011 >
b1101 <
b1101 #
b1101 ;
0,
1)
#541000
b1110 0
#545000
b1011 A
1,
#550000
0,
#552000
0)
#555000
b1011 7
b1011 @
1,
#560000
0,
#564000
b1001 2
b1001 >
b1110 <
b1110 #
b1110 ;
1)
#565000
b1001 A
b1111 0
1,
#570000
0,
#575000
b1001 7
b1001 @
1,
#576000
0)
#580000
0,
#585000
1,
#588000
b1000 2
b1000 >
b1111 <
b1111 #
b1111 ;
1)
#589000
b10000 0
#590000
0,
#595000
b1000 A
1,
#600000
0,
0)
#605000
b1000 7
b1000 @
1,
#610000
0,
#612000
03
1"
b11000 2
b11000 >
b10000 <
b10000 #
b10000 ;
1)
#613000
b10001 0
#615000
b11000 A
1,
#620000
0,
#624000
0*
0)
#625000
b11000 7
b11000 @
1,
