Day 043/non_restoring_divider.v
module non_restoring_divider#(parameter WIDTH = 4
)(
    input clk, nreset, start,
    input [WIDTH-1:0] dividend, divisor,
    output [WIDTH-1:0] quotient,
    output [WIDTH:0] remainder,
    output div_by_zero, valid
);
    localparam IDLE = 2'd0;
    localparam COMPUTE = 2'd1;
    localparam DONE = 2'd2;

    reg [1:0] state, next_state;

    always@(*) begin
        next_state = state;
        case(state) 
            IDLE: begin
                if(start) begin
                    if(dividend == 0 | divisor == 0) next_state = DONE;
                    else next_state = COMPUTE;
                end
            end
            COMPUTE: if(compute_done) next_state = DONE;
            DONE: next_state = IDLE;
            default: next_state = IDLE;
        endcase
    end

    always@(posedge clk or negedge nreset) begin
        if(!nreset) state <= IDLE;
        else state <= next_state;
    end

    //Combinational Datapath Block
    reg [2*WIDTH:0] vector;
    reg [WIDTH:0] A_new;
    wire [2*WIDTH:0] raw_left_shift;
    reg [2*WIDTH:0] shifted_vec;

    assign raw_left_shift = {vector[2*WIDTH-1:0], 1'b0};

    wire current_sign = vector[2*WIDTH];
    always@(*) begin
        if(current_sign) begin  // Previous accum was negative, hence add the divisor for the next cycle
            A_new = raw_left_shift[2*WIDTH:WIDTH] + {1'b0, divisor};
        end
        else begin 
            A_new = raw_left_shift[2*WIDTH:WIDTH] - {1'b0, divisor};
        end

        shifted_vec = {A_new, raw_left_shift[WIDTH-1:1], !A_new[WIDTH]};
    end

    //Synchronous Register Updates
    reg [$clog2(WIDTH):0] count;
    always@(posedge clk or negedge nreset) begin
        if(!nreset) begin
            count <= 0;
            vector <= 0;
        end
        else begin
            case(state)
                IDLE: begin
                    if(start) begin
                        count <= 0;
                        vector <= {{(WIDTH+1){1'b0}}, dividend};
                    end
                end
                COMPUTE: begin
                    vector <= shifted_vec;
                    count <= count + 1;
                end
                DONE: begin
                    count <= 0;
                end
            endcase
        end
    end

    // Output assignments
    assign compute_done = (count == WIDTH - 1);
    assign div_by_zero = (state == DONE && divisor == 0);
    assign valid = (state == DONE);

    assign quotient = (divisor == 0) ? {WIDTH{1'b1}}:
                      (dividend == 0) ? {WIDTH{1'b0}}:
                      vector[WIDTH-1:0];
    assign remainder = (divisor == 0) ? {(WIDTH+1){1'b0}}:
                       (dividend == 0) ? {(WIDTH+1){1'b0}}:
                       (vector[2*WIDTH]) ? ({vector[2*WIDTH:WIDTH]} + {1'b0, divisor}):
                       vector[2*WIDTH:WIDTH];
endmodule

Day 043/tb.v
`timescale 1ns / 1ps

module tb_non_restoring_divider;
    parameter WIDTH = 4;

    reg clk;
    reg nreset;
    reg start;
    reg [WIDTH-1:0] dividend;
    reg [WIDTH-1:0] divisor;

    wire [WIDTH-1:0] quotient;
    wire [WIDTH:0] remainder;
    wire div_by_zero;
    wire valid;

    // Instantiate Unit Under Test
    non_restoring_divider #(.WIDTH(WIDTH)) uut (
        .clk(clk), .nreset(nreset), .start(start),
        .dividend(dividend), .divisor(divisor),
        .quotient(quotient), .remainder(remainder),
        .div_by_zero(div_by_zero), .valid(valid)
    );

    // Clock Generation
    initial begin
        clk = 1'b0;
        forever #5 clk = ~clk;
    end

    // Verification Task
    task test_division(input [WIDTH-1:0] test_num, input [WIDTH-1:0] test_den);
        begin
            @(posedge clk);
            dividend = test_num;
            divisor  = test_den;
            start    = 1'b1;
            @(posedge clk);
            start    = 1'b0;
            
            @(posedge valid); // Handshake catches the data instantly!
            #1;
            $display("[TEST] Inputs: %0d / %0d | Quotient=%0d, Remainder=%0d | DivByZero Status=%b", 
                     test_num, test_den, quotient, remainder, div_by_zero);
            #20;
        end
    endtask

    initial begin
        $dumpfile("dump.vcd");
        $dumpvars(0);

        nreset = 1'b0; start = 1'b0; dividend = 0; divisor = 0;
        #20; nreset = 1'b1; #20;

        $display("==================================================");
        $display("RUNNING HARDWARE NON RESTORING DIVISION ACCELERATOR TESTS");
        $display("==================================================");

        // Case 1: Standard clean division (12 / 4 = 3, Remainder 0)
        test_division(4'd12, 4'd4);

        // Case 2: Division with fractional remainder (your manual example: 11 / 3 = 3, Remainder 2)
        test_division(4'd11, 4'd3);

        // Case 3: Zero dividend bypass evaluation (0 / 5 = 0, Remainder 0)
        test_division(4'd0, 4'd5);

        // Case 4: Critical Divide-by-Zero bypass safety check (8 / 0 -> Max Quotient, DivByZero Flag)
        test_division(4'd8, 4'd0);

        $display("==================================================");
        $finish;
    end
endmodule

Day 043/dump.vcd
$date
	Sun Jul 19 22:34:13 2026
$end
$version
	Icarus Verilog
$end
$timescale
	1ps
$end
$scope module tb_non_restoring_divider $end
$var wire 1 ! valid $end
$var wire 5 " remainder [4:0] $end
$var wire 4 # quotient [3:0] $end
$var wire 1 $ div_by_zero $end
$var parameter 32 % WIDTH $end
$var reg 1 & clk $end
$var reg 4 ' dividend [3:0] $end
$var reg 4 ( divisor [3:0] $end
$var reg 1 ) nreset $end
$var reg 1 * start $end
$scope module uut $end
$var wire 1 & clk $end
$var wire 1 $ div_by_zero $end
$var wire 4 + dividend [3:0] $end
$var wire 4 , divisor [3:0] $end
$var wire 1 ) nreset $end
$var wire 1 * start $end
$var wire 1 ! valid $end
$var wire 5 - remainder [4:0] $end
$var wire 9 . raw_left_shift [8:0] $end
$var wire 4 / quotient [3:0] $end
$var wire 1 0 current_sign $end
$var wire 1 1 compute_done $end
$var parameter 2 2 COMPUTE $end
$var parameter 2 3 DONE $end
$var parameter 2 4 IDLE $end
$var parameter 32 5 WIDTH $end
$var reg 5 6 A_new [4:0] $end
$var reg 3 7 count [2:0] $end
$var reg 2 8 next_state [1:0] $end
$var reg 9 9 shifted_vec [8:0] $end
$var reg 2 : state [1:0] $end
$var reg 9 ; vector [8:0] $end
$upscope $end
$scope task test_division $end
$var reg 4 < test_den [3:0] $end
$var reg 4 = test_num [3:0] $end
$upscope $end
$upscope $end
$enddefinitions $end
$comment Show the parameter values. $end
$dumpall
b100 5
b0 4
b10 3
b1 2
b100 %
$end
#0
$dumpvars
bx =
bx <
b0 ;
b0 :
b1 9
b0 8
b0 7
b0 6
01
00
b1111 /
b0 .
b0 -
b0 ,
b0 +
0*
0)
b0 (
b0 '
0&
0$
b1111 #
b0 "
0!
$end
#5000
1&
#10000
0&
#15000
1&
#20000
0&
1)
#25000
1&
#30000
0&
#35000
1&
#40000
0&
b100 <
b1100 =
#45000
b11000 .
b1100 ;
b111011000 9
b11101 6
b1100 #
b1100 /
b1 8
1*
b100 (
b100 ,
b1100 '
b1100 +
1&
#50000
0&
#55000
b1 :
b1 8
0*
1&
#60000
0&
#65000
b1 "
b1 -
b1000 #
b1000 /
b111110000 9
b11111 6
b110110000 .
10
b1 7
b111011000 ;
1&
#70000
0&
#75000
b11 "
b11 -
b0 #
b0 /
b100001 9
b10 6
b111100000 .
b10 7
b111110000 ;
1&
#80000
0&
#85000
b10 "
b10 -
b1 #
b1 /
b11 9
b0 6
b10 8
b1000010 .
00
11
b11 7
b100001 ;
1&
#90000
0&
#95000
b0 "
b0 -
b11 #
b11 /
b111000110 9
b11100 6
b0 8
b110 .
1!
b10 :
01
b100 7
b11 ;
1&
#100000
0&
#105000
b0 7
0!
b0 :
1&
#110000
0&
#115000
1&
#116000
b11 <
b1011 =
#120000
0&
#125000
b1011 #
b1011 /
b10110 .
b1011 ;
b111100110 9
b11110 6
b1 8
1*
b11 (
b11 ,
b1011 '
b1011 +
1&
#130000
0&
#135000
b1 :
b1 8
0*
1&
#140000
0&
#145000
b1 "
b1 -
b110 #
b110 /
b111111100 9
b11111 6
b111001100 .
10
b1 7
b111100110 ;
1&
#150000
0&
#155000
b10 "
b10 -
b1100 #
b1100 /
b101001 9
b10 6
b111111000 .
b10 7
b111111100 ;
1&
#160000
0&
#165000
b1001 #
b1001 /
b100011 9
b10 8
b1010010 .
00
11
b11 7
b101001 ;
1&
#170000
0&
#175000
b11 #
b11 /
b10111 9
b1 6
b0 8
b1000110 .
1!
b10 :
01
b100 7
b100011 ;
1&
#180000
0&
#185000
b0 7
0!
b0 :
1&
#190000
0&
#195000
1&
#196000
b101 <
b0 =
#200000
0&
#205000
b0 .
b0 ;
b0 #
b0 /
b0 "
b0 -
b110110000 9
b11011 6
b10 8
1*
b101 (
b101 ,
b0 '
b0 +
1&
#210000
0&
#215000
1!
b10 :
b0 8
0*
1&
#220000
0&
#225000
0!
b0 :
1&
#230000
0&
#235000
1&
#236000
b0 <
b1000 =
#240000
0&
#245000
b10000 .
b1000 ;
b10001 9
b1 6
b1111 #
b1111 /
b10 8
1*
b0 (
b0 ,
b1000 '
b1000 +
1&
#250000
0&
#255000
1$
1!
b10 :
b0 8
0*
1&
#260000
0&
#265000
0$
0!
b0 :
1&
