Day 009/half_sub.v
module half_sub(input a, b, output difference, borrow);
    assign difference = a ^ b;
    assign borrow = (~a) & b; // 0 - 1 should trigger borrow bit
endmodule

Day 009/full_sub.v
module full_sub(input a, b, borrow_in, output difference, borrow_out);
    wire diff1, borrow1, borrow2;
    half_sub s1(.a(a), .b(b), .difference(diff1), .borrow(borrow1));
    half_sub s2(.a(diff1), .b(borrow_in), .difference(difference), .borrow(borrow2));

    assign borrow_out = borrow1 | borrow2;
endmodule

Day 009/tb.v
module tb_full_sub();
    reg a, b, borrow_in;
    wire difference, borrow_out;

    full_sub uut(.a(a), .b(b), .borrow_in(borrow_in), .difference(difference), .borrow_out(borrow_out));

    initial begin
        $dumpfile("dump.vcd");
        $dumpvars(0);
        $monitor("Time: %0d ns | Inputs: A = %d, B = %d, Borrow_in = %d | Outputs: Diff = %d, B_out = %d", $time, a, b, borrow_in, difference, borrow_out);
    end

    initial begin
        a = 1'b0; b = 1'b0; borrow_in = 1'b0; #10;
        
        a = 1'b0; b = 1'b0; borrow_in = 1'b1; #10; 
        a = 1'b0; b = 1'b1; borrow_in = 1'b0; #10; 
        a = 1'b0; b = 1'b1; borrow_in = 1'b1; #10; 
        
        a = 1'b1; b = 1'b0; borrow_in = 1'b0; #10; 
        a = 1'b1; b = 1'b0; borrow_in = 1'b1; #10; 
        a = 1'b1; b = 1'b1; borrow_in = 1'b0; #10; 
        a = 1'b1; b = 1'b1; borrow_in = 1'b1; #10; 
        
        a = 1'b0; b = 1'b0; borrow_in = 1'b0; #10;
        
        $finish;
    end
endmodule

Day 009/dump.vcd
$date
	Mon Jun 15 12:06:15 2026
$end
$version
	Icarus Verilog
$end
$timescale
	1s
$end
$scope module tb_full_sub $end
$var wire 1 ! difference $end
$var wire 1 " borrow_out $end
$var reg 1 # a $end
$var reg 1 $ b $end
$var reg 1 % borrow_in $end
$scope module uut $end
$var wire 1 # a $end
$var wire 1 $ b $end
$var wire 1 % borrow_in $end
$var wire 1 " borrow_out $end
$var wire 1 ! difference $end
$var wire 1 & diff1 $end
$var wire 1 ' borrow2 $end
$var wire 1 ( borrow1 $end
$scope module s1 $end
$var wire 1 # a $end
$var wire 1 $ b $end
$var wire 1 ( borrow $end
$var wire 1 & difference $end
$upscope $end
$scope module s2 $end
$var wire 1 & a $end
$var wire 1 % b $end
$var wire 1 ' borrow $end
$var wire 1 ! difference $end
$upscope $end
$upscope $end
$upscope $end
$enddefinitions $end
$comment Show the parameter values. $end
$dumpall
$end
#0
$dumpvars
0(
0'
0&
0%
0$
0#
0"
0!
$end
#10
1"
1!
1'
1%
#20
0'
1&
1(
0%
1$
#30
0!
1%
#40
0"
1!
0(
0%
0$
1#
#50
0!
1%
#60
0&
0%
1$
#70
1"
1!
1'
1%
#80
0"
0!
0'
0%
0$
0#
