Day 038/quadrature_encoder_decoder.v
module quadrature_encoder_decoder(
    input clk, nreset,
    input [1:0] mode,
    input phaseA, phaseB,
    output reg clockwise, anticlockwise, error
);

    reg [2:0] phaseA_shifter, phaseB_shifter;

    // A CDC synchronizer
    always@(posedge clk or negedge nreset) begin
        if(!nreset) begin
            phaseA_shifter <= 3'b000;
            phaseB_shifter <= 3'b000;
        end
        else begin
            phaseA_shifter <= {phaseA_shifter[1:0], phaseA};
            phaseB_shifter <= {phaseB_shifter[1:0], phaseB};
        end
    end
    wire curr_A = phaseA_shifter[1];
    wire prev_A = phaseA_shifter[2];
    wire curr_B = phaseB_shifter[1];
    wire prev_B = phaseB_shifter[2];

    reg change;
    always@(*) begin
        case(mode)
            2'b01: change = (curr_A & ~prev_A);
            2'b10: change = (curr_A != prev_A);
            2'b11: change = (curr_A != prev_A) | (curr_B != prev_B);
            default: change = (curr_A != prev_A) || (curr_B != prev_B);
        endcase
    end

    //Register change logic
    always@(posedge clk or negedge nreset) begin
        if(!nreset) begin
            clockwise <= 0;
            anticlockwise <= 0;
            error <= 0;
        end
        else begin
            clockwise <= 0;
            anticlockwise <= 0;
            error <= 0;
            if(change) begin
                clockwise <= (~(prev_A | prev_B | curr_B) & curr_A) | (~prev_B & prev_A & curr_A & curr_B) | (prev_B & prev_A & curr_B & ~curr_A) | (prev_B & ~(prev_A | curr_A | curr_B));
                anticlockwise <= (~(prev_B | prev_A | curr_A) & curr_B) | (~(prev_B | curr_A | curr_B) & prev_A) | (prev_B & prev_A & curr_A & ~curr_B) | (prev_B & ~prev_A & curr_A & curr_B);
                error <= (~(prev_A | prev_B) & curr_A & curr_B) | (~(prev_B | curr_A) & prev_A & curr_B) | (~(curr_A | curr_B) & prev_A & prev_B) | (~(prev_A | curr_B) & prev_B & curr_A);
            end
        end
    end
    
endmodule

Day 038/tb.v
`timescale 1ns / 1ps

module tb_quadrature_encoder_decoder;

    // Testbench Stimulus Signals
    reg clk;
    reg nreset;
    reg [1:0] mode;
    reg phaseA;
    reg phaseB;

    // UUT Output Monitoring Wires
    wire clockwise;
    wire anticlockwise;
    wire error;

    // Track position externally to prove modular strobe counting success
    reg [15:0] position_counter;

    // Instantiate User's Parameterized Decoder Core
    quadrature_encoder_decoder uut (
        .clk(clk),
        .nreset(nreset),
        .mode(mode),
        .phaseA(phaseA),
        .phaseB(phaseB),
        .clockwise(clockwise),
        .anticlockwise(anticlockwise),
        .error(error)
    );

    // 100 MHz Master System Clock Generation
    initial begin
        clk = 1'b0;
        forever #5 clk = ~clk; // 10ns period clock
    end

    // External Position Accumulator tracking module strobes
    always @(posedge clk or negedge nreset) begin
        if (!nreset) begin
            position_counter <= 16'h0000;
        end else begin
            if (clockwise)     position_counter <= position_counter + 1'b1;
            if (anticlockwise) position_counter <= position_counter - 1'b1;
        end
    end

    // Task to generate one full 4-state Clockwise Quadrature Cycle
    task drive_clockwise_cycle;
        begin
            // State 10
            phaseA = 1'b1; phaseB = 1'b0; #40;
            // State 11
            phaseA = 1'b1; phaseB = 1'b1; #40;
            // State 01
            phaseA = 1'b0; phaseB = 1'b1; #40;
            // State 00
            phaseA = 1'b0; phaseB = 1'b0; #40;
        end
    endtask

    // Task to generate one full 4-state Counter-Clockwise Quadrature Cycle
    task drive_counter_clockwise_cycle;
        begin
            // State 01
            phaseA = 1'b0; phaseB = 1'b1; #40;
            // State 11
            phaseA = 1'b1; phaseB = 1'b1; #40;
            // State 10
            phaseA = 1'b1; phaseB = 1'b0; #40;
            // State 00
            phaseA = 1'b0; phaseB = 1'b0; #40;
        end
    endtask

    initial begin
        $dumpfile("dump.vcd");
        $dumpvars(0);

        // --- System Initialization & Active-Low Reset ---
        nreset = 1'b0; mode = 2'b11; phaseA = 1'b0; phaseB = 1'b0;
        #30;
        nreset = 1'b1;
        #20;

        // ====================================================================
        // TEST SCENARIO 1: Verify 4x Mode Resolution (Expect 4 counts per cycle)
        // ====================================================================
        mode = 2'b11; // 4x Resolution Mode Selection
        $display("[SIM] Target 4x Mode: Driving Clockwise Shaft Rotation...");
        drive_clockwise_cycle();
        #40;
        
        $display("[SIM] Target 4x Mode: Driving Counter-Clockwise Shaft Rotation...");
        drive_counter_clockwise_cycle();
        #40;

        // ====================================================================
        // TEST SCENARIO 2: Verify 2x Mode Resolution (Expect 2 counts per cycle)
        // ====================================================================
        mode = 2'b10; // 2x Resolution Mode Selection
        $display("[SIM] Target 2x Mode: Driving Clockwise Shaft Rotation...");
        drive_clockwise_cycle();
        #40;

        // ====================================================================
        // TEST SCENARIO 3: Verify 1x Mode Resolution (Expect 1 count per cycle)
        // ====================================================================
        mode = 2'b01; // 1x Resolution Mode Selection
        $display("[SIM] Target 1x Mode: Driving Clockwise Shaft Rotation...");
        drive_clockwise_cycle();
        #40;

        // ====================================================================
        // TEST SCENARIO 4: Verify Double-Bit-Flip Error Exception Handling
        // ====================================================================
        $display("[SIM] Injecting Speed/Sampling Violation Violation (00 -> 11)...");
        phaseA = 1'b0; phaseB = 1'b0;
        #40;
        phaseA = 1'b1; phaseB = 1'b1; // Simultaneous flip hazard injection
        #40;

        $display("[SIM] Verification complete. Analyzing position tracks.");
        $finish;
    end

endmodule

Day 038/dump.vcd
$date
	Mon Jul 13 20:16:43 2026
$end
$version
	Icarus Verilog
$end
$timescale
	1ps
$end
$scope module tb_quadrature_encoder_decoder $end
$var wire 1 ! error $end
$var wire 1 " clockwise $end
$var wire 1 # anticlockwise $end
$var reg 1 $ clk $end
$var reg 2 % mode [1:0] $end
$var reg 1 & nreset $end
$var reg 1 ' phaseA $end
$var reg 1 ( phaseB $end
$var reg 16 ) position_counter [15:0] $end
$scope module uut $end
$var wire 1 $ clk $end
$var wire 2 * mode [1:0] $end
$var wire 1 & nreset $end
$var wire 1 ' phaseA $end
$var wire 1 ( phaseB $end
$var wire 1 + prev_B $end
$var wire 1 , prev_A $end
$var wire 1 - curr_B $end
$var wire 1 . curr_A $end
$var reg 1 # anticlockwise $end
$var reg 1 / change $end
$var reg 1 " clockwise $end
$var reg 1 ! error $end
$var reg 3 0 phaseA_shifter [2:0] $end
$var reg 3 1 phaseB_shifter [2:0] $end
$upscope $end
$scope task drive_clockwise_cycle $end
$upscope $end
$scope task drive_counter_clockwise_cycle $end
$upscope $end
$upscope $end
$enddefinitions $end
$comment Show the parameter values. $end
$dumpall
$end
#0
$dumpvars
b0 1
b0 0
0/
0.
0-
0,
0+
b11 *
b0 )
0(
0'
0&
b11 %
0$
0#
0"
0!
$end
#5000
1$
#10000
0$
#15000
1$
#20000
0$
#25000
1$
#30000
0$
1&
#35000
1$
#40000
0$
#45000
1$
#50000
0$
1'
#55000
b1 0
1$
#60000
0$
#65000
1/
1.
b11 0
1$
#70000
0$
#75000
0/
1,
b111 0
1"
1$
#80000
0$
#85000
b1 )
0"
1$
#90000
0$
1(
#95000
b1 1
1$
#100000
0$
#105000
1/
1-
b11 1
1$
#110000
0$
#115000
0/
1+
b111 1
1"
1$
#120000
0$
#125000
b10 )
0"
1$
#130000
0$
0'
#135000
b110 0
1$
#140000
0$
#145000
1/
0.
b100 0
1$
#150000
0$
#155000
0/
0,
b0 0
1"
1$
#160000
0$
#165000
b11 )
0"
1$
#170000
0$
0(
#175000
b110 1
1$
#180000
0$
#185000
1/
0-
b100 1
1$
#190000
0$
#195000
0/
0+
b0 1
1"
1$
#200000
0$
#205000
b100 )
0"
1$
#210000
0$
#215000
1$
#220000
0$
#225000
1$
#230000
0$
#235000
1$
#240000
0$
#245000
1$
#250000
0$
1(
#255000
b1 1
1$
#260000
0$
#265000
1/
1-
b11 1
1$
#270000
0$
#275000
0/
1+
b111 1
1#
1$
#280000
0$
#285000
b11 )
0#
1$
#290000
0$
1'
#295000
b1 0
1$
#300000
0$
#305000
1/
1.
b11 0
1$
#310000
0$
#315000
0/
1,
b111 0
1#
1$
#320000
0$
#325000
b10 )
0#
1$
#330000
0$
0(
#335000
b110 1
1$
#340000
0$
#345000
1/
0-
b100 1
1$
#350000
0$
#355000
0/
0+
b0 1
1#
1$
#360000
0$
#365000
b1 )
0#
1$
#370000
0$
0'
#375000
b110 0
1$
#380000
0$
#385000
1/
0.
b100 0
1$
#390000
0$
#395000
0/
0,
b0 0
1#
1$
#400000
0$
#405000
b0 )
0#
1$
#410000
0$
#415000
1$
#420000
0$
#425000
1$
#430000
0$
#435000
1$
#440000
0$
#445000
1$
#450000
0$
1'
b10 %
b10 *
#455000
b1 0
1$
#460000
0$
#465000
1/
1.
b11 0
1$
#470000
0$
#475000
0/
1,
b111 0
1"
1$
#480000
0$
#485000
b1 )
0"
1$
#490000
0$
1(
#495000
b1 1
1$
#500000
0$
#505000
1-
b11 1
1$
#510000
0$
#515000
1+
b111 1
1$
#520000
0$
#525000
1$
#530000
0$
0'
#535000
b110 0
1$
#540000
0$
#545000
1/
0.
b100 0
1$
#550000
0$
#555000
0/
0,
b0 0
1"
1$
#560000
0$
#565000
b10 )
0"
1$
#570000
0$
0(
#575000
b110 1
1$
#580000
0$
#585000
0-
b100 1
1$
#590000
0$
#595000
0+
b0 1
1$
#600000
0$
#605000
1$
#610000
0$
#615000
1$
#620000
0$
#625000
1$
#630000
0$
#635000
1$
#640000
0$
#645000
1$
#650000
0$
1'
b1 %
b1 *
#655000
b1 0
1$
#660000
0$
#665000
1/
1.
b11 0
1$
#670000
0$
#675000
0/
1,
b111 0
1"
1$
#680000
0$
#685000
b11 )
0"
1$
#690000
0$
1(
#695000
b1 1
1$
#700000
0$
#705000
1-
b11 1
1$
#710000
0$
#715000
1+
b111 1
1$
#720000
0$
#725000
1$
#730000
0$
0'
#735000
b110 0
1$
#740000
0$
#745000
0.
b100 0
1$
#750000
0$
#755000
0,
b0 0
1$
#760000
0$
#765000
1$
#770000
0$
0(
#775000
b110 1
1$
#780000
0$
#785000
0-
b100 1
1$
#790000
0$
#795000
0+
b0 1
1$
#800000
0$
#805000
1$
#810000
0$
#815000
1$
#820000
0$
#825000
1$
#830000
0$
#835000
1$
#840000
0$
#845000
1$
#850000
0$
#855000
1$
#860000
0$
#865000
1$
#870000
0$
#875000
1$
#880000
0$
#885000
1$
#890000
0$
1(
1'
#895000
b1 1
b1 0
1$
#900000
0$
#905000
1/
1-
1.
b11 1
b11 0
1$
#910000
0$
#915000
0/
1+
1,
b111 1
b111 0
1!
1$
#920000
0$
#925000
0!
1$
