Day 081/imm_gen.v
module riscv_imm_gen (
    input [31:0] instr,
    output reg [31:0] imm
);
    wire [6:0] opcode = instr[6:0];

    //Standard RV32I Base Opcodes
    localparam OPC_OP_IMM = 7'b0010011; // addi...
    localparam OPC_LOAD = 7'b0000011;   // lb, lh, lw, lbu, lhu
    localparam OPC_JALR = 7'b1100111;   // jalr
    localparam OPC_STORE = 7'b0100011;  // sb, sh, sw
    localparam OPC_BRANCH = 7'b1100011; // beq, bne, blt, bge, bltu, bgeu
    localparam OPC_LUI = 7'b0110111;    // lui
    localparam OPC_AUIPC = 7'b0010111;  // auipc
    localparam OPC_JAL = 7'b1101111;    // jal

    always@(*) begin
        case(opcode)
            // I-type Immediate
            OPC_OP_IMM, OPC_LOAD, OPC_JALR: begin
                imm = {{20{instr[31]}}, instr[31:20]};
            end

            // S-type immediate
            OPC_STORE: begin
                imm = {{20{instr[31]}}, instr[31:25], instr[11:7]};
            end

            // B-type immediates
            OPC_BRANCH: begin
                imm = {{19{instr[31]}}, instr[31], instr[7], instr[30:25], instr[11:8], 1'b0};
            end

            // U-type immediate(shifted upper 20 bits)
            OPC_AUIPC, OPC_LUI: begin
                imm = {instr[31:12], 12'h00};
            end

            // J-type
            OPC_JAL: begin
                imm = {{11{instr[31]}}, instr[31], instr[19:12], instr[20], instr[30:21], 1'b0};
            end

            default: begin
                imm = 32'd0;
            end
        endcase
    end

endmodule

Day 081/riscv_regfile.v
module riscv_regfile (
    input clk,

    input [4:0] rs1, rs2,
    output [31:0] rdata1, rdata2,

    input reg_write,
    input [4:0] rd,
    input [31:0] w_data
);
    reg [31:0] rf [0:31];

    //Initial reset to 0
    integer i;
    initial begin
        for(i=0; i<32; i = i+1) 
            rf[i] = 32'd0;
    end

    //Synchronous Write
    always@(posedge clk) begin
        if(reg_write && (rd != 5'd0))
            rf[rd] <= w_data;
    end 

    //Combinational Read with internal WB forwarding and x0 hardwired to 0
    assign rdata1 = (rs1 == 5'd0) ? 32'd0 :
                    (reg_write && (rd == rs1)) ? w_data : rf[rs1];
    assign rdata2 = (rs2 == 5'd0) ? 32'd0 :
                    (reg_write && (rd == rs2)) ? w_data : rf[rs2];
endmodule

Day 081/riscv_id_stage.v
module riscv_id_stage (
    input clk, nreset,

    input stall_ex, // 1 = Hold ID/EX stage
    input flush_ex, // 1 = Clear ID/EX register to NOP bubble

    //Inputs from IF/ID reg
    input [31:0] if_id_pc, if_id_pc_plus_4,
    input [31:0] if_id_instr,

    ///Inputs from WB stage(Register file write port)
    input wb_reg_write,
    input [4:0] wb_rd,
    input [31:0] wb_wdata,

    //Raw decoded fields to hazard detection unit
    output [4:0] id_rs1, id_rs2,
    output id_rs1_valid, id_rs2_valid, //Hazard Check validity(If 0 = No need for hazard unit to check)

    //Outputs from ID/EX pipeline reg(Driven to EX stage)
    output reg [31:0] id_ex_pc, id_ex_pc_plus_4,
    output reg [31:0] id_ex_rdata1, id_ex_rdata2,
    output reg [31:0] id_ex_imm,
    output reg [4:0] id_ex_rs1, id_ex_rs2, id_ex_rd,
    output reg id_ex_rs1_valid, id_ex_rs2_valid,
    output reg [2:0] id_ex_funct3,
    output reg [6:0] id_ex_funct7,
    output reg [6:0] id_ex_opcode
);
    //NOP Encoding
    localparam [31:0] NOP_INSTRUCTION = 32'h0000_0013;

    wire [6:0] raw_opcode = if_id_instr[6:0];
    wire [4:0] raw_rd     = if_id_instr[11:7];
    wire [2:0] raw_funct3 = if_id_instr[14:12];
    wire [4:0] raw_rs1    = if_id_instr[19:15];
    wire [4:0] raw_rs2    = if_id_instr[24:20];
    wire [6:0] raw_funct7 = if_id_instr[31:25];

    assign id_rs1 = raw_rs1;
    assign id_rs2 = raw_rs2;

    reg rs1_valid, rs2_valid;
    always@(*) begin
        case(raw_opcode) 
            7'b0110011: begin // R-type
                rs1_valid = (raw_rs1 != 5'd0);
                rs2_valid = (raw_rs2 != 5'd0);
            end
            7'b0010011, // I-type ALU
            7'b0000011, // I type LOAD
            7'b1100111: begin // I type JALR
                rs1_valid = (raw_rs1 != 5'd0);
                rs2_valid = 1'b0; //Bits [24:20] are immediate, not rs2
            end

            7'b0100011: begin // S type store(sw, sb): uses both rs1 and rs2
                rs1_valid = (raw_rs1 != 5'd0);
                rs2_valid = (raw_rs2 != 5'd0);
            end

            7'b1100011: begin // B type branch(compares rs1 and rs2)
                rs1_valid = (raw_rs1 != 5'd0);
                rs2_valid = (raw_rs2 != 5'd0);
            end

            7'b0110111, //U type LUI
            7'b0010111, //U type AUIPC
            7'b1101111: begin //J type JAL
                rs1_valid = 1'b0; //No source registers are needed
                rs2_valid = 1'b0;
            end
            default: begin
                rs1_valid = 1'b0;
                rs2_valid = 1'b0;
            end
        endcase
    end
    assign id_rs1_valid = rs1_valid;
    assign id_rs2_valid = rs2_valid;

    wire [31:0] id_rdata1, id_rdata2;
    wire [31:0] id_imm;

    //Register File
    riscv_regfile u_regfile (
        .clk(clk),
        .rs1(raw_rs1),
        .rs2(raw_rs2),
        .rdata1(id_rdata1),
        .rdata2(id_rdata2),
        .reg_write(wb_reg_write),
        .rd(wb_rd),
        .w_data(wb_wdata)
    );

    //Immediate Generator
    riscv_imm_gen u_imm_gen(
        .instr(if_id_instr),
        .imm(id_imm)
    );

    always@(posedge clk or negedge nreset) begin
        if(!nreset) begin
            id_ex_pc <= 32'd0;
            id_ex_pc_plus_4 <= 32'd0;
            id_ex_rdata1 <= 32'd0;
            id_ex_rdata2 <= 32'd0;
            id_ex_imm <= 32'd0;
            id_ex_rs1 <= 5'd0;
            id_ex_rs2 <= 5'd0;
            id_ex_rs1_valid <= 1'b0;
            id_ex_rs2_valid <= 1'b0;
            id_ex_rd <= 5'd0;
            id_ex_funct3 <= 3'd0;
            id_ex_funct7 <= 7'd0;
            id_ex_opcode <= 7'b0000000; //NOP Opcode
        end 
        else if(flush_ex) begin
            id_ex_pc <= 32'd0;
            id_ex_pc_plus_4 <= 32'd0;
            id_ex_rdata1 <= 32'd0;
            id_ex_rdata2 <= 32'd0;
            id_ex_imm <= 32'd0;
            id_ex_rs1 <= 5'd0;
            id_ex_rs2 <= 5'd0;
            id_ex_rs1_valid <= 1'b0;
            id_ex_rs2_valid <= 1'b0;
            id_ex_rd <= 5'd0;
            id_ex_funct3 <= 3'd0;
            id_ex_funct7 <= 7'd0;
            id_ex_opcode <= 7'b0000000; //NOP Opcode
        end 
        else if(!stall_ex) begin
            id_ex_pc <= if_id_pc;
            id_ex_pc_plus_4 <= if_id_pc_plus_4;
            id_ex_rdata1 <= id_rdata1;
            id_ex_rdata2 <= id_rdata2;
            id_ex_imm <= id_imm;
            id_ex_rs1 <= raw_rs1;
            id_ex_rs2 <= raw_rs2;
            id_ex_rs1_valid <= id_rs1_valid;
            id_ex_rs2_valid <= id_rs2_valid;
            id_ex_rd <= raw_rd;
            id_ex_funct3 <= raw_funct3;
            id_ex_funct7 <= raw_funct7;
            id_ex_opcode <= raw_opcode;
        end
    end 

endmodule

Day 081/tb.v
`timescale 1ns / 1ps

module tb_riscv_id_stage();

    parameter CLK_PERIOD = 10;

    reg         clk;
    reg         nreset;

    // Controls
    reg         stall_ex;
    reg         flush_ex;

    // Inputs from IF/ID
    reg  [31:0] if_id_pc;
    reg  [31:0] if_id_pc_plus_4;
    reg  [31:0] if_id_instr;

    // Inputs from WB
    reg         wb_reg_write;
    reg  [4:0]  wb_rd;
    reg  [31:0] wb_wdata;

    // Outputs from ID Stage
    wire [4:0]  id_rs1;
    wire [4:0]  id_rs2;
    wire        id_rs1_valid;
    wire        id_rs2_valid;

    wire [31:0] id_ex_pc;
    wire [31:0] id_ex_pc_plus_4;
    wire [31:0] id_ex_rdata1;
    wire [31:0] id_ex_rdata2;
    wire [31:0] id_ex_imm;
    wire [4:0]  id_ex_rs1;
    wire [4:0]  id_ex_rs2;
    wire        id_ex_rs1_valid;
    wire        id_ex_rs2_valid;
    wire [4:0]  id_ex_rd;
    wire [2:0]  id_ex_funct3;
    wire [6:0]  id_ex_funct7;
    wire [6:0]  id_ex_opcode;

    integer errors = 0;

    // Instantiate UUT
    riscv_id_stage uut (
        .clk             (clk),
        .nreset          (nreset),
        .stall_ex        (stall_ex),
        .flush_ex        (flush_ex),
        .if_id_pc        (if_id_pc),
        .if_id_pc_plus_4 (if_id_pc_plus_4),
        .if_id_instr     (if_id_instr),
        .wb_reg_write    (wb_reg_write),
        .wb_rd           (wb_rd),
        .wb_wdata        (wb_wdata),
        .id_rs1          (id_rs1),
        .id_rs2          (id_rs2),
        .id_rs1_valid    (id_rs1_valid),
        .id_rs2_valid    (id_rs2_valid),
        .id_ex_pc        (id_ex_pc),
        .id_ex_pc_plus_4 (id_ex_pc_plus_4),
        .id_ex_rdata1    (id_ex_rdata1),
        .id_ex_rdata2    (id_ex_rdata2),
        .id_ex_imm       (id_ex_imm),
        .id_ex_rs1       (id_ex_rs1),
        .id_ex_rs2       (id_ex_rs2),
        .id_ex_rs1_valid (id_ex_rs1_valid),
        .id_ex_rs2_valid (id_ex_rs2_valid),
        .id_ex_rd        (id_ex_rd),
        .id_ex_funct3    (id_ex_funct3),
        .id_ex_funct7    (id_ex_funct7),
        .id_ex_opcode    (id_ex_opcode)
    );

    // Clock Generation
    always #(CLK_PERIOD / 2) clk = ~clk;

    initial begin
        $dumpfile("dump.vcd");
        $dumpvars(0, tb_riscv_id_stage);

        clk             = 0;
        nreset          = 0;
        stall_ex        = 0;
        flush_ex        = 0;
        if_id_pc        = 32'd0;
        if_id_pc_plus_4 = 32'd4;
        if_id_instr     = 32'h0000_0000; // NOP
        wb_reg_write    = 0;
        wb_rd           = 5'd0;
        wb_wdata        = 32'd0;

        #(CLK_PERIOD * 3);
        @(negedge clk);
        nreset = 1;

        $display("\n=======================================================================================================");
        $display("                   DAY 81: RISC-V INSTRUCTION DECODE (ID) STAGE VERIFICATION                           ");
        $display("=======================================================================================================");

        // --- TEST 1: Register File Writes, x0 Hardwiring & Validity Flag Behavior ---
        $display("\n--- TEST 1: Register File Writes, x0 Hardwiring & Validity Qualifiers ---");
        // Write 0xDEADBEEF to x5
        @(negedge clk);
        wb_reg_write = 1'b1;
        wb_rd        = 5'd5;
        wb_wdata     = 32'hDEADBEEF;

        // Try to overwrite x0 with 0xCAFEBABE
        @(negedge clk);
        wb_rd        = 5'd0;
        wb_wdata     = 32'hCAFEBABE;

        @(negedge clk);
        wb_reg_write = 1'b0;

        // Feed instruction: add x6, x5, x0 (R-Type: rs1=x5, rs2=x0)
        if_id_instr  = {7'b0000000, 5'd0, 5'd5, 3'b000, 5'd6, 7'b0110011};

        #(1);
        // Verify combinational validity: rs1(x5) is valid; rs2(x0) must be INVALID (0)
        if (id_rs1_valid !== 1'b1 || id_rs2_valid !== 1'b0) begin
            $display("[FAIL] Combinational valid mismatch! id_rs1_valid=%b (exp 1), id_rs2_valid=%b (exp 0)",
                     id_rs1_valid, id_rs2_valid);
            errors = errors + 1;
        end else begin
            $display("[PASS] Combinational validity: rs1(x5) valid=1, rs2(x0) valid=0 (suppressed)");
        end

        @(posedge clk);
        #(1);
        if (id_ex_rdata1 !== 32'hDEADBEEF) begin
            $display("[FAIL] Read x5 failed! Got: 0x%08h, Expected: 0xDEADBEEF", id_ex_rdata1);
            errors = errors + 1;
        end else begin
            $display("[PASS] Read x5 succeeded (0xDEADBEEF)");
        end

        if (id_ex_rdata2 !== 32'h0000_0000) begin
            $display("[FAIL] x0 was modified! Got: 0x%08h, Expected: 0x00000000", id_ex_rdata2);
            errors = errors + 1;
        end else begin
            $display("[PASS] x0 correctly invariant at 0x00000000");
        end

        // Verify registered validity in ID/EX
        if (id_ex_rs1_valid !== 1'b1 || id_ex_rs2_valid !== 1'b0) begin
            $display("[FAIL] Registered valid mismatch! id_ex_rs1_valid=%b, id_ex_rs2_valid=%b",
                     id_ex_rs1_valid, id_ex_rs2_valid);
            errors = errors + 1;
        end else begin
            $display("[PASS] Registered validity: id_ex_rs1_valid=1, id_ex_rs2_valid=0");
        end

        // --- TEST 2: Internal RegFile WB Bypass ---
        $display("\n--- TEST 2: Internal RegFile Bypass Forwarding ---");
        @(negedge clk);
        wb_reg_write = 1'b1;
        wb_rd        = 5'd10;
        wb_wdata     = 32'hA5A55A5A;
        // Instruction: add x1, x10, x0
        if_id_instr  = {7'b0000000, 5'd0, 5'd10, 3'b000, 5'd1, 7'b0110011};

        #(1);
        if (uut.u_regfile.rdata1 !== 32'hA5A55A5A) begin
            $display("[FAIL] Internal bypass failed! Combinational rdata1: 0x%08h", uut.u_regfile.rdata1);
            errors = errors + 1;
        end else begin
            $display("[PASS] Internal RegFile bypass forwarded write data combinationally in same cycle!");
        end

        @(posedge clk);
        #(1);
        wb_reg_write = 1'b0;

        // --- TEST 3: Immediate Generator & Field Validity Across All RV32I Formats ---
        $display("\n--- TEST 3: Immediate Generator & Register Validity Across Formats ---");

        // 3a. I-Type: addi x1, x2, -42 (rs1=x2, imm=-42)
        // Note: instr[24:20] contains immediate bits 5'b00110 (=6), NOT rs2!
        // instr = {12'hFA6, 5'd2, 3'b000, 5'd1, 7'b0010011} = 0xFA610093
        @(negedge clk);
        if_id_instr = 32'hFA610093;

        #(1);
        if (id_rs1_valid !== 1'b1 || id_rs2_valid !== 1'b0) begin
            $display("[FAIL] I-Type validity error! id_rs1_valid=%b (exp 1), id_rs2_valid=%b (exp 0)",
                     id_rs1_valid, id_rs2_valid);
            errors = errors + 1;
        end else begin
            $display("[PASS] I-Type validity: rs1(x2) valid=1, rs2 immediate bits suppressed (valid=0)");
        end

        @(posedge clk);
        #(1);
        if (id_ex_imm !== 32'hFFFFFFA6 || id_ex_rs1_valid !== 1'b1 || id_ex_rs2_valid !== 1'b0) begin
            $display("[FAIL] I-Type decode/pipeline latch error! Imm: 0x%08h, v1=%b, v2=%b",
                     id_ex_imm, id_ex_rs1_valid, id_ex_rs2_valid);
            errors = errors + 1;
        end else begin
            $display("[PASS] I-Type Registered: Imm = -90 (0x%08h), rs1_valid=1, rs2_valid=0", id_ex_imm);
        end

        // 3b. S-Type: sw x5, -8(x2) (Uses rs1=x2 and rs2=x5)
        // instr = 0xFE512C23
        @(negedge clk);
        if_id_instr = 32'hFE512C23;

        #(1);
        if (id_rs1_valid !== 1'b1 || id_rs2_valid !== 1'b1) begin
            $display("[FAIL] S-Type validity error! id_rs1_valid=%b, id_rs2_valid=%b (exp 1, 1)",
                     id_rs1_valid, id_rs2_valid);
            errors = errors + 1;
        end

        @(posedge clk);
        #(1);
        if (id_ex_imm !== 32'hFFFFFFF8 || id_ex_rs1_valid !== 1'b1 || id_ex_rs2_valid !== 1'b1) begin
            $display("[FAIL] S-Type decode error! Imm: 0x%08h, v1=%b, v2=%b",
                     id_ex_imm, id_ex_rs1_valid, id_ex_rs2_valid);
            errors = errors + 1;
        end else begin
            $display("[PASS] S-Type Registered: Imm = -8 (0x%08h), rs1_valid=1, rs2_valid=1", id_ex_imm);
        end

        // 3c. B-Type: beq x1, x2, -16 (Branches compare rs1=x1 and rs2=x2)
        // instr = 0xFE2088E3
        @(negedge clk);
        if_id_instr = 32'hFE2088E3;

        #(1);
        if (id_rs1_valid !== 1'b1 || id_rs2_valid !== 1'b1) begin
            $display("[FAIL] B-Type validity error! id_rs1_valid=%b, id_rs2_valid=%b (exp 1, 1)",
                     id_rs1_valid, id_rs2_valid);
            errors = errors + 1;
        end

        @(posedge clk);
        #(1);
        if (id_ex_imm !== 32'hFFFFFFF0 || id_ex_rs1_valid !== 1'b1 || id_ex_rs2_valid !== 1'b1) begin
            $display("[FAIL] B-Type decode error! Imm: 0x%08h, v1=%b, v2=%b",
                     id_ex_imm, id_ex_rs1_valid, id_ex_rs2_valid);
            errors = errors + 1;
        end else begin
            $display("[PASS] B-Type Registered: Imm = -16 (0x%08h), rs1_valid=1, rs2_valid=1", id_ex_imm);
        end

        // 3d. U-Type: lui x3, 0x12345 (No source registers read)
        // instr = 0x123451B7
        @(negedge clk);
        if_id_instr = 32'h123451B7;

        #(1);
        if (id_rs1_valid !== 1'b0 || id_rs2_valid !== 1'b0) begin
            $display("[FAIL] U-Type validity error! id_rs1_valid=%b, id_rs2_valid=%b (exp 0, 0)",
                     id_rs1_valid, id_rs2_valid);
            errors = errors + 1;
        end

        @(posedge clk);
        #(1);
        if (id_ex_imm !== 32'h12345000 || id_ex_rs1_valid !== 1'b0 || id_ex_rs2_valid !== 1'b0) begin
            $display("[FAIL] U-Type decode error! Imm: 0x%08h, v1=%b, v2=%b",
                     id_ex_imm, id_ex_rs1_valid, id_ex_rs2_valid);
            errors = errors + 1;
        end else begin
            $display("[PASS] U-Type Registered: Imm = 0x%08h, rs1_valid=0, rs2_valid=0", id_ex_imm);
        end

        // 3e. J-Type: jal x1, -2048 (No source registers read)
        // instr = 0x801FF0EF
        @(negedge clk);
        if_id_instr = 32'h801FF0EF;

        #(1);
        if (id_rs1_valid !== 1'b0 || id_rs2_valid !== 1'b0) begin
            $display("[FAIL] J-Type validity error! id_rs1_valid=%b, id_rs2_valid=%b (exp 0, 0)",
                     id_rs1_valid, id_rs2_valid);
            errors = errors + 1;
        end

        @(posedge clk);
        #(1);
        if (id_ex_imm !== 32'hFFFFF800 || id_ex_rs1_valid !== 1'b0 || id_ex_rs2_valid !== 1'b0) begin
            $display("[FAIL] J-Type decode error! Imm: 0x%08h, v1=%b, v2=%b",
                     id_ex_imm, id_ex_rs1_valid, id_ex_rs2_valid);
            errors = errors + 1;
        end else begin
            $display("[PASS] J-Type Registered: Imm = -2048 (0x%08h), rs1_valid=0, rs2_valid=0", id_ex_imm);
        end

        // --- TEST 4: ID/EX Register Stall & Flush Behavior ---
        $display("\n--- TEST 4: ID/EX Pipeline Stall & Flush ---");
        @(negedge clk);
        stall_ex    = 1'b1;
        // Present an R-type (add x1, x2, x3) on IF/ID while pipeline is stalled
        if_id_instr = {7'b0000000, 5'd3, 5'd2, 3'b000, 5'd1, 7'b0110011};

        @(posedge clk);
        #(1);
        // During stall, the register must hold the previous J-type values (imm = -2048, valid = 0)
        if (id_ex_imm !== 32'hFFFFF800 || id_ex_rs1_valid !== 1'b0 || id_ex_rs2_valid !== 1'b0) begin
            $display("[FAIL] ID/EX drifted during stall! Imm: 0x%08h, rs1_v=%b, rs2_v=%b",
                     id_ex_imm, id_ex_rs1_valid, id_ex_rs2_valid);
            errors = errors + 1;
        end else begin
            $display("[PASS] Pipeline correctly held previous state and validity across stall_ex!");
        end

        @(negedge clk);
        stall_ex = 1'b0;
        flush_ex = 1'b1; // Trigger branch misprediction flush

        @(posedge clk);
        #(1);
        if (id_ex_opcode !== 7'b0000000 || id_ex_rd !== 5'd0 ||
            id_ex_rs1_valid !== 1'b0    || id_ex_rs2_valid !== 1'b0) begin
            $display("[FAIL] Flush failed to inject NOP bubble or clear valids! Opcode: 0x%02h, rd: %0d, v1=%b, v2=%b",
                     id_ex_opcode, id_ex_rd, id_ex_rs1_valid, id_ex_rs2_valid);
            errors = errors + 1;
        end else begin
            $display("[PASS] Pipeline register successfully cleared to NOP bubble with zeroed valids on flush_ex!");
        end

        #(CLK_PERIOD * 5);
        $display("\n=======================================================================================================");
        if (errors == 0)
            $display("   DAY 81 RISC-V ID STAGE VERIFICATION SUCCESSFUL: 0 ERRORS DETECTED! (PASSED)");
        else
            $display("   VERIFICATION FAILED WITH %0d ERROR(S)!", errors);
        $display("=======================================================================================================\n");

        $finish;
    end

endmodule

Day 081/dump.vcd
$date
	Sat Sep 26 13:21:58 2026
$end
$version
	Icarus Verilog
$end
$timescale
	1ps
$end
$scope module tb_riscv_id_stage $end
$var wire 1 ! id_rs2_valid $end
$var wire 5 " id_rs2 [4:0] $end
$var wire 1 # id_rs1_valid $end
$var wire 5 $ id_rs1 [4:0] $end
$var wire 1 % id_ex_rs2_valid $end
$var wire 5 & id_ex_rs2 [4:0] $end
$var wire 1 ' id_ex_rs1_valid $end
$var wire 5 ( id_ex_rs1 [4:0] $end
$var wire 32 ) id_ex_rdata2 [31:0] $end
$var wire 32 * id_ex_rdata1 [31:0] $end
$var wire 5 + id_ex_rd [4:0] $end
$var wire 32 , id_ex_pc_plus_4 [31:0] $end
$var wire 32 - id_ex_pc [31:0] $end
$var wire 7 . id_ex_opcode [6:0] $end
$var wire 32 / id_ex_imm [31:0] $end
$var wire 7 0 id_ex_funct7 [6:0] $end
$var wire 3 1 id_ex_funct3 [2:0] $end
$var parameter 32 2 CLK_PERIOD $end
$var reg 1 3 clk $end
$var reg 1 4 flush_ex $end
$var reg 32 5 if_id_instr [31:0] $end
$var reg 32 6 if_id_pc [31:0] $end
$var reg 32 7 if_id_pc_plus_4 [31:0] $end
$var reg 1 8 nreset $end
$var reg 1 9 stall_ex $end
$var reg 5 : wb_rd [4:0] $end
$var reg 1 ; wb_reg_write $end
$var reg 32 < wb_wdata [31:0] $end
$var integer 32 = errors [31:0] $end
$scope module uut $end
$var wire 1 3 clk $end
$var wire 1 4 flush_ex $end
$var wire 5 > id_rs1 [4:0] $end
$var wire 1 # id_rs1_valid $end
$var wire 5 ? id_rs2 [4:0] $end
$var wire 1 ! id_rs2_valid $end
$var wire 32 @ if_id_instr [31:0] $end
$var wire 32 A if_id_pc [31:0] $end
$var wire 32 B if_id_pc_plus_4 [31:0] $end
$var wire 1 8 nreset $end
$var wire 1 9 stall_ex $end
$var wire 5 C wb_rd [4:0] $end
$var wire 1 ; wb_reg_write $end
$var wire 32 D wb_wdata [31:0] $end
$var wire 5 E raw_rs2 [4:0] $end
$var wire 5 F raw_rs1 [4:0] $end
$var wire 5 G raw_rd [4:0] $end
$var wire 7 H raw_opcode [6:0] $end
$var wire 7 I raw_funct7 [6:0] $end
$var wire 3 J raw_funct3 [2:0] $end
$var wire 32 K id_rdata2 [31:0] $end
$var wire 32 L id_rdata1 [31:0] $end
$var wire 32 M id_imm [31:0] $end
$var parameter 32 N NOP_INSTRUCTION $end
$var reg 3 O id_ex_funct3 [2:0] $end
$var reg 7 P id_ex_funct7 [6:0] $end
$var reg 32 Q id_ex_imm [31:0] $end
$var reg 7 R id_ex_opcode [6:0] $end
$var reg 32 S id_ex_pc [31:0] $end
$var reg 32 T id_ex_pc_plus_4 [31:0] $end
$var reg 5 U id_ex_rd [4:0] $end
$var reg 32 V id_ex_rdata1 [31:0] $end
$var reg 32 W id_ex_rdata2 [31:0] $end
$var reg 5 X id_ex_rs1 [4:0] $end
$var reg 1 ' id_ex_rs1_valid $end
$var reg 5 Y id_ex_rs2 [4:0] $end
$var reg 1 % id_ex_rs2_valid $end
$var reg 1 Z rs1_valid $end
$var reg 1 [ rs2_valid $end
$scope module u_imm_gen $end
$var wire 32 \ instr [31:0] $end
$var wire 7 ] opcode [6:0] $end
$var parameter 7 ^ OPC_AUIPC $end
$var parameter 7 _ OPC_BRANCH $end
$var parameter 7 ` OPC_JAL $end
$var parameter 7 a OPC_JALR $end
$var parameter 7 b OPC_LOAD $end
$var parameter 7 c OPC_LUI $end
$var parameter 7 d OPC_OP_IMM $end
$var parameter 7 e OPC_STORE $end
$var reg 32 f imm [31:0] $end
$upscope $end
$scope module u_regfile $end
$var wire 1 3 clk $end
$var wire 5 g rd [4:0] $end
$var wire 1 ; reg_write $end
$var wire 5 h rs1 [4:0] $end
$var wire 5 i rs2 [4:0] $end
$var wire 32 j w_data [31:0] $end
$var wire 32 k rdata2 [31:0] $end
$var wire 32 l rdata1 [31:0] $end
$var integer 32 m i [31:0] $end
$upscope $end
$upscope $end
$upscope $end
$enddefinitions $end
$comment Show the parameter values. $end
$dumpall
b100011 e
b10011 d
b110111 c
b11 b
b1100111 a
b1101111 `
b1100011 _
b10111 ^
b10011 N
b1010 2
$end
#0
$dumpvars
b100000 m
b0 l
b0 k
b0 j
b0 i
b0 h
b0 g
b0 f
b0 ]
b0 \
0[
0Z
b0 Y
b0 X
b0 W
b0 V
b0 U
b0 T
b0 S
b0 R
b0 Q
b0 P
b0 O
b0 M
b0 L
b0 K
b0 J
b0 I
b0 H
b0 G
b0 F
b0 E
b0 D
b0 C
b100 B
b0 A
b0 @
b0 ?
b0 >
b0 =
b0 <
0;
b0 :
09
08
b100 7
b0 6
b0 5
04
03
b0 1
b0 0
b0 /
b0 .
b0 -
b0 ,
b0 +
b0 *
b0 )
b0 (
0'
b0 &
0%
b0 $
0#
b0 "
0!
$end
#5000
13
#10000
03
#15000
13
#20000
03
#25000
13
#30000
18
03
#35000
b100 ,
b100 T
13
#40000
b11011110101011011011111011101111 <
b11011110101011011011111011101111 D
b11011110101011011011111011101111 j
b101 :
b101 C
b101 g
1;
03
#45000
13
#50000
b11001010111111101011101010111110 <
b11001010111111101011101010111110 D
b11001010111111101011101010111110 j
b0 :
b0 C
b0 g
03
#55000
13
#60000
b11011110101011011011111011101111 L
b11011110101011011011111011101111 l
1#
1Z
b110011 H
b110 G
b101 $
b101 >
b101 F
b101 h
b110011 ]
b101000001100110011 5
b101000001100110011 @
b101000001100110011 \
0;
03
#65000
b110011 .
b110011 R
b110 +
b110 U
1'
b101 (
b101 X
b11011110101011011011111011101111 *
b11011110101011011011111011101111 V
13
#70000
b10100101101001010101101001011010 L
b10100101101001010101101001011010 l
b1 G
b1010 $
b1010 >
b1010 F
b1010 h
b1010000000010110011 5
b1010000000010110011 @
b1010000000010110011 \
b10100101101001010101101001011010 <
b10100101101001010101101001011010 D
b10100101101001010101101001011010 j
b1010 :
b1010 C
b1010 g
1;
03
#75000
b1 +
b1 U
b1010 (
b1010 X
b10100101101001010101101001011010 *
b10100101101001010101101001011010 V
13
#76000
0;
#80000
b0 L
b0 l
b10011 H
b10 $
b10 >
b10 F
b10 h
b110 "
b110 ?
b110 E
b110 i
b1111101 I
b11111111111111111111111110100110 M
b11111111111111111111111110100110 f
b10011 ]
b11111010011000010000000010010011 5
b11111010011000010000000010010011 @
b11111010011000010000000010010011 \
03
#85000
b10011 .
b10011 R
b1111101 0
b1111101 P
b110 &
b110 Y
b10 (
b10 X
b11111111111111111111111110100110 /
b11111111111111111111111110100110 Q
b0 *
b0 V
13
#90000
b11011110101011011011111011101111 K
b11011110101011011011111011101111 k
1!
1[
b100011 H
b11000 G
b10 J
b101 "
b101 ?
b101 E
b101 i
b1111111 I
b11111111111111111111111111111000 M
b11111111111111111111111111111000 f
b100011 ]
b11111110010100010010110000100011 5
b11111110010100010010110000100011 @
b11111110010100010010110000100011 \
03
#95000
b100011 .
b100011 R
b1111111 0
b1111111 P
b10 1
b10 O
b11000 +
b11000 U
1%
b101 &
b101 Y
b11111111111111111111111111111000 /
b11111111111111111111111111111000 Q
b11011110101011011011111011101111 )
b11011110101011011011111011101111 W
13
#100000
b0 K
b0 k
b1100011 H
b10001 G
b0 J
b1 $
b1 >
b1 F
b1 h
b10 "
b10 ?
b10 E
b10 i
b11111111111111111111111111110000 M
b11111111111111111111111111110000 f
b1100011 ]
b11111110001000001000100011100011 5
b11111110001000001000100011100011 @
b11111110001000001000100011100011 \
03
#105000
b1100011 .
b1100011 R
b0 1
b0 O
b10001 +
b10001 U
b10 &
b10 Y
b1 (
b1 X
b11111111111111111111111111110000 /
b11111111111111111111111111110000 Q
b0 )
b0 W
13
#110000
0!
0[
0#
0Z
b110111 H
b11 G
b101 J
b1000 $
b1000 >
b1000 F
b1000 h
b11 "
b11 ?
b11 E
b11 i
b1001 I
b10010001101000101000000000000 M
b10010001101000101000000000000 f
b110111 ]
b10010001101000101000110110111 5
b10010001101000101000110110111 @
b10010001101000101000110110111 \
03
#115000
b110111 .
b110111 R
b1001 0
b1001 P
b101 1
b101 O
b11 +
b11 U
0%
0'
b11 &
b11 Y
b1000 (
b1000 X
b10010001101000101000000000000 /
b10010001101000101000000000000 Q
13
#120000
b1101111 H
b1 G
b111 J
b11111 $
b11111 >
b11111 F
b11111 h
b1 "
b1 ?
b1 E
b1 i
b1000000 I
b11111111111111111111100000000000 M
b11111111111111111111100000000000 f
b1101111 ]
b10000000000111111111000011101111 5
b10000000000111111111000011101111 @
b10000000000111111111000011101111 \
03
#125000
b1101111 .
b1101111 R
b1000000 0
b1000000 P
b111 1
b111 O
b1 +
b1 U
b1 &
b1 Y
b11111 (
b11111 X
b11111111111111111111100000000000 /
b11111111111111111111100000000000 Q
13
#130000
1!
1[
1#
1Z
b110011 H
b0 J
b10 $
b10 >
b10 F
b10 h
b11 "
b11 ?
b11 E
b11 i
b0 I
b0 M
b0 f
b110011 ]
b1100010000000010110011 5
b1100010000000010110011 @
b1100010000000010110011 \
19
03
#135000
13
#140000
14
09
03
#145000
b0 .
b0 R
b0 0
b0 P
b0 1
b0 O
b0 +
b0 U
b0 &
b0 Y
b0 (
b0 X
b0 /
b0 Q
b0 ,
b0 T
13
